Workbook
Name PRINT_TITLES_MI: 'ISS10102'!$4:$9

Sheet Bi-monthly net issuance
A2: Auction no. | B2: Date | C2: Issues (billions of UgShs.) a/ | D2: Paper | E2: Paper | F2: Maturities (billions of UgShs.) b/ | G2: Net Issuance
B3: 37776 | E3: 273 | F3: 7000000000
E4: 182 | F4: 6000000000
E5: 91 | F5: 4000000000
F7: =SUM(F3:F6) -> 17000000000
A9: 561 | B9: 37783 | C9: 10000000000 | D9: 91 | E9: 364 | F9: 13000000000
A10: , | C10: 12000000000 | D10: 182 | E10: 273 | F10: 7999800000
C11: 18000000000 | D11: 273 | E11: 182 | F11: 5999800000
C12: 25000000000 | D12: 364
C13: =SUM(C9:C12) -> 65000000000 | F13: =SUM(F9:F12) -> 26999600000
G14: =+C13-F13-F7 -> 21000400000
B15: =+B9+7 -> 37790 | E15: 364 | F15: 13000000000
E16: 273 | F16: 9000000000
E17: 182 | F17: 6000000000
E18: 91 | F18: 12000000000
F20: =SUM(F15:F19) -> 40000000000
A22: 562 | B22: 37797 | C22: 8000000000 | D22: 91 | E22: 364 | F22: 11999900000
C23: 13999900000 | D23: 182 | E23: 273 | F23: 10000000000
C24: 21000000000 | D24: 273 | E24: 182 | F24: 2969000000
C25: 28999900000 | D25: 364
C26: =SUM(C22:C25) -> 71999800000 | F26: =SUM(F22:F25) -> 24968900000
G27: =+C26-F26-F20 -> 7030900000
B28: 37804 | E28: 364 | F28: 12000000000
E29: 273 | F29: 8999900000
E30: 182 | F30: 2635700000
E31: 91 | F31: 5000000000
F33: =SUM(F28:F32) -> 28635600000
A35: 563 | B35: 37811 | C35: 10000000000 | D35: 91 | E35: 364 | F35: 10000000000
C36: 14999900000 | D36: 182 | E36: 182 | F36: 4000000000
C37: 25000000000 | D37: 273 | E37: 273 | F37: 8000000000
C38: 30000000000 | D38: 364
C39: =SUM(C35:C38) -> 79999900000 | F39: =SUM(F35:F38) -> 22000000000
G40: =+C39-F39-F33 -> 29364300000
B41: 37818 | E41: 364 | F41: 14000000000
E42: 273 | F42: 8000000000
E43: 182 | F43: 3500000000
E44: 91 | F44: 6291200000
F46: =SUM(F41:F45) -> 31791200000
A48: 564 | B48: 37825 | C48: 7000000000 | D48: 91 | E48: 364 | F48: 14000000000
C49: 12999800000 | D49: 182 | E49: 273 | F49: 10000000000
C50: 21000000000 | D50: 273 | E50: 182 | F50: 3000000000
C51: 28999900000 | D51: 364
C52: =SUM(C48:C51) -> 69999700000 | F52: =SUM(F48:F51) -> 27000000000
G53: =+C52-F52-F46 -> 11208500000
B54: 37832 | E54: 364 | F54: 16000000000
E55: 273 | F55: 6000000000
E56: 182 | F56: 2000000000
E57: 91 | F57: 7000000000
F59: =SUM(F54:F58) -> 31000000000
A61: 565 | B61: 37839 | C61: 4999900000 | D61: 91 | E61: 364 | F61: 10000000000
C62: 10000000000 | D62: 182 | E62: 273 | F62: 7000000000
C63: 17000000000 | D63: 273 | E63: 182 | F63: 2000000000
C64: 27999900000 | D64: 364
C65: =SUM(C61:C64) -> 59999800000 | F65: =SUM(F61:F64) -> 19000000000
G66: =+C65-F65-F59 -> 9999800000
B67: 37846 | E67: 364 | F67: 11000000000
E68: 273 | F68: 7000000000
E69: 91 | F69: 8000000000
F71: =SUM(F67:F70) -> 26000000000
A73: 566 | B73: 37853 | C73: 7000000000 | D73: 91 | E73: 364 | F73: 11999900000
C74: 15000000000 | D74: 182 | E74: 273 | F74: 9000000000
C75: 22999900000 | D75: 273 | E75: 182 | F75: 5000000000
C76: 30000000000 | D76: 364
C77: =SUM(C73:C76) -> 74999900000 | F77: =SUM(F73:F76) -> 25999900000
G78: =+C77-F77-F71 -> 23000000000
B79: 37860 | E79: 364 | F79: 12999900000
E80: 273 | F80: 8000000000
E81: 91 | F81: 8000000000
F83: =SUM(F79:F82) -> 28999900000
A85: 567 | B85: 37867 | C85: 9999900000 | D85: 91 | E85: 364 | F85: 14000000000
C86: 15000000000 | D86: 182 | E86: 273 | F86: 8000000000
C87: 20000000000 | D87: 273 | E87: 182 | F87: 5000000000
C88: 35000000000 | D88: 364
C89: =SUM(C85:C88) -> 79999900000 | F89: =SUM(F85:F88) -> 27000000000
G90: =+C89-F89-F83 -> 24000000000
B91: 37874 | E91: 364 | F91: 15000000000
E92: 273 | F92: 8000000000
E93: 91 | F93: 10000000000
F95: =SUM(F91:F94) -> 33000000000
A97: 568 | B97: 37881 | C97: 15000000000 | D97: 91 | E97: 364 | F97: 16499900000
C98: 16754000000 | D98: 182 | E98: 273 | F98: 7999900000
C99: 21999900000 | D99: 273 | E99: 182 | F99: 13000000000
C100: 36000000000 | D100: 364
C101: =SUM(C97:C100) -> 89753900000 | F101: =SUM(F97:F100) -> 37499800000
G102: =+C101-F101-F95 -> 19254100000
B103: 37888 | E103: 364 | F103: 18499900000
E104: 273 | F104: 7587000000
E105: 91 | F105: 8000000000
F107: =SUM(F103:F106) -> 34086900000
A109: 569 | B109: 37895 | C109: 15000000000 | D109: 91 | E109: 273 | F109: 6000000000
C110: 16999800000 | D110: 182 | E110: 364 | F110: 13999800000
C111: 22000000000 | D111: 273
C112: 35999900000 | D112: 364
C113: =SUM(C109:C112) -> 89999700000 | F113: =SUM(F109:F111) -> 19999800000
G114: =+C113-F113-F107 -> 35913000000
B115: 37902 | E115: 91 | F115: 10000000000
E116: 273 | F116: 5000000000
E117: 364 | F117: 15000000000
F119: =SUM(F115:F118) -> 30000000000
A121: 570 | B121: 37909 | C121: 8000000000 | D121: 91 | E121: 182 | F121: 6000000000
...

Sheet ISS10102
A2: Ref:ISS0001. WK3
A3: worksheet a
A4: - | B4: - | D4: - | E4: - | F4: - | G4: - | H4: - | I4: - | J4: - | K4: - | L4: - | M4: - | N4: - | O4: - | P4: - | Q4: -
A5: Auction | B5: Issue date | D5: Amount offered | E5: Total bids | F5: Over/(Under) | G5: Face Value of | H5: Cost Value | I5: Interest due | J5: Date due | K5: Duration | L5: Implicit annual | M5: Clearing | N5: Lowest | O5: Weighted | P5: Average | Q5: Annualised
A6: No | D6: in | E6: (Competitive & | F6: Subscribed | G6: issues | L6: interest rate | M6: factor | N6: factor | O6: Average | P6: Discount | Q6: yield
D7: Auction | E7: Uncompetitive) | M7: (%) | N7: (%) | O7: Price | P7: factor
B8: (1) | D8: (1a) | E8: (1b) | G8: (2) | H8: (3) | I8: (4) | J8: (5) | K8: (6) | L8: (9) | M8: (10) | N8: (11) | O8: (12) | P8: (13)
A9: - | B9: - | D9: - | E9: - | F9: - | G9: - | H9: - | I9: - | J9: - | K9: - | L9: - | M9: - | N9: - | O9: - | P9: - | Q9: -
A11: 469 | B11: 37076 | D11: 1500000000 | E11: 2402100000 | F11: =E11-D11 -> 902100000 | G11: 1500000000 | H11: 1473850685 | I11: =G11-H11 -> 26149315 | J11: =B11+K11 -> 37167 | K11: 91 | N11: 4.412 | O11: =H11/G11*100 -> 98.256712 | P11: =(100-O11)/100*(365/91)*100 -> 6.9923077 | Q11: =((100-O11)/O11*(365/91))*100 -> 7.1163664
D12: 1500000000 | E12: 2670000000 | F12: =E12-D12 -> 1170000000 | G12: 1500000000 | H12: 1440153500 | I12: =G12-H12 -> 59846500 | J12: =B11+K12+1 -> 37259 | K12: 182 | N12: 7.621 | O12: =H12/G12*100 -> 96.010233 | P12: =(100-O12)/100*(365/182)*100 -> 8.0014551 | Q12: =((100-O12)/O12*(365/182))*100 -> 8.3339607
D13: 4000000000 | E13: 5477000000 | F13: =E13-D13 -> 1477000000 | G13: 4000000000 | H13: 3698699840 | I13: =G13-H13 -> 301300160 | J13: =B11+K13+1 -> 37350 | K13: 273 | N13: 9.426 | O13: =H13/G13*100 -> 92.467496 | P13: =(100-O13)/100*(365/273)*100 -> 10.07093 | Q13: =((100-O13)/O13*(365/273))*100 -> 10.891319
D14: 5000000000 | E14: 6412000000 | F14: =E14-D14 -> 1412000000 | G14: 5000000000 | H14: 4459772680 | I14: =G14-H14 -> 540227320 | J14: =B11+K14+1 -> 37441 | K14: 364 | N14: 10.123 | O14: =H14/G14*100 -> 89.195454 | P14: =(100-O14)/100*(365/364)*100 -> 10.834229 | Q14: =((100-O14)/O14*(365/364))*100 -> 12.146616
A16: =A11+1 -> 470 | B16: =B11+7 -> 37083 | D16: 2000000000 | E16: 6763900000 | F16: =E16-D16 -> 4763900000 | G16: 2000000000 | H16: 1966357750 | I16: =G16-H16 -> 33642250 | J16: =B16+K16 -> 37174 | K16: 91 | N16: 6 | O16: =H16/G16*100 -> 98.317887 | P16: =(100-O16)/100*(365/91)*100 -> 6.7469348 | Q16: =((100-O16)/O16*(365/91))*100 -> 6.8623675
D17: 2000000000 | E17: 2030000000 | F17: =E17-D17 -> 30000000 | G17: 2000000000 | H17: 1895843600 | I17: =G17-H17 -> 104156400 | J17: =B16+K17+1 -> 37266 | K17: 182 | N17: 7.85 | O17: =H17/G17*100 -> 94.79218 | P17: =(100-O17)/100*(365/182)*100 -> 10.444254 | Q17: =((100-O17)/O17*(365/182))*100 -> 11.018055
D18: 5000000000 | E18: 5000000000 | F18: =E18-D18 -> 0 | G18: 5000000000 | H18: 4570702500 | I18: =G18-H18 -> 429297500 | J18: =B16+K18+1 -> 37357 | K18: 273 | N18: 10.629 | O18: =H18/G18*100 -> 91.41405 | P18: =(100-O18)/100*(365/273)*100 -> 11.479384 | Q18: =((100-O18)/O18*(365/273))*100 -> 12.55757
D19: 7000000000 | E19: 7000000000 | F19: =E19-D19 -> 0 | G19: 7000000000 | H19: 6220102016 | I19: =G19-H19 -> 779897984 | J19: =B16+K19+1 -> 37448 | K19: 364 | N19: 9.916 | O19: =H19/G19*100 -> 88.8586 | P19: =(100-O19)/100*(365/364)*100 -> 11.172008 | Q19: =((100-O19)/O19*(365/364))*100 -> 12.572793
A21: =A16+1 -> 471 | B21: =B16+7 -> 37090 | D21: 2000000000 | E21: 3562000000 | F21: =E21-D21 -> 1562000000 | G21: 2000000000 | H21: 1964154360 | I21: =G21-H21 -> 35845640 | J21: =B21+K21 -> 37181 | K21: 91 | N21: 6.746 | O21: =H21/G21*100 -> 98.207718 | P21: =(100-O21)/100*(365/91)*100 -> 7.1888234 | Q21: =((100-O21)/O21*(365/91))*100 -> 7.3200188
D22: 2000000000 | E22: 3088900000 | F22: =E22-D22 -> 1088900000 | G22: 2000000000 | H22: 1878252919 | I22: =G22-H22 -> 121747081 | J22: =B21+K22+1 -> 37273 | K22: 182 | N22: 11.03 | O22: =H22/G22*100 -> 93.912646 | P22: =(100-O22)/100*(365/182)*100 -> 12.208155 | Q22: =((100-O22)/O22*(365/182))*100 -> 12.999479
D23: 5000000000 | E23: 5000000000 | F23: =E23-D23 -> 0 | G23: 5000000000 | H23: 4483755000 | I23: =G23-H23 -> 516245000 | J23: =B21+K23+1 -> 37364 | K23: 273 | N23: 11.848 | O23: =H23/G23*100 -> 89.6751 | P23: =(100-O23)/100*(365/273)*100 -> 13.804353 | Q23: =((100-O23)/O23*(365/273))*100 -> 15.393742
D24: 7000000000 | E24: 7000000000 | F24: =E24-D24 -> 0 | G24: 7000000000 | H24: 6001002268 | I24: =G24-H24 -> 998997732 | J24: =B21+K24+1 -> 37455 | K24: 364 | N24: 11 | O24: =H24/G24*100 -> 85.728604 | P24: =(100-O24)/100*(365/364)*100 -> 14.310603 | Q24: =((100-O24)/O24*(365/364))*100 -> 16.692915
A26: =A21+1 -> 472 | B26: =B21+7 -> 37097 | D26: 3000000000 | E26: 3034500000 | F26: =E26-D26 -> 34500000 | G26: 3000000000 | H26: 2920291115 | I26: =G26-H26 -> 79708885 | J26: =B26+K26 -> 37188 | K26: 91 | N26: 7.019 | O26: =H26/G26*100 -> 97.343037 | P26: =(100-O26)/100*(365/91)*100 -> 10.657049 | Q26: =((100-O26)/O26*(365/91))*100 -> 10.947931
D27: 4000000000 | E27: 4000000000 | F27: =E27-D27 -> 0 | G27: 4000000000 | H27: 3676427332 | I27: =G27-H27 -> 323572668 | J27: =B26+K27+1 -> 37280 | K27: 182 | N27: 9.999 | O27: =H27/G27*100 -> 91.910683 | P27: =(100-O27)/100*(365/182)*100 -> 16.22308 | Q27: =((100-O27)/O27*(365/182))*100 -> 17.650919
D28: 5000000000 | E28: 5000000000 | F28: =E28-D28 -> 0 | G28: 5000000000 | H28: 4265972900 | I28: =G28-H28 -> 734027100 | J28: =B26+K28+1 -> 37371 | K28: 273 | N28: 12 | O28: =H28/G28*100 -> 85.319458 | P28: =(100-O28)/100*(365/273)*100 -> 19.627831 | Q28: =((100-O28)/O28*(365/273))*100 -> 23.005105
D29: 7000000000 | E29: 7000000000 | F29: =E29-D29 -> 0 | G29: 7000000000 | H29: 5421688900 | I29: =G29-H29 -> 1578311100 | J29: =B26+K29+1 -> 37462 | K29: 364 | N29: 16.713 | O29: =H29/G29*100 -> 77.452699 | P29: =(100-O29)/100*(365/364)*100 -> 22.609245 | Q29: =((100-O29)/O29*(365/364))*100 -> 29.191035
B31: TOTAL JULY 2001 | D31: =SUM(D11:D29) -> 63000000000 | E31: =SUM(E11:E29) -> 75440400000 | F31: =SUM(F11:F29) -> 12440400000 | G31: =SUM(G11:G29) -> 63000000000 | H31: =SUM(H11:H29) -> 56337027365 | I31: =SUM(I11:I29) -> 6662972635 | L31: Monthly Average of 91 day bill rate | O31: =AVERAGEA(O11,O16,O21,O26) -> 98.031339 | P31: =AVERAGEA(P11,P16,P21,P26) -> 7.8962786
L32: Monthly Average of 182 day bill rate | O32: =AVERAGEA(O12,O17,O22,O27) -> 94.156436 | P32: =AVERAGEA(P12,P17,P22,P27) -> 11.719236
L33: Monthly Average of 273 day bill rate | O33: =AVERAGEA(O13,O18,O23,O28) -> 89.719026 | P33: =AVERAGEA(P13,P18,P23,P28) -> 13.745625
L34: Monthly Average of 364 day bill rate | O34: =AVERAGEA(O14,O19,O24,O29) -> 85.308839 | P34: =AVERAGEA(P14,P19,P24,P29) -> 14.731521
A36: =A26+1 -> 473 | B36: =B26+7 -> 37104 | D36: 3000000000 | E36: 3000000000 | F36: =E36-D36 -> 0 | G36: 3000000000 | H36: 2899532650 | I36: =G36-H36 -> 100467350 | J36: =B36+K36 -> 37195 | K36: 91 | N36: 9.001 | O36: =H36/G36*100 -> 96.651088 | P36: =(100-O36)/100*(365/91)*100 -> 13.432448 | Q36: =((100-O36)/O36*(365/91))*100 -> 13.897875
D37: 4000000000 | E37: 8279400000 | F37: =E37-D37 -> 4279400000 | G37: 4000000000 | H37: 3670506802 | I37: =G37-H37 -> 329493198 | J37: =B36+K37+1 -> 37287 | K37: 182 | N37: 13.116 | O37: =H37/G37*100 -> 91.76267 | P37: =(100-O37)/100*(365/182)*100 -> 16.51992 | Q37: =((100-O37)/O37*(365/182))*100 -> 18.002876
D38: 4000000000 | E38: 10723700000 | F38: =E38-D38 -> 6723700000 | G38: 3999900000 | H38: 3411615570 | I38: =G38-H38 -> 588284430 | J38: =B36+K38+1 -> 37378 | K38: 273 | N38: 17.381 | O38: =H38/G38*100 -> 85.292522 | P38: =(100-O38)/100*(365/273)*100 -> 19.663845 | Q38: =((100-O38)/O38*(365/273))*100 -> 23.054594
D39: 5000000000 | E39: 15353400000 | F39: =E39-D39 -> 10353400000 | G39: 5000000000 | H39: 4012973427 | I39: =G39-H39 -> 987026573 | J39: =B36+K39+1 -> 37469 | K39: 364 | N39: 15.041 | O39: =H39/G39*100 -> 80.259469 | P39: =(100-O39)/100*(365/364)*100 -> 19.794764 | Q39: =((100-O39)/O39*(365/364))*100 -> 24.663462
A41: =A36+1 -> 474 | B41: =B36+7 -> 37111 | D41: 3000000000 | E41: 4969200000 | F41: =E41-D41 -> 1969200000 | G41: 3000000000 | H41: 2895219779 | I41: =G41-H41 -> 104780221 | J41: =B41+K41 -> 37202 | K41: 91 | N41: 12.001 | O41: =H41/G41*100 -> 96.507326 | P41: =(100-O41)/100*(365/91)*100 -> 14.009077 | Q41: =((100-O41)/O41*(365/91))*100 -> 14.516076
D42: 4000000000 | E42: 6417600000 | F42: =E42-D42 -> 2417600000 | G42: 4000000000 | H42: 3670675212 | I42: =G42-H42 -> 329324788 | J42: =B41+K42+1 -> 37294 | K42: 182 | N42: 14.038 | O42: =H42/G42*100 -> 91.76688 | P42: =(100-O42)/100*(365/182)*100 -> 16.511476 | Q42: =((100-O42)/O42*(365/182))*100 -> 17.992849
D43: 6000000000 | E43: 10552200000 | F43: =E43-D43 -> 4552200000 | G43: 6000000000 | H43: 5070862258 | I43: =G43-H43 -> 929137742 | J43: =B41+K43+1 -> 37385 | K43: 273 | N43: 18 | O43: =H43/G43*100 -> 84.514371 | P43: =(100-O43)/100*(365/273)*100 -> 20.704229 | Q43: =((100-O43)/O43*(365/273))*100 -> 24.49788
D44: 7000000000 | E44: 15452500000 | F44: =E44-D44 -> 8452500000 | G44: 7000000000 | H44: 5594245390 | I44: =G44-H44 -> 1405754610 | J44: =B41+K44+1 -> 37476 | K44: 364 | N44: 18 | O44: =H44/G44*100 -> 79.917791 | P44: =(100-O44)/100*(365/364)*100 -> 20.13738 | Q44: =((100-O44)/O44*(365/364))*100 -> 25.197618
A46: =A41+1 -> 475 | B46: =B41+7 -> 37118 | D46: 3000000000 | E46: 8552600000 | F46: =E46-D46 -> 5552600000 | G46: 3000000000 | H46: 2897370000 | I46: =G46-H46 -> 102630000 | J46: =B46+K46 -> 37209 | K46: 91 | N46: 10.998 | O46: =H46/G46*100 -> 96.579 | P46: =(100-O46)/100*(365/91)*100 -> 13.721593 | Q46: =((100-O46)/O46*(365/91))*100 -> 14.207637
D47: 4000000000 | E47: 9595200000 | F47: =E47-D47 -> 5595200000 | G47: 4000000000 | H47: 3683572728 | I47: =G47-H47 -> 316427272 | J47: =B46+K47+1 -> 37301 | K47: 182 | N47: 15.673 | O47: =H47/G47*100 -> 92.089318 | P47: =(100-O47)/100*(365/182)*100 -> 15.864829 | Q47: =((100-O47)/O47*(365/182))*100 -> 17.227654
D48: 5000000000 | E48: 9401000000 | F48: =E48-D48 -> 4401000000 | G48: 5000000000 | H48: 4213782060 | I48: =G48-H48 -> 786217940 | J48: =B46+K48+1 -> 37392 | K48: 273 | N48: 18.918 | O48: =H48/G48*100 -> 84.275641 | P48: =(100-O48)/100*(365/273)*100 -> 21.02341 | Q48: =((100-O48)/O48*(365/273))*100 -> 24.94601
D49: 8000000000 | E49: 11284200000 | F49: =E49-D49 -> 3284200000 | G49: 8000000000 | H49: 6279888734 | I49: =G49-H49 -> 1720111266 | J49: =B46+K49+1 -> 37483 | K49: 364 | N49: 17.047 | O49: =H49/G49*100 -> 78.498609 | P49: =(100-O49)/100*(365/364)*100 -> 21.560461 | Q49: =((100-O49)/O49*(365/364))*100 -> 27.466042
A51: =A46+1 -> 476 | B51: =B46+7 -> 37125 | D51: 3000000000 | E51: 6090200000 | F51: =E51-D51 -> 3090200000 | G51: 3000000000 | H51: 2897927590 | I51: =G51-H51 -> 102072410 | J51: =B51+K51 -> 37216 | K51: 91 | N51: 12.234 | O51: =H51/G51*100 -> 96.597586 | P51: =(100-O51)/100*(365/91)*100 -> 13.647044 | Q51: =((100-O51)/O51*(365/91))*100 -> 14.127728
D52: 4000000000 | E52: 7640300000 | F52: =E52-D52 -> 3640300000 | G52: 4000000000 | H52: 3684876740 | I52: =G52-H52 -> 315123260 | J52: =B51+K52+1 -> 37308 | K52: 182 | N52: 14.941 | O52: =H52/G52*100 -> 92.121918 | P52: =(100-O52)/100*(365/182)*100 -> 15.799449 | Q52: =((100-O52)/O52*(365/182))*100 -> 17.150586
D53: 5000000000 | E53: 14861900000 | F53: =E53-D53 -> 9861900000 | G53: 4999900000 | H53: 4271361534 | I53: =G53-H53 -> 728538466 | J53: =B51+K53+1 -> 37399 | K53: 273 | N53: 17.381 | O53: =H53/G53*100 -> 85.428939 | P53: =(100-O53)/100*(365/273)*100 -> 19.481455 | Q53: =((100-O53)/O53*(365/273))*100 -> 22.80428
D54: 8000000000 | E54: 24842300000 | F54: =E54-D54 -> 16842300000 | G54: 8000000000 | H54: 6344013800 | I54: =G54-H54 -> 1655986200 | J54: =B51+K54+1 -> 37490 | K54: 364 | N54: 19.052 | O54: =H54/G54*100 -> 79.300173 | P54: =(100-O54)/100*(365/364)*100 -> 20.756695 | Q54: =((100-O54)/O54*(365/364))*100 -> 26.174842
A56: =A51+1 -> 477 | B56: =B51+7 -> 37132 | D56: 2000000000 | E56: 4022300000 | F56: =E56-D56 -> 2022300000 | G56: 2000000000 | H56: 1933101900 | I56: =G56-H56 -> 66898100 | J56: =B56+K56 -> 37223 | K56: 91 | N56: 12.001 | O56: =H56/G56*100 -> 96.655095 | P56: =(100-O56)/100*(365/91)*100 -> 13.416377 | Q56: =((100-O56)/O56*(365/91))*100 -> 13.880673
D57: 3000000000 | E57: 6817700000 | F57: =E57-D57 -> 3817700000 | G57: 3000000000 | H57: 2772024660 | I57: =G57-H57 -> 227975340 | J57: =B56+K57+1 -> 37315 | K57: 182 | N57: 14.379 | O57: =H57/G57*100 -> 92.400822 | P57: =(100-O57)/100*(365/182)*100 -> 15.24011 | Q57: =((100-O57)/O57*(365/182))*100 -> 16.493479
D58: 4000000000 | E58: 12127000000 | F58: =E58-D58 -> 8127000000 | G58: 3999900000 | H58: 3461414160 | I58: =G58-H58 -> 538485840 | J58: =B56+K58+1 -> 37406 | K58: 273 | N58: 17.515 | O58: =H58/G58*100 -> 86.537517 | P58: =(100-O58)/100*(365/273)*100 -> 17.99929 | Q58: =((100-O58)/O58*(365/273))*100 -> 20.799406
D59: 6000000000 | E59: 21190000000 | F59: =E59-D59 -> 15190000000 | G59: 6000000000 | H59: 4895849528 | I59: =G59-H59 -> 1104150472 | J59: =B56+K59+1 -> 37497 | K59: 364 | N59: 17 | O59: =H59/G59*100 -> 81.597492 | P59: =(100-O59)/100*(365/364)*100 -> 18.453064 | Q59: =((100-O59)/O59*(365/364))*100 -> 22.614744
B61: TOTAL AUG 2001 | D61: =SUM(D36:D59) -> 91000000000 | E61: =SUM(E36:E59) -> 211172700000 | F61: =SUM(F36:F59) -> 120172700000 | G61: =SUM(G36:G59) -> 90999700000 | H61: =SUM(H36:H59) -> 78560814522 | I61: =SUM(I36:I59) -> 12438885478 | L61: Monthly Average of 91 day bill rate | O61: =AVERAGEA(O36,O41,O46,O51,O56) -> 96.598019 | P61: =AVERAGEA(P36,P41,P46,P51,P56) -> 13.645308
L62: Monthly Average of 182 day bill rate | O62: =AVERAGEA(O37,O42,O47,O52,O57) -> 92.028322 | P62: =AVERAGEA(P37,P42,P47,P52,P57) -> 15.987157
L63: Monthly Average of 273 day bill rate | O63: =AVERAGEA(O38,O43,O48,O53,O58) -> 85.209798 | P63: =AVERAGEA(P38,P43,P48,P53,P58) -> 19.774446
L64: Monthly Average of 364 day bill rate | O64: =AVERAGEA(O39,O44,O49,O54,O59) -> 79.914707 | P64: =AVERAGEA(P39,P44,P49,P54,P59) -> 20.140473
A66: =A56+1 -> 478 | B66: 37139 | D66: 3000000000 | E66: 3000000000 | F66: =E66-D66 -> 0 | G66: 3000000000 | H66: 2902667373 | I66: =G66-H66 -> 97332627 | J66: =B66+K66 -> 37230 | K66: 91 | N66: 10.489 | O66: =H66/G66*100 -> 96.755579 | P66: =(100-O66)/100*(365/91)*100 -> 13.013337 | Q66: =((100-O66)/O66*(365/91))*100 -> 13.449702
D67: 4000000000 | E67: 4000000000 | F67: =E67-D67 -> 0 | G67: 4000000000 | H67: 3697377278 | I67: =G67-H67 -> 302622722 | J67: =B66+K67+1 -> 37322 | K67: 182 | N67: 14 | O67: =H67/G67*100 -> 92.434432 | P67: =(100-O67)/100*(365/182)*100 -> 15.172705 | Q67: =((100-O67)/O67*(365/182))*100 -> 16.41456
D68: 5000000000 | E68: 4999800000 | F68: =E68-D68 -> -200000 | G68: 4999800000 | H68: 4342526855 | I68: =G68-H68 -> 657273145 | J68: =B66+K68+1 -> 37413 | K68: 273 | N68: 17 | O68: =H68/G68*100 -> 86.854011 | P68: =(100-O68)/100*(365/273)*100 -> 17.576139 | Q68: =((100-O68)/O68*(365/273))*100 -> 20.236416
D69: 8000000000 | E69: 8000000000 | F69: =E69-D69 -> 0 | G69: 8000000000 | H69: 6605823681 | I69: =G69-H69 -> 1394176319 | J69: =B66+K69+1 -> 37504 | K69: 364 | N69: 16.044 | O69: =H69/G69*100 -> 82.572796 | P69: =(100-O69)/100*(365/364)*100 -> 17.475081 | Q69: =((100-O69)/O69*(365/364))*100 -> 21.163242
A71: =A66+1 -> 479 | B71: =B66+7 -> 37146 | D71: 3000000000 | E71: 7713300000 | F71: =E71-D71 -> 4713300000 | G71: 2999900000 | H71: 2910595503 | I71: =G71-H71 -> 89304497 | J71: =B71+K71 -> 37237 | K71: 91 | N71: 10.629 | O71: =H71/G71*100 -> 97.023084 | P71: =(100-O71)/100*(365/91)*100 -> 11.940377 | Q71: =((100-O71)/O71*(365/91))*100 -> 12.306738
D72: 4000000000 | E72: 10703100000 | F72: =E72-D72 -> 6703100000 | G72: 3999900000 | H72: 3719315125 | I72: =G72-H72 -> 280584875 | J72: =B71+K72+1 -> 37329 | K72: 182 | N72: 13 | O72: =H72/G72*100 -> 92.985203 | P72: =(100-O72)/100*(365/182)*100 -> 14.068137 | Q72: =((100-O72)/O72*(365/182))*100 -> 15.129437
D73: 5000000000 | E73: 16566000000 | F73: =E73-D73 -> 11566000000 | G73: 5000000000 | H73: 4397456245 | I73: =G73-H73 -> 602543755 | J73: =B71+K73+1 -> 37420 | K73: 273 | N73: 15.119 | O73: =H73/G73*100 -> 87.949125 | P73: =(100-O73)/100*(365/273)*100 -> 16.111976 | Q73: =((100-O73)/O73*(365/273))*100 -> 18.319655
D74: 8000000000 | E74: 22810600000 | F74: =E74-D74 -> 14810600000 | G74: 7999900000 | H74: 6714532035 | I74: =G74-H74 -> 1285367965 | J74: =B71+K74+1 -> 37511 | K74: 364 | N74: 15.296 | O74: =H74/G74*100 -> 83.9327 | P74: =(100-O74)/100*(365/364)*100 -> 16.111441 | Q74: =((100-O74)/O74*(365/364))*100 -> 19.195667
A76: =A71+1 -> 480 | B76: =B71+7 -> 37153 | D76: 3000000000 | E76: 6345200000 | F76: =E76-D76 -> 3345200000 | G76: 3000000000 | H76: 2914052620 | I76: =G76-H76 -> 85947380 | J76: =B76+K76 -> 37244 | K76: 91 | N76: 10.629 | O76: =H76/G76*100 -> 97.135087 | P76: =(100-O76)/100*(365/91)*100 -> 11.491133 | Q76: =((100-O76)/O76*(365/91))*100 -> 11.830054
D77: 4000000000 | E77: 6831500000 | F77: =E77-D77 -> 2831500000 | G77: 4000000000 | H77: 3719466530 | I77: =G77-H77 -> 280533470 | J77: =B76+K77+1 -> 37336 | K77: 182 | N77: 13 | O77: =H77/G77*100 -> 92.986663 | P77: =(100-O77)/100*(365/182)*100 -> 14.065208 | Q77: =((100-O77)/O77*(365/182))*100 -> 15.126049
D78: 5000000000 | E78: 12395200000 | F78: =E78-D78 -> 7395200000 | G78: 4999700000 | H78: 4432431555 | I78: =G78-H78 -> 567268445 | J78: =B76+K78+1 -> 37427 | K78: 273 | N78: 14.292 | O78: =H78/G78*100 -> 88.65395 | P78: =(100-O78)/100*(365/273)*100 -> 15.169627 | Q78: =((100-O78)/O78*(365/273))*100 -> 17.111056
D79: 8000000000 | E79: 18959200000 | F79: =E79-D79 -> 10959200000 | G79: 8000000000 | H79: 6823165425 | I79: =G79-H79 -> 1176834575 | J79: =B76+K79+1 -> 37518 | K79: 364 | N79: 14.165 | O79: =H79/G79*100 -> 85.289568 | P79: =(100-O79)/100*(365/364)*100 -> 14.750845 | Q79: =((100-O79)/O79*(365/364))*100 -> 17.295017
A81: =A76+1 -> 481 | B81: =B76+7 -> 37160 | D81: 2000000000 | E81: 3299500000 | F81: =E81-D81 -> 1299500000 | G81: 2000000000 | H81: 1941382978 | I81: =G81-H81 -> 58617022 | J81: =B81+K81 -> 37251 | K81: 91 | N81: 10.83 | O81: =H81/G81*100 -> 97.069149 | P81: =(100-O81)/100*(365/91)*100 -> 11.755612 | Q81: =((100-O81)/O81*(365/91))*100 -> 12.110554
D82: 3000000000 | E82: 7517600000 | F82: =E82-D82 -> 4517600000 | G82: 3000000000 | H82: 2804464804 | I82: =G82-H82 -> 195535196 | J82: =B81+K82+1 -> 37343 | K82: 182 | N82: 12.234 | O82: =H82/G82*100 -> 93.48216 | P82: =(100-O82)/100*(365/182)*100 -> 13.071492 | Q82: =((100-O82)/O82*(365/182))*100 -> 13.982873
D83: 4000000000 | E83: 11636000000 | F83: =E83-D83 -> 7636000000 | G83: 3999900000 | H83: 3584442625 | I83: =G83-H83 -> 415457375 | J83: =B81+K83+1 -> 37434 | K83: 273 | N83: 13.169 | O83: =H83/G83*100 -> 89.613306 | P83: =(100-O83)/100*(365/273)*100 -> 13.886972 | Q83: =((100-O83)/O83*(365/273))*100 -> 15.496551
D84: 8000000000 | E84: 14976600000 | F84: =E84-D84 -> 6976600000 | G84: 8000000000 | H84: 6884172060 | I84: =G84-H84 -> 1115827940 | J84: =B81+K84+1 -> 37525 | K84: 364 | N84: 13.136 | O84: =H84/G84*100 -> 86.052151 | P84: =(100-O84)/100*(365/364)*100 -> 13.986168 | Q84: =((100-O84)/O84*(365/364))*100 -> 16.25313
B86: TOTAL SEP 2001 | D86: =SUM(D66:D84) -> 77000000000 | E86: =SUM(E66:E84) -> 159753600000 | F86: =SUM(F66:F84) -> 82753600000 | G86: =SUM(G66:G84) -> 76999100000 | H86: =SUM(H66:H84) -> 68393872692 | I86: =SUM(I66:I84) -> 8605227308 | L86: Monthly Average of 91 day bill rate | O86: =AVERAGEA(O66,O71,O76,O81) -> 96.995725 | P86: =AVERAGEA(P66,P71,P76,P81) -> 12.050114 | Q86: =AVERAGEA(Q66,Q71,Q76,Q81) -> 12.424262
L87: Monthly Average of 182 day bill rate | O87: =AVERAGEA(O67,O72,O77,O82) -> 92.972115 | P87: =AVERAGEA(P67,P72,P77,P82) -> 14.094386 | Q87: =AVERAGEA(Q67,Q72,Q77,Q82) -> 15.16323
L88: Monthly Average of 273 day bill rate | O88: =AVERAGEA(O68,O73,O78,O83) -> 88.267598 | P88: =AVERAGEA(P68,P73,P78,P83) -> 15.686178 | Q88: =AVERAGEA(Q68,Q73,Q78,Q83) -> 17.790919
L89: Monthly Average of 364 day bill rate | O89: =AVERAGEA(O69,O74,O79,O84) -> 84.461804 | P89: =AVERAGEA(P69,P74,P79,P84) -> 15.580884 | Q89: =AVERAGEA(Q69,Q74,Q79,Q84) -> 18.476764
A91: =A81+1 -> 482 | B91: =B81+7 -> 37167 | D91: 2000000000 | E91: 7976800000 | F91: =E91-D91 -> 5976800000 | G91: 1999900000 | H91: 1944815051 | I91: =G91-H91 -> 55084949 | J91: =B91+K91 -> 37258 | K91: 91 | N91: 10.593 | O91: =H91/G91*100 -> 97.245615 | P91: =(100-O91)/100*(365/91)*100 -> 11.047809 | Q91: =((100-O91)/O91*(365/91))*100 -> 11.360727
D92: 3000000000 | E92: 7190900000 | F92: =E92-D92 -> 4190900000 | G92: 2999900000 | H92: 2814589727 | I92: =G92-H92 -> 185310273 | J92: =B91+K92+1 -> 37350 | K92: 182 | N92: 11.766 | O92: =H92/G92*100 -> 93.822785 | P92: =(100-O92)/100*(365/182)*100 -> 12.388371 | Q92: =((100-O92)/O92*(365/182))*100 -> 13.204011
D93: 4000000000 | E93: 8376000000 | F93: =E93-D93 -> 4376000000 | G93: 3999900000 | H93: 3603379951 | I93: =G93-H93 -> 396520049 | J93: =B91+K93+1 -> 37441 | K93: 273 | N93: 12.568 | O93: =H93/G93*100 -> 90.086751 | P93: =(100-O93)/100*(365/273)*100 -> 13.253978 | Q93: =((100-O93)/O93*(365/273))*100 -> 14.712461
D94: 8000000000 | E94: 13773000000 | F94: =E94-D94 -> 5773000000 | G94: 8000000000 | H94: 6897486170 | I94: =G94-H94 -> 1102513830 | J94: =B91+K94+1 -> 37532 | K94: 364 | N94: 12.5 | O94: =H94/G94*100 -> 86.218577 | P94: =(100-O94)/100*(365/364)*100 -> 13.819284 | Q94: =((100-O94)/O94*(365/364))*100 -> 16.028198
A96: =A91+1 -> 483 | B96: =B91+7 -> 37174 | D96: 2000000000 | E96: 10082200000 | F96: =E96-D96 -> 8082200000 | G96: 2000000000 | H96: 1950843886 | I96: =G96-H96 -> 49156114 | J96: =B96+K96 -> 37265 | K96: 91 | N96: 9.654 | O96: =H96/G96*100 -> 97.542194 | P96: =(100-O96)/100*(365/91)*100 -> 9.8582317 | Q96: =((100-O96)/O96*(365/91))*100 -> 10.106633
D97: 3000000000 | E97: 7100500000 | F97: =E97-D97 -> 4100500000 | G97: 2999900000 | H97: 2826262928 | I97: =G97-H97 -> 173637072 | J97: =B96+K97+1 -> 37357 | K97: 182 | N97: 11.205 | O97: =H97/G97*100 -> 94.211905 | P97: =(100-O97)/100*(365/182)*100 -> 11.607993 | Q97: =((100-O97)/O97*(365/182))*100 -> 12.321154
D98: 4000000000 | E98: 9208000000 | F98: =E98-D98 -> 5208000000 | G98: 4000000000 | H98: 3613052690 | I98: =G98-H98 -> 386947310 | J98: =B96+K98+1 -> 37448 | K98: 273 | N98: 12.16 | O98: =H98/G98*100 -> 90.326317 | P98: =(100-O98)/100*(365/273)*100 -> 12.933678 | Q98: =((100-O98)/O98*(365/273))*100 -> 14.318837
D99: 8000000000 | E99: 16275100000 | F99: =E99-D99 -> 8275100000 | G99: 8000000000 | H99: 6901193713 | I99: =G99-H99 -> 1098806287 | J99: =B96+K99+1 -> 37539 | K99: 364 | N99: 12.93 | O99: =H99/G99*100 -> 86.264921 | P99: =(100-O99)/100*(365/364)*100 -> 13.772812 | Q99: =((100-O99)/O99*(365/364))*100 -> 15.965716
A101: =A96+1 -> 484 | B101: =B96+7 -> 37181 | D101: 2000000000 | E101: 9931100000 | F101: =E101-D101 -> 7931100000 | G101: 2000000000 | H101: 1960323996 | I101: =G101-H101 -> 39676004 | J101: =B101+K101 -> 37272 | K101: 91 | N101: 6.999 | O101: =H101/G101*100 -> 98.0162 | P101: =(100-O101)/100*(365/91)*100 -> 7.9570008 | Q101: =((100-O101)/O101*(365/91))*100 -> 8.1180466
D102: 3000000000 | E102: 12000600000 | F102: =E102-D102 -> 9000600000 | G102: 3000000000 | H102: 2846426314 | I102: =G102-H102 -> 153573686 | J102: =B101+K102+1 -> 37364 | K102: 182 | N102: 9.001 | O102: =H102/G102*100 -> 94.880877 | P102: =(100-O102)/100*(365/182)*100 -> 10.266373 | Q102: =((100-O102)/O102*(365/182))*100 -> 10.820276
D103: 4000000000 | E103: 12281000000 | F103: =E103-D103 -> 8281000000 | G103: 4000000000 | H103: 3628802660 | I103: =G103-H103 -> 371197340 | J103: =B101+K103+1 -> 37455 | K103: 273 | N103: 12 | O103: =H103/G103*100 -> 90.720067 | P103: =(100-O103)/100*(365/273)*100 -> 12.407237 | Q103: =((100-O103)/O103*(365/273))*100 -> 13.676398
D104: 8000000000 | E104: 17358000000 | F104: =E104-D104 -> 9358000000 | G104: 8000000000 | H104: 6931435340 | I104: =G104-H104 -> 1068564660 | J104: =B101+K104+1 -> 37546 | K104: 364 | N104: 12 | O104: =H104/G104*100 -> 86.642942 | P104: =(100-O104)/100*(365/364)*100 -> 13.393753 | Q104: =((100-O104)/O104*(365/364))*100 -> 15.458563
A106: =A101+1 -> 485 | B106: =B101+7 -> 37188 | D106: 2000000000 | E106: 2919200000 | F106: =E106-D106 -> 919200000 | G106: 2000000000 | H106: 1958434024 | I106: =G106-H106 -> 41565976 | J106: =B106+K106 -> 37279 | K106: 91 | N106: 7.845 | O106: =H106/G106*100 -> 97.921701 | P106: =(100-O106)/100*(365/91)*100 -> 8.3360336 | Q106: =((100-O106)/O106*(365/91))*100 -> 8.5129584
D107: 3000000000 | E107: 4935300000 | F107: =E107-D107 -> 1935300000 | G107: 2999900000 | H107: 2854346884 | I107: =G107-H107 -> 145553116 | J107: =B106+K107+1 -> 37371 | K107: 182 | N107: 8.686 | O107: =H107/G107*100 -> 95.148068 | P107: =(100-O107)/100*(365/182)*100 -> 9.7305235 | Q107: =((100-O107)/O107*(365/182))*100 -> 10.226717
D108: 4000000000 | E108: 5369500000 | F108: =E108-D108 -> 1369500000 | G108: 4000000000 | H108: 3647779923 | I108: =G108-H108 -> 352220077 | J108: =B106+K108+1 -> 37462 | K108: 273 | N108: 8.666 | O108: =H108/G108*100 -> 91.194498 | P108: =(100-O108)/100*(365/273)*100 -> 11.772924 | Q108: =((100-O108)/O108*(365/273))*100 -> 12.909687
D109: 8000000000 | E109: 14369500000 | F109: =E109-D109 -> 6369500000 | G109: 8000000000 | H109: 6997034628 | I109: =G109-H109 -> 1002965372 | J109: =B106+K109+1 -> 37553 | K109: 364 | N109: 12 | O109: =H109/G109*100 -> 87.462933 | P109: =(100-O109)/100*(365/364)*100 -> 12.57151 | Q109: =((100-O109)/O109*(365/364))*100 -> 14.373529
A111: =A106+1 -> 486 | B111: =B106+7 -> 37195 | D111: 2000000000 | E111: 5359000000 | F111: =E111-D111 -> 3359000000 | G111: 1999900000 | H111: 1961387440 | I111: =G111-H111 -> 38512560 | J111: =B111+K111 -> 37286 | K111: 91 | N111: 7.364 | O111: =H111/G111*100 -> 98.074276 | P111: =(100-O111)/100*(365/91)*100 -> 7.724059 | Q111: =((100-O111)/O111*(365/91))*100 -> 7.8757237
D112: 2000000000 | E112: 5738800000 | F112: =E112-D112 -> 3738800000 | G112: 2000000000 | H112: 1906225848 | I112: =G112-H112 -> 93774152 | J112: =B111+K112+1 -> 37378 | K112: 182 | N112: 9.071 | O112: =H112/G112*100 -> 95.311292 | P112: =(100-O112)/100*(365/182)*100 -> 9.4031773 | Q112: =((100-O112)/O112*(365/182))*100 -> 9.8657537
D113: 3000000000 | E113: 8260800000 | F113: =E113-D113 -> 5260800000 | G113: 3000000000 | H113: 2768805482 | I113: =G113-H113 -> 231194518 | J113: =B111+K113+1 -> 37469 | K113: 273 | N113: 9.499 | O113: =H113/G113*100 -> 92.293516 | P113: =(100-O113)/100*(365/273)*100 -> 10.303541 | Q113: =((100-O113)/O113*(365/273))*100 -> 11.163884
D114: 5000000000 | E114: 15853700000 | F114: =E114-D114 -> 10853700000 | G114: 4999900000 | H114: 4402932800 | I114: =G114-H114 -> 596967200 | J114: =B111+K114+1 -> 37560 | K114: 364 | N114: 11 | O114: =H114/G114*100 -> 88.060417 | P114: =(100-O114)/100*(365/364)*100 -> 11.972384 | Q114: =((100-O114)/O114*(365/364))*100 -> 13.595647
B116: TOTAL OCT 2001 | D116: =SUM(D91:D114) -> 80000000000 | E116: =SUM(E91:E114) -> 194359000000 | F116: =SUM(F91:F114) -> 114359000000 | G116: =SUM(G91:G114) -> 79999300000 | H116: =SUM(H91:H114) -> 72415559455 | I116: =SUM(I91:I114) -> 7583740545 | L116: Monthly Average of 91 day bill rate | O116: =AVERAGEA(O91,O96,O101,O106,O111) -> 97.759997 | P116: =AVERAGEA(P91,P96,P101,P106,P111) -> 8.9846267 | Q116: =AVERAGEA(Q91,Q96,Q101,Q106,Q111) -> 9.1948177
L117: Monthly Average of 182 day bill rate | O117: =AVERAGEA(O92,O97,O102,O107,O112) -> 94.674985 | P117: =AVERAGEA(P92,P97,P102,P107,P112) -> 10.679288 | Q117: =AVERAGEA(Q92,Q97,Q102,Q107,Q112) -> 11.287582
L118: Monthly Average of 273 day bill rate | O118: =AVERAGEA(O93,O98,O103,O108,O113) -> 90.92423 | P118: =AVERAGEA(P93,P98,P103,P108,P113) -> 12.134272 | Q118: =AVERAGEA(Q93,Q98,Q103,Q108,Q113) -> 13.356253
L119: Monthly Average of 364 day bill rate | O119: =AVERAGEA(O94,O99,O104,O109,O114) -> 86.929958 | P119: =AVERAGEA(P94,P99,P104,P109,P114) -> 13.105949 | Q119: =AVERAGEA(Q94,Q99,Q104,Q109,Q114) -> 15.08433
A121: =A111+1 -> 487 | B121: =B111+7 -> 37202 | D121: 2000000000 | E121: 4897400000 | F121: =E121-D121 -> 2897400000 | G121: 1999900000 | H121: 1963564342 | I121: =G121-H121 -> 36335658 | J121: =B121+K121 -> 37293 | K121: 91 | N121: 6.783 | O121: =H121/G121*100 -> 98.183126 | P121: =(100-O121)/100*(365/91)*100 -> 7.2874606 | Q121: =((100-O121)/O121*(365/91))*100 -> 7.4223147
D122: 3000000000 | E122: 5866400000 | F122: =E122-D122 -> 2866400000 | G122: 3000000000 | H122: 2865331424 | I122: =G122-H122 -> 134668576 | J122: =B121+K122+1 -> 37385 | K122: 182 | N122: 3.61 | O122: =H122/G122*100 -> 95.511047 | P122: =(100-O122)/100*(365/182)*100 -> 9.0025696 | Q122: =((100-O122)/O122*(365/182))*100 -> 9.4256841
D123: 4000000000 | E123: 9789600000 | F123: =E123-D123 -> 5789600000 | G123: 4000000000 | H123: 3694062442 | I123: =G123-H123 -> 305937558 | J123: =B121+K123+1 -> 37476 | K123: 273 | N123: 9.499 | O123: =H123/G123*100 -> 92.351561 | P123: =(100-O123)/100*(365/273)*100 -> 10.225935 | Q123: =((100-O123)/O123*(365/273))*100 -> 11.072834
D124: 8000000000 | E124: 17576200000 | F124: =E124-D124 -> 9576200000 | G124: 7999800000 | H124: 7104350028 | I124: =G124-H124 -> 895449972 | J124: =B121+K124+1 -> 37567 | K124: 364 | N124: 9.913 | O124: =H124/G124*100 -> 88.806596 | P124: =(100-O124)/100*(365/364)*100 -> 11.224156 | Q124: =((100-O124)/O124*(365/364))*100 -> 12.638876
...

Sheet maturities - 91
A2: Ref:ISS0001. WK3
A3: worksheet a
A4: - | B4: - | C4: - | D4: - | E4: - | F4: - | G4: - | H4: - | I4: - | J4: - | K4: - | L4: - | M4: - | N4: - | O4: - | Q4: -
A5: Auction | B5: Issue date | C5: Amount offered | D5: Total bids | E5: Over/(Under) | F5: Face Value of | G5: Cost Value | H5: Interest due | I5: Date due | J5: Duration | K5: Implicit annual | L5: Clearing | M5: Lowest | N5: Weighted | O5: Average | P5: Money Market yield | Q5: Annualised | R5: Bid to cover ratios
A6: No | C6: in | D6: (Competitive & | E6: Subscribed | F6: issues | K6: interest rate | L6: factor | M6: factor | N6: Average | O6: Discount | Q6: yield
C7: Auction | D7: Uncompetitive) | L7: (%) | M7: (%) | N7: Price | O7: factor
B8: (1) | C8: (1a) | D8: (1b) | F8: (2) | G8: (3) | H8: (4) | I8: (5) | J8: (6) | K8: (9) | L8: (10) | M8: (11) | N8: (12) | O8: (13)
A9: - | B9: - | D9: - | E9: - | F9: - | G9: - | H9: - | I9: - | J9: - | K9: - | L9: - | M9: - | N9: - | O9: - | Q9: -
A11: ='ISS10102'!A11 -> 469 | B11: ='ISS10102'!B11 -> 37076 | C11: ='ISS10102'!D11 -> 1500000000 | D11: ='ISS10102'!E11 -> 2402100000 | E11: ='ISS10102'!F11 -> 902100000 | F11: ='ISS10102'!G11 -> 1500000000 | G11: ='ISS10102'!H11 -> 1473850685 | H11: ='ISS10102'!I11 -> 26149315 | I11: ='ISS10102'!J11 -> 37167 | J11: ='ISS10102'!K11 -> 91 | ... O11: ='ISS10102'!P11 -> 6.9923077 | Q11: ='ISS10102'!Q11 -> 7.1163664 | R11: =D11/C11 -> 1.6014
A12: ='ISS10102'!A16 -> 470 | B12: ='ISS10102'!B16 -> 37083 | C12: ='ISS10102'!D16 -> 2000000000 | D12: ='ISS10102'!E16 -> 6763900000 | E12: ='ISS10102'!F16 -> 4763900000 | F12: ='ISS10102'!G16 -> 2000000000 | G12: ='ISS10102'!H16 -> 1966357750 | H12: ='ISS10102'!I16 -> 33642250 | I12: ='ISS10102'!J16 -> 37174 | J12: ='ISS10102'!K16 -> 91 | ... O12: ='ISS10102'!P16 -> 6.7469348 | Q12: ='ISS10102'!Q16 -> 6.8623675 | R12: =+D12/F12 -> 3.38195 | T12: 2001 | U12: =+SUMIF(#REF!,T12,G:G) -> #REF!
A13: ='ISS10102'!A21 -> 471 | B13: ='ISS10102'!B21 -> 37090 | C13: ='ISS10102'!D21 -> 2000000000 | D13: ='ISS10102'!E21 -> 3562000000 | E13: ='ISS10102'!F21 -> 1562000000 | F13: ='ISS10102'!G21 -> 2000000000 | G13: ='ISS10102'!H21 -> 1964154360 | H13: ='ISS10102'!I21 -> 35845640 | I13: ='ISS10102'!J21 -> 37181 | J13: ='ISS10102'!K21 -> 91 | ... O13: ='ISS10102'!P21 -> 7.1888234 | Q13: ='ISS10102'!Q21 -> 7.3200188 | R13: =+D13/F13 -> 1.781 | T13: 2002 | U13: =+SUMIF(#REF!,T13,G:G) -> #REF!
A14: ='ISS10102'!A26 -> 472 | B14: ='ISS10102'!B26 -> 37097 | C14: ='ISS10102'!D26 -> 3000000000 | D14: ='ISS10102'!E26 -> 3034500000 | E14: ='ISS10102'!F26 -> 34500000 | F14: ='ISS10102'!G26 -> 3000000000 | G14: ='ISS10102'!H26 -> 2920291115 | H14: ='ISS10102'!I26 -> 79708885 | I14: ='ISS10102'!J26 -> 37188 | J14: ='ISS10102'!K26 -> 91 | ... O14: ='ISS10102'!P26 -> 10.657049 | Q14: ='ISS10102'!Q26 -> 10.947931 | R14: =+D14/F14 -> 1.0115 | T14: 2003 | U14: =+SUMIF(#REF!,T14,G:G) -> #REF!
A15: ='ISS10102'!A36 -> 473 | B15: ='ISS10102'!B36 -> 37104 | C15: ='ISS10102'!D36 -> 3000000000 | D15: ='ISS10102'!E36 -> 3000000000 | E15: ='ISS10102'!F36 -> 0 | F15: ='ISS10102'!G36 -> 3000000000 | G15: ='ISS10102'!H36 -> 2899532650 | H15: ='ISS10102'!I36 -> 100467350 | I15: ='ISS10102'!J36 -> 37195 | J15: ='ISS10102'!K36 -> 91 | ... O15: ='ISS10102'!P36 -> 13.432448 | Q15: ='ISS10102'!Q36 -> 13.897875 | R15: =+D15/F15 -> 1 | T15: 2004 | U15: =+SUMIF(#REF!,T15,G:G) -> #REF!
F16: =SUM(F11:F15) -> 11500000000 | R16: =+D16/F16 -> 0 | T16: 2005 | U16: =+SUMIF(#REF!,T16,G:G) -> #REF!
A17: ='ISS10102'!A41 -> 474 | B17: ='ISS10102'!B41 -> 37111 | C17: ='ISS10102'!D41 -> 3000000000 | D17: ='ISS10102'!E41 -> 4969200000 | E17: ='ISS10102'!F41 -> 1969200000 | F17: ='ISS10102'!G41 -> 3000000000 | G17: ='ISS10102'!H41 -> 2895219779 | H17: ='ISS10102'!I41 -> 104780221 | I17: ='ISS10102'!J41 -> 37202 | J17: ='ISS10102'!K41 -> 91 | ... O17: ='ISS10102'!P41 -> 14.009077 | Q17: ='ISS10102'!Q41 -> 14.516076 | R17: =+D17/F17 -> 1.6564 | T17: 2006 | U17: =+SUMIF(#REF!,T17,G:G) -> #REF!
A18: ='ISS10102'!A46 -> 475 | B18: ='ISS10102'!B46 -> 37118 | C18: ='ISS10102'!D46 -> 3000000000 | D18: ='ISS10102'!E46 -> 8552600000 | E18: ='ISS10102'!F46 -> 5552600000 | F18: ='ISS10102'!G46 -> 3000000000 | G18: ='ISS10102'!H46 -> 2897370000 | H18: ='ISS10102'!I46 -> 102630000 | I18: ='ISS10102'!J46 -> 37209 | J18: ='ISS10102'!K46 -> 91 | ... O18: ='ISS10102'!P46 -> 13.721593 | Q18: ='ISS10102'!Q46 -> 14.207637 | R18: =+D18/F18 -> 2.8508667 | T18: 2007 | U18: =+SUMIF(#REF!,T18,G:G) -> #REF!
A19: ='ISS10102'!A51 -> 476 | B19: ='ISS10102'!B51 -> 37125 | C19: ='ISS10102'!D51 -> 3000000000 | D19: ='ISS10102'!E51 -> 6090200000 | E19: ='ISS10102'!F51 -> 3090200000 | F19: ='ISS10102'!G51 -> 3000000000 | G19: ='ISS10102'!H51 -> 2897927590 | H19: ='ISS10102'!I51 -> 102072410 | I19: ='ISS10102'!J51 -> 37216 | J19: ='ISS10102'!K51 -> 91 | ... O19: ='ISS10102'!P51 -> 13.647044 | Q19: ='ISS10102'!Q51 -> 14.127728 | R19: =+D19/F19 -> 2.0300667 | T19: 2008 | U19: =+SUMIF(#REF!,T19,G:G) -> #REF!
A20: ='ISS10102'!A56 -> 477 | B20: ='ISS10102'!B56 -> 37132 | C20: ='ISS10102'!D56 -> 2000000000 | D20: ='ISS10102'!E56 -> 4022300000 | E20: ='ISS10102'!F56 -> 2022300000 | F20: ='ISS10102'!G56 -> 2000000000 | G20: ='ISS10102'!H56 -> 1933101900 | H20: ='ISS10102'!I56 -> 66898100 | I20: ='ISS10102'!J56 -> 37223 | J20: ='ISS10102'!K56 -> 91 | ... O20: ='ISS10102'!P56 -> 13.416377 | Q20: ='ISS10102'!Q56 -> 13.880673 | R20: =+D20/F20 -> 2.01115 | T20: 2009 | U20: =+SUMIF(#REF!,T20,G:G) -> #REF!
F21: =SUM(F17:F20) -> 11000000000 | R21: =+D21/F21 -> 0 | T21: 2010 | U21: =+SUMIF(#REF!,T21,G:G) -> #REF!
A22: ='ISS10102'!A66 -> 478 | B22: ='ISS10102'!B66 -> 37139 | C22: ='ISS10102'!D66 -> 3000000000 | D22: ='ISS10102'!E66 -> 3000000000 | E22: ='ISS10102'!F66 -> 0 | F22: ='ISS10102'!G66 -> 3000000000 | G22: ='ISS10102'!H66 -> 2902667373 | H22: ='ISS10102'!I66 -> 97332627 | I22: ='ISS10102'!J66 -> 37230 | J22: ='ISS10102'!K66 -> 91 | ... O22: ='ISS10102'!P66 -> 13.013337 | Q22: ='ISS10102'!Q66 -> 13.449702 | R22: =+D22/F22 -> 1 | T22: 2011 | U22: =+SUMIF(#REF!,T22,G:G) -> #REF!
A23: ='ISS10102'!A71 -> 479 | B23: ='ISS10102'!B71 -> 37146 | C23: ='ISS10102'!D71 -> 3000000000 | D23: ='ISS10102'!E71 -> 7713300000 | E23: ='ISS10102'!F71 -> 4713300000 | F23: ='ISS10102'!G71 -> 2999900000 | G23: ='ISS10102'!H71 -> 2910595503 | H23: ='ISS10102'!I71 -> 89304497 | I23: ='ISS10102'!J71 -> 37237 | J23: ='ISS10102'!K71 -> 91 | ... O23: ='ISS10102'!P71 -> 11.940377 | Q23: ='ISS10102'!Q71 -> 12.306738 | R23: =+D23/F23 -> 2.5711857 | T23: 2012 | U23: =+SUMIF(#REF!,T23,G:G) -> #REF!
A24: ='ISS10102'!A76 -> 480 | B24: ='ISS10102'!B76 -> 37153 | C24: ='ISS10102'!D76 -> 3000000000 | D24: ='ISS10102'!E76 -> 6345200000 | E24: ='ISS10102'!F76 -> 3345200000 | F24: ='ISS10102'!G76 -> 3000000000 | G24: ='ISS10102'!H76 -> 2914052620 | H24: ='ISS10102'!I76 -> 85947380 | I24: ='ISS10102'!J76 -> 37244 | J24: ='ISS10102'!K76 -> 91 | ... O24: ='ISS10102'!P76 -> 11.491133 | Q24: ='ISS10102'!Q76 -> 11.830054 | R24: =+D24/F24 -> 2.1150667 | T24: 2013 | U24: =+SUMIF(#REF!,T24,G:G) -> #REF!
A25: ='ISS10102'!A81 -> 481 | B25: ='ISS10102'!B81 -> 37160 | C25: ='ISS10102'!D81 -> 2000000000 | D25: ='ISS10102'!E81 -> 3299500000 | E25: ='ISS10102'!F81 -> 1299500000 | F25: ='ISS10102'!G81 -> 2000000000 | G25: ='ISS10102'!H81 -> 1941382978 | H25: ='ISS10102'!I81 -> 58617022 | I25: ='ISS10102'!J81 -> 37251 | J25: ='ISS10102'!K81 -> 91 | ... O25: ='ISS10102'!P81 -> 11.755612 | Q25: ='ISS10102'!Q81 -> 12.110554 | R25: =+D25/F25 -> 1.64975 | T25: 2014 | U25: =+SUMIF(#REF!,T25,G:G) -> #REF!
F26: =SUM(F22:F25) -> 10999900000 | R26: =+D26/F26 -> 0 | T26: 2015 | U26: =+SUMIF(#REF!,T26,G:G) -> #REF!
A27: ='ISS10102'!A91 -> 482 | B27: ='ISS10102'!B91 -> 37167 | C27: ='ISS10102'!D91 -> 2000000000 | D27: ='ISS10102'!E91 -> 7976800000 | E27: ='ISS10102'!F91 -> 5976800000 | F27: ='ISS10102'!G91 -> 1999900000 | G27: ='ISS10102'!H91 -> 1944815051 | H27: ='ISS10102'!I91 -> 55084949 | I27: ='ISS10102'!J91 -> 37258 | J27: ='ISS10102'!K91 -> 91 | ... O27: ='ISS10102'!P91 -> 11.047809 | Q27: ='ISS10102'!Q91 -> 11.360727 | R27: =+D27/F27 -> 3.9885994 | T27: 2016 | U27: =+SUMIF(#REF!,T27,G:G) -> #REF!
A28: ='ISS10102'!A96 -> 483 | B28: ='ISS10102'!B96 -> 37174 | C28: ='ISS10102'!D96 -> 2000000000 | D28: ='ISS10102'!E96 -> 10082200000 | E28: ='ISS10102'!F96 -> 8082200000 | F28: ='ISS10102'!G96 -> 2000000000 | G28: ='ISS10102'!H96 -> 1950843886 | H28: ='ISS10102'!I96 -> 49156114 | I28: ='ISS10102'!J96 -> 37265 | J28: ='ISS10102'!K96 -> 91 | ... O28: ='ISS10102'!P96 -> 9.8582317 | Q28: ='ISS10102'!Q96 -> 10.106633 | R28: =+D28/F28 -> 5.0411 | T28: 2017 | U28: =+SUMIF(#REF!,T28,G:G) -> #REF!
A29: ='ISS10102'!A101 -> 484 | B29: ='ISS10102'!B101 -> 37181 | C29: ='ISS10102'!D101 -> 2000000000 | D29: ='ISS10102'!E101 -> 9931100000 | E29: ='ISS10102'!F101 -> 7931100000 | F29: ='ISS10102'!G101 -> 2000000000 | G29: ='ISS10102'!H101 -> 1960323996 | H29: ='ISS10102'!I101 -> 39676004 | I29: ='ISS10102'!J101 -> 37272 | J29: ='ISS10102'!K101 -> 91 | ... O29: ='ISS10102'!P101 -> 7.9570008 | Q29: ='ISS10102'!Q101 -> 8.1180466 | R29: =+D29/F29 -> 4.96555 | T29: 2018 | U29: =+SUMIF(#REF!,T29,G:G) -> #REF!
A30: ='ISS10102'!A106 -> 485 | B30: ='ISS10102'!B106 -> 37188 | C30: ='ISS10102'!D106 -> 2000000000 | D30: ='ISS10102'!E106 -> 2919200000 | E30: ='ISS10102'!F106 -> 919200000 | F30: ='ISS10102'!G106 -> 2000000000 | G30: ='ISS10102'!H106 -> 1958434024 | H30: ='ISS10102'!I106 -> 41565976 | I30: ='ISS10102'!J106 -> 37279 | J30: ='ISS10102'!K106 -> 91 | ... O30: ='ISS10102'!P106 -> 8.3360336 | Q30: ='ISS10102'!Q106 -> 8.5129584 | R30: =+D30/F30 -> 1.4596 | T30: 2019 | U30: =+SUMIF(#REF!,T30,G:G) -> #REF!
A31: ='ISS10102'!A111 -> 486 | B31: ='ISS10102'!B111 -> 37195 | C31: ='ISS10102'!D111 -> 2000000000 | D31: ='ISS10102'!E111 -> 5359000000 | E31: ='ISS10102'!F111 -> 3359000000 | F31: ='ISS10102'!G111 -> 1999900000 | G31: ='ISS10102'!H111 -> 1961387440 | H31: ='ISS10102'!I111 -> 38512560 | I31: ='ISS10102'!J111 -> 37286 | J31: ='ISS10102'!K111 -> 91 | ... O31: ='ISS10102'!P111 -> 7.724059 | Q31: ='ISS10102'!Q111 -> 7.8757237 | R31: =+D31/F31 -> 2.679634 | T31: 2020 | U31: =+SUMIF(#REF!,T31,G:G) -> #REF!
F32: =SUM(F27:F31) -> 9999800000 | R32: =+D32/F32 -> 0 | T32: 2021 | U32: =+SUMIF(#REF!,T32,G:G) -> #REF!
A33: ='ISS10102'!A121 -> 487 | B33: ='ISS10102'!B121 -> 37202 | C33: ='ISS10102'!D121 -> 2000000000 | D33: ='ISS10102'!E121 -> 4897400000 | E33: ='ISS10102'!F121 -> 2897400000 | F33: ='ISS10102'!G121 -> 1999900000 | G33: ='ISS10102'!H121 -> 1963564342 | H33: ='ISS10102'!I121 -> 36335658 | I33: ='ISS10102'!J121 -> 37293 | J33: ='ISS10102'!K121 -> 91 | ... O33: ='ISS10102'!P121 -> 7.2874606 | Q33: ='ISS10102'!Q121 -> 7.4223147 | R33: =+D33/F33 -> 2.4488224 | T33: 2022 | U33: =+SUMIF(#REF!,T33,G:G) -> #REF!
A34: ='ISS10102'!A126 -> 488 | B34: ='ISS10102'!B126 -> 37209 | C34: ='ISS10102'!D126 -> 2000000000 | D34: ='ISS10102'!E126 -> 7030600000 | E34: ='ISS10102'!F126 -> 5030600000 | F34: ='ISS10102'!G126 -> 1999900000 | G34: ='ISS10102'!H126 -> 1965227616 | H34: ='ISS10102'!I126 -> 34672384 | I34: ='ISS10102'!J126 -> 37300 | J34: ='ISS10102'!K126 -> 91 | ... O34: ='ISS10102'!P126 -> 6.9538753 | Q34: ='ISS10102'!Q126 -> 7.076562 | R34: =+D34/F34 -> 3.5154758 | U34: =+SUMIF(#REF!,T34,G:G) -> #REF!
A35: ='ISS10102'!A131 -> 489 | B35: ='ISS10102'!B131 -> 37216 | C35: ='ISS10102'!D131 -> 3000000000 | D35: ='ISS10102'!E131 -> 9919200000 | E35: ='ISS10102'!F131 -> 6919200000 | F35: ='ISS10102'!G131 -> 3000000000 | G35: ='ISS10102'!H131 -> 2950319502 | H35: ='ISS10102'!I131 -> 49680498 | I35: ='ISS10102'!J131 -> 37307 | J35: ='ISS10102'!K131 -> 91 | ... O35: ='ISS10102'!P131 -> 6.6422644 | Q35: ='ISS10102'!Q131 -> 6.7541136 | R35: =+D35/F35 -> 3.3064 | U35: =+SUMIF(#REF!,T35,G:G) -> #REF!
A36: ='ISS10102'!A136 -> 490 | B36: ='ISS10102'!B136 -> 37223 | C36: ='ISS10102'!D136 -> 3000000000 | D36: ='ISS10102'!E136 -> 5436600000 | E36: ='ISS10102'!F136 -> 2436600000 | F36: ='ISS10102'!G136 -> 3000000000 | G36: ='ISS10102'!H136 -> 2950756509 | H36: ='ISS10102'!I136 -> 49243491 | I36: ='ISS10102'!J136 -> 37314 | J36: ='ISS10102'!K136 -> 91 | ... O36: ='ISS10102'!P136 -> 6.5838367 | Q36: ='ISS10102'!Q136 -> 6.6937106 | R36: =+D36/F36 -> 1.8122 | U36: =+SUMIF(#REF!,T36,G:G) -> #REF!
F37: =SUM(F33:F36) -> 9999800000 | R37: =+D37/F37 -> 0 | U37: =+SUMIF(#REF!,T37,G:G) -> #REF!
A38: ='ISS10102'!A146 -> 491 | B38: ='ISS10102'!B146 -> 37230 | C38: ='ISS10102'!D146 -> 3000000000 | D38: ='ISS10102'!E146 -> 9665700000 | E38: ='ISS10102'!F146 -> 6665700000 | F38: ='ISS10102'!G146 -> 3000000000 | G38: ='ISS10102'!H146 -> 2953689106 | H38: ='ISS10102'!I146 -> 46310894 | I38: ='ISS10102'!J146 -> 37321 | J38: ='ISS10102'!K146 -> 91 | ... O38: ='ISS10102'!P146 -> 6.1917496 | Q38: ='ISS10102'!Q146 -> 6.28883 | R38: =+D38/F38 -> 3.2219 | U38: =+SUMIF(#REF!,T38,G:G) -> #REF!
A39: ='ISS10102'!A151 -> 492 | B39: ='ISS10102'!B151 -> 37237 | C39: ='ISS10102'!D151 -> 3000000000 | D39: ='ISS10102'!E151 -> 7214300000 | E39: ='ISS10102'!F151 -> 4214300000 | F39: ='ISS10102'!G151 -> 2999900000 | G39: ='ISS10102'!H151 -> 2958084326 | H39: ='ISS10102'!I151 -> 41815674 | I39: ='ISS10102'!J151 -> 37328 | J39: ='ISS10102'!K151 -> 91 | ... O39: ='ISS10102'!P151 -> 5.5909267 | Q39: ='ISS10102'!Q151 -> 5.6699604 | R39: =+D39/F39 -> 2.4048468 | U39: =+SUMIF(#REF!,T39,G:G) -> #REF!
A40: ='ISS10102'!A156 -> 493 | B40: ='ISS10102'!B156 -> 37244 | C40: ='ISS10102'!D156 -> 3000000000 | D40: ='ISS10102'!E156 -> 4718200000 | E40: ='ISS10102'!F156 -> 1718200000 | F40: ='ISS10102'!G156 -> 3000000000 | G40: ='ISS10102'!H156 -> 2958123874 | H40: ='ISS10102'!I156 -> 41876126 | I40: ='ISS10102'!J156 -> 37335 | J40: ='ISS10102'!K156 -> 91 | ... O40: ='ISS10102'!P156 -> 5.5988227 | Q40: ='ISS10102'!Q156 -> 5.6780814 | R40: =+D40/F40 -> 1.5727333 | U40: =+SUMIF(#REF!,T40,G:G) -> #REF!
A41: ='ISS10102'!A161 -> 494 | B41: ='ISS10102'!B161 -> 37252 | C41: ='ISS10102'!D161 -> 2000000000 | D41: ='ISS10102'!E161 -> 4074800000 | E41: ='ISS10102'!F161 -> 2074800000 | F41: ='ISS10102'!G161 -> 2000000000 | G41: ='ISS10102'!H161 -> 1972695240 | H41: ='ISS10102'!I161 -> 27304760 | I41: ='ISS10102'!J161 -> 37343 | J41: ='ISS10102'!K161 -> 91 | ... O41: ='ISS10102'!P161 -> 5.4759546 | Q41: ='ISS10102'!Q161 -> 5.5517492 | R41: =+D41/F41 -> 2.0374 | U41: =+SUMIF(#REF!,T41,G:G) -> #REF!
F42: =SUM(F38:F41) -> 10999900000 | R42: =+D42/F42 -> 0 | U42: =+SUMIF(#REF!,T42,G:G) -> #REF!
A43: ='ISS10102'!A171 -> 495 | B43: ='ISS10102'!B171 -> 37258 | C43: ='ISS10102'!D171 -> 2000000000 | D43: ='ISS10102'!E171 -> 4934300000 | E43: ='ISS10102'!F171 -> 2934300000 | F43: ='ISS10102'!G171 -> 1999900000 | G43: ='ISS10102'!H171 -> 1973409985 | H43: ='ISS10102'!I171 -> 26490015 | I43: ='ISS10102'!J171 -> 37349 | J43: ='ISS10102'!K171 -> 91 | ... O43: ='ISS10102'!P171 -> 5.3128236 | Q43: ='ISS10102'!Q171 -> 5.3841401 | R43: =+D43/F43 -> 2.4672734 | U43: =+SUMIF(#REF!,T43,G:G) -> #REF!
A44: ='ISS10102'!A177 -> 496 | B44: ='ISS10102'!B177 -> 37265 | C44: ='ISS10102'!D177 -> 2000000000 | D44: ='ISS10102'!E177 -> 5847900000 | E44: ='ISS10102'!F177 -> 3847900000 | F44: ='ISS10102'!G177 -> 1999900000 | G44: ='ISS10102'!H177 -> 1974518140 | H44: ='ISS10102'!I177 -> 25381860 | I44: ='ISS10102'!J177 -> 37356 | J44: ='ISS10102'!K177 -> 91 | ... O44: ='ISS10102'!P177 -> 5.0905726 | Q44: ='ISS10102'!Q177 -> 5.1560104 | R44: =+D44/F44 -> 2.9240962 | U44: =+SUMIF(#REF!,T44,G:G) -> #REF!
A45: ='ISS10102'!A183 -> 497 | B45: ='ISS10102'!B183 -> 37272 | C45: ='ISS10102'!D183 -> 3000000000 | D45: ='ISS10102'!E183 -> 10229700000 | E45: ='ISS10102'!F183 -> 7229700000 | F45: ='ISS10102'!G183 -> 3000000000 | G45: ='ISS10102'!H183 -> 2962476556 | H45: ='ISS10102'!I183 -> 37523444 | I45: ='ISS10102'!J183 -> 37363 | J45: ='ISS10102'!K183 -> 91 | ... O45: ='ISS10102'!P183 -> 5.0168707 | Q45: ='ISS10102'!Q183 -> 5.0804156 | R45: =+D45/F45 -> 3.4099 | U45: =+SUMIF(#REF!,T45,G:G) -> #REF!
A46: ='ISS10102'!A190 -> 498 | B46: ='ISS10102'!B190 -> 37279 | C46: ='ISS10102'!D190 -> 2000000000 | D46: ='ISS10102'!E190 -> 9376400000 | E46: ='ISS10102'!F190 -> 7376400000 | F46: ='ISS10102'!G190 -> 1999900000 | G46: ='ISS10102'!H190 -> 1975883936 | H46: ='ISS10102'!I190 -> 24016064 | I46: ='ISS10102'!J190 -> 37370 | J46: ='ISS10102'!K190 -> 91 | ... O46: ='ISS10102'!P190 -> 4.8166493 | Q46: ='ISS10102'!Q190 -> 4.8751937 | R46: =+D46/F46 -> 4.6884344 | U46: =+SUMIF(#REF!,T46,G:G) -> #REF!
A47: ='ISS10102'!A197 -> 499 | B47: ='ISS10102'!B197 -> 37286 | C47: ='ISS10102'!D197 -> 2000000000 | D47: ='ISS10102'!E197 -> 7293700000 | E47: ='ISS10102'!F197 -> 5293700000 | F47: ='ISS10102'!G197 -> 1999900000 | G47: ='ISS10102'!H197 -> 1978694871 | H47: ='ISS10102'!I197 -> 21205129 | I47: ='ISS10102'!J197 -> 37377 | J47: ='ISS10102'!K197 -> 91 | ... O47: ='ISS10102'!P197 -> 4.2528896 | Q47: ='ISS10102'!Q197 -> 4.2984667 | R47: =+D47/F47 -> 3.6470324 | U47: =+SUMIF(#REF!,T47,G:G) -> #REF!
F48: =SUM(F43:F47) -> 10999600000 | R48: =+D48/F48 -> 0 | U48: =+SUMIF(#REF!,T48,G:G) -> #REF!
A49: ='ISS10102'!A210 -> 500 | B49: ='ISS10102'!B210 -> 37293 | C49: ='ISS10102'!D210 -> 1000000000 | D49: ='ISS10102'!E210 -> 2415300000 | E49: ='ISS10102'!F210 -> 1415300000 | F49: ='ISS10102'!G210 -> 1000000000 | G49: ='ISS10102'!H210 -> 990709511 | H49: ='ISS10102'!I210 -> 9290489 | I49: ='ISS10102'!J210 -> 37384 | J49: ='ISS10102'!K210 -> 91 | ... O49: ='ISS10102'!P210 -> 3.7264049 | Q49: ='ISS10102'!Q210 -> 3.7613497 | R49: =+D49/F49 -> 2.4153 | U49: =+SUMIF(#REF!,T49,G:G) -> #REF!
A50: ='ISS10102'!A217 -> 501 | B50: ='ISS10102'!B217 -> 37300 | C50: ='ISS10102'!D217 -> 2000000000 | D50: ='ISS10102'!E217 -> 5488800000 | E50: ='ISS10102'!F217 -> 3488800000 | F50: ='ISS10102'!G217 -> 2000000000 | G50: ='ISS10102'!H217 -> 1981973224 | H50: ='ISS10102'!I217 -> 18026776 | I50: ='ISS10102'!J217 -> 37393 | J50: ='ISS10102'!K217 -> 91 | ... O50: ='ISS10102'!P217 -> 3.61526 | Q50: ='ISS10102'!Q217 -> 3.6481421 | R50: =+D50/F50 -> 2.7444 | U50: =+SUMIF(#REF!,T50,G:G) -> #REF!
A51: ='ISS10102'!A224 -> 502 | B51: ='ISS10102'!B224 -> 37307 | C51: ='ISS10102'!D224 -> 3000000000 | D51: ='ISS10102'!E224 -> 6486800000 | E51: ='ISS10102'!F224 -> 3486800000 | F51: ='ISS10102'!G224 -> 3000000000 | G51: ='ISS10102'!H224 -> 2975390304 | H51: ='ISS10102'!I224 -> 24609696 | I51: ='ISS10102'!J224 -> 37400 | J51: ='ISS10102'!K224 -> 91 | ... O51: ='ISS10102'!P224 -> 3.2903073 | Q51: ='ISS10102'!Q224 -> 3.3175217 | R51: =+D51/F51 -> 2.1622667 | U51: =+SUMIF(#REF!,T51,G:G) -> #REF!
A52: ='ISS10102'!A231 -> 503 | B52: ='ISS10102'!B231 -> 37314 | C52: ='ISS10102'!D231 -> 3000000000 | D52: ='ISS10102'!E231 -> 11515000000 | E52: ='ISS10102'!F231 -> 8515000000 | F52: ='ISS10102'!G231 -> 2999900000 | G52: ='ISS10102'!H231 -> 2977672643 | H52: ='ISS10102'!I231 -> 22227357 | I52: ='ISS10102'!J231 -> 37407 | J52: ='ISS10102'!K231 -> 91 | ... O52: ='ISS10102'!P231 -> 2.9718886 | Q52: ='ISS10102'!Q231 -> 2.9940727 | R52: =+D52/F52 -> 3.8384613 | U52: =+SUMIF(#REF!,T52,G:G) -> #REF!
F53: =SUM(F49:F52) -> 8999900000 | R53: =+D53/F53 -> 0 | U53: =+SUMIF(#REF!,T53,G:G) -> #REF!
A54: ='ISS10102'!A243 -> 504 | B54: ='ISS10102'!B243 -> 37321 | C54: ='ISS10102'!D243 -> 3000000000 | D54: ='ISS10102'!E243 -> 8380200000 | E54: ='ISS10102'!F243 -> 5380200000 | F54: ='ISS10102'!G243 -> 3000000000 | G54: ='ISS10102'!H243 -> 2978104812 | H54: ='ISS10102'!I243 -> 21895188 | I54: ='ISS10102'!J243 -> 37413 | J54: ='ISS10102'!K243 -> 91 | ... O54: ='ISS10102'!P243 -> 2.9273786 | Q54: ='ISS10102'!Q243 -> 2.9489009 | R54: =+D54/F54 -> 2.7934 | U54: =+SUMIF(#REF!,T54,G:G) -> #REF!
A55: ='ISS10102'!A250 -> 505 | B55: ='ISS10102'!B250 -> 37328 | C55: ='ISS10102'!D250 -> 2000000000 | D55: ='ISS10102'!E250 -> 6653100000 | E55: ='ISS10102'!F250 -> 4653100000 | F55: ='ISS10102'!G250 -> 2000000000 | G55: ='ISS10102'!H250 -> 1986307263 | H55: ='ISS10102'!I250 -> 13692737 | I55: ='ISS10102'!J250 -> 37420 | J55: ='ISS10102'!K250 -> 91 | ... O55: ='ISS10102'!P250 -> 2.7460709 | Q55: ='ISS10102'!Q250 -> 2.7650011 | R55: =+D55/F55 -> 3.32655 | U55: =+SUMIF(#REF!,T55,G:G) -> #REF!
A56: ='ISS10102'!A257 -> 506 | B56: ='ISS10102'!B257 -> 37335 | C56: ='ISS10102'!D257 -> 3000000000 | D56: ='ISS10102'!E257 -> 6733900000 | E56: ='ISS10102'!F257 -> 3733900000 | F56: ='ISS10102'!G257 -> 3000000000 | G56: ='ISS10102'!H257 -> 2979848874 | H56: ='ISS10102'!I257 -> 20151126 | I56: ='ISS10102'!J257 -> 37427 | J56: ='ISS10102'!K257 -> 91 | ... O56: ='ISS10102'!P257 -> 2.6941982 | Q56: ='ISS10102'!Q257 -> 2.7124176 | R56: =+D56/F56 -> 2.2446333 | U56: =+SUMIF(#REF!,T56,G:G) -> #REF!
A57: ='ISS10102'!A264 -> 507 | B57: ='ISS10102'!B264 -> 37342 | C57: ='ISS10102'!D264 -> 3000000000 | D57: ='ISS10102'!E264 -> 3913000000 | E57: ='ISS10102'!F264 -> 913000000 | F57: ='ISS10102'!G264 -> 3000000000 | G57: ='ISS10102'!H264 -> 2973773862 | H57: ='ISS10102'!I264 -> 26226138 | I57: ='ISS10102'!J264 -> 37434 | J57: ='ISS10102'!K264 -> 91 | ... O57: ='ISS10102'!P264 -> 3.506425 | Q57: ='ISS10102'!Q264 -> 3.5373487 | R57: =+D57/F57 -> 1.3043333 | U57: =+SUMIF(#REF!,T57,G:G) -> #REF!
F58: =SUM(F54:F57) -> 11000000000 | R58: =+D58/F58 -> 0 | U58: =+SUMIF(#REF!,T58,G:G) -> #REF!
A59: ='ISS10102'!A275 -> 508 | B59: ='ISS10102'!B275 -> 37349 | C59: ='ISS10102'!D275 -> 2000000000 | D59: ='ISS10102'!E275 -> 4786200000 | E59: ='ISS10102'!F275 -> 2786200000 | F59: ='ISS10102'!G275 -> 2000000000 | G59: ='ISS10102'!H275 -> 1974372078 | H59: ='ISS10102'!I275 -> 25627922 | I59: ='ISS10102'!J275 -> 37441 | J59: ='ISS10102'!K275 -> 91 | ... O59: ='ISS10102'!P275 -> 5.1396657 | Q59: ='ISS10102'!Q275 -> 5.20638 | R59: =+D59/F59 -> 2.3931 | U59: =+SUMIF(#REF!,T59,G:G) -> #REF!
A60: ='ISS10102'!A281 -> 509 | B60: ='ISS10102'!B281 -> 37356 | C60: ='ISS10102'!D281 -> 1500000000 | D60: ='ISS10102'!E281 -> 5729400000 | E60: ='ISS10102'!F281 -> 4229400000 | F60: ='ISS10102'!G281 -> 1500000000 | G60: ='ISS10102'!H281 -> 1482014112 | H60: ='ISS10102'!I281 -> 17985888 | I60: ='ISS10102'!J281 -> 37448 | J60: ='ISS10102'!K281 -> 91 | ... O60: ='ISS10102'!P281 -> 4.8094133 | Q60: ='ISS10102'!Q281 -> 4.8677808 | R60: =+D60/F60 -> 3.8196 | U60: =+SUMIF(#REF!,T60,G:G) -> #REF!
A61: ='ISS10102'!A287 -> 510 | B61: ='ISS10102'!B287 -> 37363 | C61: ='ISS10102'!D287 -> 1500000000 | D61: ='ISS10102'!E287 -> 6586500000 | E61: ='ISS10102'!F287 -> 5086500000 | F61: ='ISS10102'!G287 -> 1500000000 | G61: ='ISS10102'!H287 -> 1482661695 | H61: ='ISS10102'!I287 -> 17338305 | I61: ='ISS10102'!J287 -> 37455 | J61: ='ISS10102'!K287 -> 91 | ... O61: ='ISS10102'!P287 -> 4.6362501 | Q61: ='ISS10102'!Q287 -> 4.6904665 | R61: =+D61/F61 -> 4.391 | U61: =+SUMIF(#REF!,T61,G:G) -> #REF!
A62: ='ISS10102'!A293 -> 511 | B62: ='ISS10102'!B293 -> 37370 | C62: ='ISS10102'!D293 -> 1500000000 | D62: ='ISS10102'!E293 -> 5638700000 | E62: ='ISS10102'!F293 -> 4138700000 | F62: ='ISS10102'!G293 -> 1499900000 | G62: ='ISS10102'!H293 -> 1484264370 | H62: ='ISS10102'!I293 -> 15635630 | I62: ='ISS10102'!J293 -> 37462 | J62: ='ISS10102'!K293 -> 91 | ... O62: ='ISS10102'!P293 -> 4.1812348 | Q62: ='ISS10102'!Q293 -> 4.225281 | R62: =+D62/F62 -> 3.759384 | U62: =+SUMIF(#REF!,T62,G:G) -> #REF!
F63: =SUM(F59:F62) -> 6499900000 | R63: =+D63/F63 -> 0 | U63: =+SUMIF(#REF!,T63,G:G) -> #REF!
A64: ='ISS10102'!A305 -> 512 | B64: ='ISS10102'!B305 -> 37378 | C64: ='ISS10102'!D305 -> 1500000000 | D64: ='ISS10102'!E305 -> 2703000000 | E64: ='ISS10102'!F305 -> 1203000000 | F64: ='ISS10102'!G305 -> 1500000000 | G64: ='ISS10102'!H305 -> 1484694900 | H64: ='ISS10102'!I305 -> 15305100 | I64: ='ISS10102'!J305 -> 37470 | J64: ='ISS10102'!K305 -> 91 | ... O64: ='ISS10102'!P305 -> 4.0925725 | Q64: ='ISS10102'!Q305 -> 4.1347611 | R64: =+D64/F64 -> 1.802 | U64: =+SUMIF(#REF!,T64,G:G) -> #REF!
A65: ='ISS10102'!A311 -> 513 | B65: ='ISS10102'!B311 -> 37384 | C65: ='ISS10102'!D311 -> 1500000000 | D65: ='ISS10102'!E311 -> 6614600000 | E65: ='ISS10102'!F311 -> 5114600000 | F65: ='ISS10102'!G311 -> 1500000000 | G65: ='ISS10102'!H311 -> 1485140406 | H65: ='ISS10102'!I311 -> 14859594 | I65: ='ISS10102'!J311 -> 37476 | J65: ='ISS10102'!K311 -> 91 | ... O65: ='ISS10102'!P311 -> 3.9734445 | Q65: ='ISS10102'!Q311 -> 4.0132009 | R65: =+D65/F65 -> 4.4097333 | U65: =+SUMIF(#REF!,T65,G:G) -> #REF!
A66: ='ISS10102'!A317 -> 514 | B66: ='ISS10102'!B317 -> 37391 | C66: ='ISS10102'!D317 -> 2000000000 | D66: ='ISS10102'!E317 -> 6479200000 | E66: ='ISS10102'!F317 -> 4479200000 | F66: ='ISS10102'!G317 -> 1999900000 | G66: ='ISS10102'!H317 -> 1980139690 | H66: ='ISS10102'!I317 -> 19760310 | I66: ='ISS10102'!J317 -> 37483 | J66: ='ISS10102'!K317 -> 91 | ... O66: ='ISS10102'!P317 -> 3.9631175 | Q66: ='ISS10102'!Q317 -> 4.0026664 | R66: =+D66/F66 -> 3.239762 | U66: =+SUMIF(#REF!,T66,G:G) -> #REF!
A67: ='ISS10102'!A323 -> 515 | B67: ='ISS10102'!B323 -> 37398 | C67: ='ISS10102'!D323 -> 3000000000 | D67: ='ISS10102'!E323 -> 7232500000 | E67: ='ISS10102'!F323 -> 4232500000 | F67: ='ISS10102'!G323 -> 3000000000 | G67: ='ISS10102'!H323 -> 2969563450 | H67: ='ISS10102'!I323 -> 30436550 | I67: ='ISS10102'!J323 -> 37490 | J67: ='ISS10102'!K323 -> 91 | ... O67: ='ISS10102'!P323 -> 4.0693556 | Q67: ='ISS10102'!Q323 -> 4.1110645 | R67: =+D67/F67 -> 2.4108333 | U67: =+SUMIF(#REF!,T67,G:G) -> #REF!
A68: ='ISS10102'!A330 -> 516 | B68: ='ISS10102'!B330 -> 37405 | C68: ='ISS10102'!D330 -> 4000000000 | D68: ='ISS10102'!E330 -> 10780900000 | E68: ='ISS10102'!F330 -> 6780900000 | F68: ='ISS10102'!G330 -> 4000000000 | G68: ='ISS10102'!H330 -> 3956446402 | H68: ='ISS10102'!I330 -> 43553598 | I68: ='ISS10102'!J330 -> 37497 | J68: ='ISS10102'!K330 -> 91 | ... O68: ='ISS10102'!P330 -> 4.3673251 | Q68: ='ISS10102'!Q330 -> 4.4154017 | R68: =+D68/F68 -> 2.695225 | U68: =+SUMIF(#REF!,T68,G:G) -> #REF!
F69: =SUM(F64:F68) -> 11999900000 | R69: =+D69/F69 -> 0 | U69: =+SUMIF(#REF!,T69,G:G) -> #REF!
A70: ='ISS10102'!A343 -> 517 | B70: ='ISS10102'!B343 -> 37412 | C70: ='ISS10102'!D343 -> 4000000000 | D70: ='ISS10102'!E343 -> 4000000000 | E70: ='ISS10102'!F343 -> 0 | F70: ='ISS10102'!G343 -> 4000000000 | G70: ='ISS10102'!H343 -> 3950748340 | H70: ='ISS10102'!I343 -> 49251660 | I70: ='ISS10102'!J343 -> 37504 | J70: ='ISS10102'!K343 -> 91 | ... O70: ='ISS10102'!P343 -> 4.9386967 | Q70: ='ISS10102'!Q343 -> 5.0002645 | R70: =+D70/F70 -> 1 | U70: =+SUMIF(#REF!,T70,G:G) -> #REF!
A71: ='ISS10102'!A350 -> 518 | B71: ='ISS10102'!B350 -> 37419 | C71: ='ISS10102'!D350 -> 4000000000 | D71: ='ISS10102'!E350 -> 7617200000 | E71: ='ISS10102'!F350 -> 3617200000 | F71: ='ISS10102'!G350 -> 4000000000 | G71: ='ISS10102'!H350 -> 3946995500 | H71: ='ISS10102'!I350 -> 53004500 | I71: ='ISS10102'!J350 -> 37511 | J71: ='ISS10102'!K350 -> 91 | ... O71: ='ISS10102'!P350 -> 5.3150117 | Q71: ='ISS10102'!Q350 -> 5.3863874 | R71: =+D71/F71 -> 1.9043 | U71: =+SUMIF(#REF!,T71,G:G) -> #REF!
A72: ='ISS10102'!A356 -> 519 | B72: ='ISS10102'!B356 -> 37426 | C72: ='ISS10102'!D356 -> 4000000000 | D72: ='ISS10102'!E356 -> 7168800000 | E72: ='ISS10102'!F356 -> 3168800000 | F72: ='ISS10102'!G356 -> 4000000000 | G72: ='ISS10102'!H356 -> 3946472556 | H72: ='ISS10102'!I356 -> 53527444 | I72: ='ISS10102'!J356 -> 37518 | J72: ='ISS10102'!K356 -> 91 | ... O72: ='ISS10102'!P356 -> 5.3674497 | Q72: ='ISS10102'!Q356 -> 5.4402504 | R72: =+D72/F72 -> 1.7922 | U72: =+SUMIF(#REF!,T72,G:G) -> #REF!
A73: ='ISS10102'!A363 -> 520 | B73: ='ISS10102'!B363 -> 37433 | C73: ='ISS10102'!D363 -> 3000000000 | D73: ='ISS10102'!E363 -> 5591800000 | E73: ='ISS10102'!F363 -> 2591800000 | F73: ='ISS10102'!G363 -> 2999800000 | G73: ='ISS10102'!H363 -> 2959268939 | H73: ='ISS10102'!I363 -> 40531061 | I73: ='ISS10102'!J363 -> 37525 | J73: ='ISS10102'!K363 -> 91 | ... O73: ='ISS10102'!P363 -> 5.4193493 | Q73: ='ISS10102'!Q363 -> 5.4935744 | R73: =+D73/F73 -> 1.8640576 | U73: =+SUMIF(#REF!,T73,G:G) -> #REF!
F74: =SUM(F70:F73) -> 14999800000 | R74: =+D74/F74 -> 0 | U74: =+SUMIF(#REF!,T74,G:G) -> #REF!
A75: ='ISS10102'!A376 -> 521 | B75: ='ISS10102'!B376 -> 37440 | C75: ='ISS10102'!D376 -> 3000000000 | D75: ='ISS10102'!E376 -> 3000000000 | E75: ='ISS10102'!F376 -> 0 | F75: ='ISS10102'!G376 -> 3000000000 | G75: ='ISS10102'!H376 -> 2957730049 | H75: ='ISS10102'!I376 -> 42269951 | I75: ='ISS10102'!J376 -> 37532 | J75: ='ISS10102'!K376 -> 91 | ... O75: ='ISS10102'!P376 -> 5.651477 | Q75: ='ISS10102'!Q376 -> 5.7322442 | R75: =+D75/F75 -> 1 | U75: =+SUMIF(#REF!,T75,G:G) -> #REF!
A76: ='ISS10102'!A382 -> 522 | B76: ='ISS10102'!B382 -> 37447 | C76: ='ISS10102'!D382 -> 2000000000 | D76: ='ISS10102'!E382 -> 2000000000 | E76: ='ISS10102'!F382 -> 0 | F76: ='ISS10102'!G382 -> 2000000000 | G76: ='ISS10102'!H382 -> 1970477969 | H76: ='ISS10102'!I382 -> 29522031 | I76: ='ISS10102'!J382 -> 37539 | J76: ='ISS10102'!K382 -> 91 | ... O76: ='ISS10102'!P382 -> 5.9206271 | Q76: ='ISS10102'!Q382 -> 6.0093309 | R76: =+D76/F76 -> 1 | U76: =+SUMIF(#REF!,T76,G:G) -> #REF!
A77: ='ISS10102'!A388 -> 523 | B77: ='ISS10102'!B388 -> 37454 | C77: ='ISS10102'!D388 -> 2000000000 | D77: ='ISS10102'!E388 -> 4386900000 | E77: ='ISS10102'!F388 -> 2386900000 | F77: ='ISS10102'!G388 -> 2000000000 | G77: ='ISS10102'!H388 -> 1971040936 | H77: ='ISS10102'!I388 -> 28959064 | I77: ='ISS10102'!J388 -> 37546 | J77: ='ISS10102'!K388 -> 91 | ... O77: ='ISS10102'!P388 -> 5.8077244 | Q77: ='ISS10102'!Q388 -> 5.893053 | R77: =+D77/F77 -> 2.19345 | U77: =+SUMIF(#REF!,T77,G:G) -> #REF!
A78: ='ISS10102'!A394 -> 524 | B78: ='ISS10102'!B394 -> 37461 | C78: ='ISS10102'!D394 -> 2000000000 | D78: ='ISS10102'!E394 -> 3142300000 | E78: ='ISS10102'!F394 -> 1142300000 | F78: ='ISS10102'!G394 -> 2000000000 | G78: ='ISS10102'!H394 -> 1970277817 | H78: ='ISS10102'!I394 -> 29722183 | I78: ='ISS10102'!J394 -> 37553 | J78: ='ISS10102'!K394 -> 91 | ... O78: ='ISS10102'!P394 -> 5.9607675 | Q78: ='ISS10102'!Q394 -> 6.0506873 | R78: =+D78/F78 -> 1.57115 | U78: =+SUMIF(#REF!,T78,G:G) -> #REF!
A79: ='ISS10102'!A400 -> 525 | B79: ='ISS10102'!B400 -> 37468 | C79: ='ISS10102'!D400 -> 2000000000 | D79: ='ISS10102'!E400 -> 2000000000 | E79: ='ISS10102'!F400 -> 0 | F79: ='ISS10102'!G400 -> 2000000000 | G79: ='ISS10102'!H400 -> 1970280000 | H79: ='ISS10102'!I400 -> 29720000 | I79: ='ISS10102'!J400 -> 37560 | J79: ='ISS10102'!K400 -> 91 | ... O79: ='ISS10102'!P400 -> 5.9603297 | Q79: ='ISS10102'!Q400 -> 6.0502362 | R79: =+D79/F79 -> 1 | U79: =+SUMIF(#REF!,T79,G:G) -> #REF!
F80: =SUM(F75:F79) -> 11000000000 | R80: =+D80/F80 -> 0 | U80: =+SUMIF(#REF!,T80,G:G) -> #REF!
A81: ='ISS10102'!A413 -> 526 | B81: ='ISS10102'!B413 -> 37475 | C81: ='ISS10102'!D413 -> 1000000000 | D81: ='ISS10102'!E413 -> 1774000000 | E81: ='ISS10102'!F413 -> 774000000 | F81: ='ISS10102'!G413 -> 999900000 | G81: ='ISS10102'!H413 -> 985028156 | H81: ='ISS10102'!I413 -> 14871844 | I81: ='ISS10102'!J413 -> 37567 | J81: ='ISS10102'!K413 -> 91 | ... O81: ='ISS10102'!P413 -> 5.9656769 | Q81: ='ISS10102'!Q413 -> 6.055746 | R81: =+D81/F81 -> 1.7741774 | U81: =+SUMIF(#REF!,T81,G:G) -> #REF!
A82: ='ISS10102'!A420 -> 527 | B82: ='ISS10102'!B420 -> 37482 | C82: ='ISS10102'!D420 -> 1000000000 | D82: ='ISS10102'!E420 -> 1000000000 | E82: ='ISS10102'!F420 -> 0 | F82: ='ISS10102'!G420 -> 1000000000 | G82: ='ISS10102'!H420 -> 984909850 | H82: ='ISS10102'!I420 -> 15090150 | I82: ='ISS10102'!J420 -> 37574 | J82: ='ISS10102'!K420 -> 91 | ... O82: ='ISS10102'!P420 -> 6.0526426 | Q82: ='ISS10102'!Q420 -> 6.1453772 | R82: =+D82/F82 -> 1 | U82: =+SUMIF(#REF!,T82,G:G) -> #REF!
A83: ='ISS10102'!A427 -> 528 | B83: ='ISS10102'!B427 -> 37489 | C83: ='ISS10102'!D427 -> 1000000000 | D83: ='ISS10102'!E427 -> 1826200000 | E83: ='ISS10102'!F427 -> 826200000 | F83: ='ISS10102'!G427 -> 1000000000 | G83: ='ISS10102'!H427 -> 983848430 | H83: ='ISS10102'!I427 -> 16151570 | I83: ='ISS10102'!J427 -> 37581 | J83: ='ISS10102'!K427 -> 91 | ... O83: ='ISS10102'!P427 -> 6.478377 | Q83: ='ISS10102'!Q427 -> 6.5847307 | R83: =+D83/F83 -> 1.8262 | U83: =+SUMIF(#REF!,T83,G:G) -> #REF!
A84: =+A83+1 -> 529 | B84: =+B83+7 -> 37496 | C84: 1000000000 | D84: 2129400000 | E84: =D84-C84 -> 1129400000 | F84: 999900000 | G84: 983778397 | H84: =F84-G84 -> 16121603 | I84: =B84+J84+1 -> 37588 | J84: 91 | N84: =G84/F84*100 -> 98.387678 | O84: =(100-N84)/100*(365/91)*100 -> 6.4670039 | Q84: =((100-N84)/N84*(365/91))*100 -> 6.5729815 | R84: =+D84/F84 -> 2.129613 | U84: =+SUMIF(#REF!,T84,G:G) -> #REF!
F85: =SUM(F81:F84) -> 3999800000 | R85: =+D85/F85 -> 0 | U85: =+SUMIF(#REF!,T85,G:G) -> #REF!
R86: =+D86/F86 -> #DIV/0! | U86: =+SUMIF(#REF!,T86,G:G) -> #REF!
R87: =+D87/F87 -> #DIV/0! | U87: =+SUMIF(#REF!,T87,G:G) -> #REF!
A88: =+A84+1 -> 530 | B88: =+B84+7 -> 37503 | C88: 1000000000 | D88: 3736000000 | E88: =D88-C88 -> 2736000000 | F88: 1000000000 | G88: 983917720 | H88: =F88-G88 -> 16082280 | I88: =B88+J88+1 -> 37595 | J88: 91 | N88: =G88/F88*100 -> 98.391772 | O88: =(100-N88)/100*(365/91)*100 -> 6.4505848 | Q88: =((100-N88)/N88*(365/91))*100 -> 6.5560206 | R88: =+D88/F88 -> 3.736 | U88: =+SUMIF(#REF!,T88,G:G) -> #REF!
A89: =+A88+1 -> 531 | B89: =+B88+7 -> 37510 | C89: 2000000000 | D89: 3512000000 | E89: =D89-C89 -> 1512000000 | F89: 2000000000 | G89: 1967962220 | H89: =F89-G89 -> 32037780 | I89: =B89+J89+1 -> 37602 | J89: 91 | N89: =G89/F89*100 -> 98.398111 | O89: =(100-N89)/100*(365/91)*100 -> 6.4251592 | Q89: =((100-N89)/N89*(365/91))*100 -> 6.5297587 | R89: =+D89/F89 -> 1.756 | U89: =+SUMIF(#REF!,T89,G:G) -> #REF!
A90: =+A89+1 -> 532 | B90: =+B89+7 -> 37517 | C90: 2500000000 | D90: 3065000000 | E90: =D90-C90 -> 565000000 | F90: 2500000000 | G90: 2460044700 | H90: =F90-G90 -> 39955300 | I90: =B90+J90+1 -> 37609 | J90: 91 | N90: =G90/F90*100 -> 98.401788 | O90: =(100-N90)/100*(365/91)*100 -> 6.4104108 | Q90: =((100-N90)/N90*(365/91))*100 -> 6.5145267 | R90: =+D90/F90 -> 1.226 | U90: =+SUMIF(#REF!,T90,G:G) -> #REF!
A91: =+A90+1 -> 533 | B91: =+B90+7 -> 37524 | C91: 3000000000 | D91: 3000000000 | E91: =D91-C91 -> 0 | F91: 3000000000 | G91: 2951426673 | H91: =F91-G91 -> 48573327 | I91: =B91+J91+1 -> 37616 | J91: 91 | N91: =G91/F91*100 -> 98.380889 | O91: =(100-N91)/100*(365/91)*100 -> 6.494236 | Q91: =((100-N91)/N91*(365/91))*100 -> 6.6011154 | R91: =+D91/F91 -> 1 | U91: =+SUMIF(#REF!,T91,G:G) -> #REF!
F92: =SUM(F88:F91) -> 8500000000 | R92: =+D92/F92 -> 0 | U92: =+SUMIF(#REF!,T92,G:G) -> #REF!
R93: =+D93/F93 -> #DIV/0! | U93: =+SUMIF(#REF!,T93,G:G) -> #REF!
R94: =+D94/F94 -> #DIV/0! | U94: =+SUMIF(#REF!,T94,G:G) -> #REF!
A95: =+A91+1 -> 534 | B95: =+B91+7 -> 37531 | C95: 2000000000 | D95: 2000000000 | E95: =D95-C95 -> 0 | F95: 2000000000 | G95: 1966362800 | H95: =F95-G95 -> 33637200 | I95: =B95+J95+1 -> 37623 | J95: 91 | N95: =G95/F95*100 -> 98.31814 | O95: =(100-N95)/100*(365/91)*100 -> 6.745922 | Q95: =((100-N95)/N95*(365/91))*100 -> 6.8613198 | R95: =+D95/F95 -> 1 | U95: =+SUMIF(#REF!,T95,G:G) -> #REF!
A96: =+A95+1 -> 535 | B96: =+B95+8 -> 37539 | C96: 2000000000 | D96: 2000000000 | E96: =D96-C96 -> 0 | F96: 2000000000 | G96: 1966360000 | H96: =F96-G96 -> 33640000 | I96: =B96+J96+1 -> 37631 | J96: 91 | N96: =G96/F96*100 -> 98.318 | O96: =(100-N96)/100*(365/91)*100 -> 6.7464835 | Q96: =((100-N96)/N96*(365/91))*100 -> 6.8619007 | R96: =+D96/F96 -> 1 | U96: =+SUMIF(#REF!,T96,G:G) -> #REF!
A97: =+A96+1 -> 536 | B97: =+B96+6 -> 37545 | C97: 8000000000 | D97: 8000000000 | E97: =D97-C97 -> 0 | F97: 8000000000 | G97: 7855201300 | H97: =F97-G97 -> 144798700 | I97: =B97+J97+1 -> 37637 | J97: 91 | N97: =G97/F97*100 -> 98.190016 | O97: =(100-N97)/100*(365/91)*100 -> 7.2598249 | Q97: =((100-N97)/N97*(365/91))*100 -> 7.3936488 | R97: =+D97/F97 -> 1 | U97: =+SUMIF(#REF!,T97,G:G) -> #REF!
A98: =+A97+1 -> 537 | B98: =+B97+7 -> 37552 | C98: 4000000000 | D98: 4000000000 | E98: =D98-C98 -> 0 | F98: 4000000000 | G98: 3930951424 | H98: =F98-G98 -> 69048576 | I98: =B98+J98+1 -> 37644 | J98: 91 | N98: =G98/F98*100 -> 98.273786 | O98: =(100-N98)/100*(365/91)*100 -> 6.923827 | Q98: =((100-N98)/N98*(365/91))*100 -> 7.0454465 | R98: =+D98/F98 -> 1 | U98: =+SUMIF(#REF!,T98,G:G) -> #REF!
A99: =+A98+1 -> 538 | B99: =+B98+7 -> 37559 | C99: 4000000000 | D99: 4000000000 | E99: =D99-C99 -> 0 | F99: 4000000000 | G99: 3927212000 | H99: =F99-G99 -> 72788000 | I99: =B99+J99+1 -> 37651 | J99: 91 | N99: =G99/F99*100 -> 98.1803 | O99: =(100-N99)/100*(365/91)*100 -> 7.2987967 | Q99: =((100-N99)/N99*(365/91))*100 -> 7.4340746 | R99: =+D99/F99 -> 1 | U99: =+SUMIF(#REF!,T99,G:G) -> #REF!
F100: =SUM(F95:F99) -> 20000000000 | H100: =SUM(H95:H99) -> 353912476 | R100: =+D100/F100 -> 0 | U100: =+SUMIF(#REF!,T100,G:G) -> #REF!
R101: =+D101/F101 -> #DIV/0! | U101: =+SUMIF(#REF!,T101,G:G) -> #REF!
R102: =+D102/F102 -> #DIV/0! | U102: =+SUMIF(#REF!,T102,G:G) -> #REF!
...

Sheet maturities - 182
A2: Ref:ISS9899. WK3
A3: worksheet b
A4: - | B4: - | C4: - | D4: - | E4: - | F4: - | G4: - | H4: - | I4: - | J4: - | K4: - | L4: - | M4: - | N4: - | O4: -
A5: Auction | B5: Issue date | C5: Amount offered | D5: Total bids | E5: Over/(Under) | F5: Face Value of | G5: Cost Value | H5: Interest due | I5: Date due | J5: Duration | K5: Implicit annual | L5: Clearing | M5: Lowest | N5: Weighted | O5: Average | P5: Money Market | Q5: Annualised | R5: Rejected Amount | S5: Bid-to-cover
A6: No | C6: in | D6: (Competitive & | E6: Subscribed | F6: issues | K6: interest rate | L6: factor | M6: factor | N6: Average | O6: Discount | Q6: yield
C7: Auction | D7: Uncompetitive) | L7: (%) | M7: (%) | N7: Price | O7: factor
B8: (1) | C8: (1a) | D8: (1b) | F8: (2) | G8: (3) | H8: (4) | I8: (5) | J8: (6) | K8: -9 | L8: -10 | M8: -11 | N8: (12) | O8: (13)
A9: - | B9: - | C9: - | D9: - | E9: - | F9: - | G9: - | H9: - | I9: - | J9: - | K9: - | L9: - | M9: - | N9: - | O9: - | Q9: -
A10: 469 | B10: 37076 | C10: ='ISS10102'!D12 -> 1500000000 | D10: ='ISS10102'!E12 -> 2670000000 | E10: ='ISS10102'!F12 -> 1170000000 | F10: ='ISS10102'!G12 -> 1500000000 | G10: ='ISS10102'!H12 -> 1440153500 | H10: ='ISS10102'!I12 -> 59846500 | I10: ='ISS10102'!J12 -> 37259 | J10: ='ISS10102'!K12 -> 182 | M10: ='ISS10102'!N12 -> 7.621 | N10: ='ISS10102'!O12 -> 96.010233 | O10: ='ISS10102'!P12 -> 8.0014551 | Q10: =((100-N10)/N10*(365/182))*100 -> 8.3339607 | R10: =((100-O10)/O10*(365/182))*100 -> 2305.8628 | AA10: =2+1.5+1.5+1.5+1.5+1.5+1.5+2+2+2.5+3.5+3.5+3.5+3.4+3+3+3+1.5+11.5+11+10.99+9.99+9.99+10.99+10.99+8.99+11 -> 137.34
A11: =A10+1 -> 470 | B11: =B10+7 -> 37083 | C11: ='ISS10102'!D17 -> 2000000000 | D11: ='ISS10102'!E17 -> 2030000000 | E11: ='ISS10102'!F17 -> 30000000 | F11: ='ISS10102'!G17 -> 2000000000 | G11: ='ISS10102'!H17 -> 1895843600 | H11: ='ISS10102'!I17 -> 104156400 | I11: ='ISS10102'!J17 -> 37266 | J11: ='ISS10102'!K17 -> 182 | M11: ='ISS10102'!N17 -> 7.85 | N11: ='ISS10102'!O17 -> 94.79218 | O11: ='ISS10102'!P17 -> 10.444254 | Q11: =((100-N11)/N11*(365/182))*100 -> 11.018055 | R11: =((100-O11)/O11*(365/182))*100 -> 1719.6398
A12: =A11+1 -> 471 | B12: =B11+7 -> 37090 | C12: ='ISS10102'!D22 -> 2000000000 | D12: ='ISS10102'!E22 -> 3088900000 | E12: ='ISS10102'!F22 -> 1088900000 | F12: ='ISS10102'!G22 -> 2000000000 | G12: ='ISS10102'!H22 -> 1878252919 | H12: ='ISS10102'!I22 -> 121747081 | I12: ='ISS10102'!J22 -> 37273 | J12: ='ISS10102'!K22 -> 182 | M12: ='ISS10102'!N22 -> 11.03 | N12: ='ISS10102'!O22 -> 93.912646 | O12: ='ISS10102'!P22 -> 12.208155 | Q12: =((100-N12)/N12*(365/182))*100 -> 12.999479 | R12: =((100-O12)/O12*(365/182))*100 -> 1442.2004
A13: =A12+1 -> 472 | B13: =B12+7 -> 37097 | C13: ='ISS10102'!D27 -> 4000000000 | D13: ='ISS10102'!E27 -> 4000000000 | E13: ='ISS10102'!F27 -> 0 | F13: ='ISS10102'!G27 -> 4000000000 | G13: ='ISS10102'!H27 -> 3676427332 | H13: ='ISS10102'!I27 -> 323572668 | I13: ='ISS10102'!J27 -> 37280 | J13: ='ISS10102'!K27 -> 182 | M13: ='ISS10102'!N27 -> 9.999 | N13: ='ISS10102'!O27 -> 91.910683 | O13: ='ISS10102'!P27 -> 16.22308 | Q13: =((100-N13)/N13*(365/182))*100 -> 17.650919 | R13: =((100-O13)/O13*(365/182))*100 -> 1035.6489
B15: Total July 2001 | C15: =SUM(C10:C13) -> 9500000000 | D15: =SUM(D10:D13) -> 11788900000 | E15: =SUM(E10:E13) -> 2288900000 | F15: =SUM(F10:F13) -> 9500000000 | G15: =SUM(G10:G13) -> 8890677351 | H15: =SUM(H10:H13) -> 609322649 | N15: =AVERAGEA(N10:N13) -> 94.156436 | O15: =AVERAGEA(O10:O13) -> 11.719236 | Q15: =AVERAGEA(Q10:Q13) -> 12.500603 | R15: =((100-O15)/O15*(365/182))*100 -> 1510.7349
W16: 2001 | X16: =+SUMIF(#REF!,W16,G:G) -> #REF!
A17: =A13+1 -> 473 | B17: =B13+7 -> 37104 | C17: ='ISS10102'!D37 -> 4000000000 | D17: ='ISS10102'!E37 -> 8279400000 | E17: ='ISS10102'!F37 -> 4279400000 | F17: ='ISS10102'!G37 -> 4000000000 | G17: ='ISS10102'!H37 -> 3670506802 | H17: ='ISS10102'!I37 -> 329493198 | I17: ='ISS10102'!J37 -> 37287 | J17: ='ISS10102'!K37 -> 182 | M17: ='ISS10102'!N37 -> 13.116 | N17: ='ISS10102'!O37 -> 91.76267 | O17: ='ISS10102'!P37 -> 16.51992 | Q17: =((100-N17)/N17*(365/182))*100 -> 18.002876 | R17: =((100-O17)/O17*(365/182))*100 -> 1013.4362 | W17: 2002 | X17: =+SUMIF(#REF!,W17,G:G) -> #REF!
A18: =A17+1 -> 474 | B18: =B17+7 -> 37111 | C18: ='ISS10102'!D42 -> 4000000000 | D18: ='ISS10102'!E42 -> 6417600000 | E18: ='ISS10102'!F42 -> 2417600000 | F18: ='ISS10102'!G42 -> 4000000000 | G18: ='ISS10102'!H42 -> 3670675212 | H18: ='ISS10102'!I42 -> 329324788 | I18: ='ISS10102'!J42 -> 37294 | J18: ='ISS10102'!K42 -> 182 | M18: ='ISS10102'!N42 -> 14.038 | N18: ='ISS10102'!O42 -> 91.76688 | O18: ='ISS10102'!P42 -> 16.511476 | Q18: =((100-N18)/N18*(365/182))*100 -> 17.992849 | R18: =((100-O18)/O18*(365/182))*100 -> 1014.057 | W18: 2003 | X18: =+SUMIF(#REF!,W18,G:G) -> #REF!
A19: =A18+1 -> 475 | B19: =B18+7 -> 37118 | C19: ='ISS10102'!D47 -> 4000000000 | D19: ='ISS10102'!E47 -> 9595200000 | E19: ='ISS10102'!F47 -> 5595200000 | F19: ='ISS10102'!G47 -> 4000000000 | G19: ='ISS10102'!H47 -> 3683572728 | H19: ='ISS10102'!I47 -> 316427272 | I19: =I18+7 -> 37301 | J19: ='ISS10102'!K47 -> 182 | M19: ='ISS10102'!N47 -> 15.673 | N19: ='ISS10102'!O47 -> 92.089318 | O19: ='ISS10102'!P47 -> 15.864829 | Q19: =((100-N19)/N19*(365/182))*100 -> 17.227654 | R19: =((100-O19)/O19*(365/182))*100 -> 1063.5641 | W19: 2004 | X19: =+SUMIF(#REF!,W19,G:G) -> #REF!
A20: =A19+1 -> 476 | B20: =B19+7 -> 37125 | C20: ='ISS10102'!D52 -> 4000000000 | D20: ='ISS10102'!E52 -> 7640300000 | E20: ='ISS10102'!F52 -> 3640300000 | F20: ='ISS10102'!G52 -> 4000000000 | G20: ='ISS10102'!H52 -> 3684876740 | H20: ='ISS10102'!I52 -> 315123260 | I20: =I19+7 -> 37308 | J20: ='ISS10102'!K52 -> 182 | M20: ='ISS10102'!N52 -> 14.941 | N20: ='ISS10102'!O52 -> 92.121918 | O20: ='ISS10102'!P52 -> 15.799449 | Q20: =((100-N20)/N20*(365/182))*100 -> 17.150586 | R20: =((100-O20)/O20*(365/182))*100 -> 1068.7951 | W20: 2005 | X20: =+SUMIF(#REF!,W20,G:G) -> #REF!
A21: =A20+1 -> 477 | B21: =B20+7 -> 37132 | C21: ='ISS10102'!D57 -> 3000000000 | D21: ='ISS10102'!E57 -> 6817700000 | E21: ='ISS10102'!F57 -> 3817700000 | F21: ='ISS10102'!G57 -> 3000000000 | G21: ='ISS10102'!H57 -> 2772024660 | H21: ='ISS10102'!I57 -> 227975340 | I21: =I20+7 -> 37315 | J21: ='ISS10102'!K57 -> 182 | M21: ='ISS10102'!N57 -> 14.379 | N21: ='ISS10102'!O57 -> 92.400822 | O21: ='ISS10102'!P57 -> 15.24011 | Q21: =((100-N21)/N21*(365/182))*100 -> 16.493479 | R21: =((100-O21)/O21*(365/182))*100 -> 1115.3824 | W21: 2006 | X21: =+SUMIF(#REF!,W21,G:G) -> #REF!
W22: 2007 | X22: =+SUMIF(#REF!,W22,G:G) -> #REF!
B23: Total Aug 2001 | C23: =SUM(C17:C21) -> 19000000000 | D23: =SUM(D17:D21) -> 38750200000 | E23: =SUM(E17:E21) -> 19750200000 | F23: =SUM(F17:F21) -> 19000000000 | G23: =SUM(G17:G21) -> 17481656142 | H23: =SUM(H17:H21) -> 1518343858 | N23: =AVERAGEA(N17:N21) -> 92.028322 | O23: =AVERAGEA(O17:O21) -> 15.987157 | Q23: =AVERAGEA(Q17:Q21) -> 17.373489 | R23: =((100-O23)/O23*(365/182))*100 -> 1053.8916 | W23: 2008 | X23: =+SUMIF(#REF!,W23,G:G) -> #REF!
W24: 2009 | X24: =+SUMIF(#REF!,W24,G:G) -> #REF!
A25: =A21+1 -> 478 | B25: =B21+7 -> 37139 | C25: ='ISS10102'!D67 -> 4000000000 | D25: ='ISS10102'!E67 -> 4000000000 | E25: ='ISS10102'!F67 -> 0 | F25: ='ISS10102'!G67 -> 4000000000 | G25: ='ISS10102'!H67 -> 3697377278 | H25: =F25-G25 -> 302622722 | I25: =I21+7 -> 37322 | J25: ='ISS10102'!K67 -> 182 | M25: 14 | N25: ='ISS10102'!O67 -> 92.434432 | O25: ='ISS10102'!P67 -> 15.172705 | Q25: =((100-N25)/N25*(365/182))*100 -> 16.41456 | R25: =((100-O25)/O25*(365/182))*100 -> 1121.2284 | W25: 2010 | X25: =+SUMIF(#REF!,W25,G:G) -> #REF!
A26: 479 | B26: =B25+7 -> 37146 | C26: ='ISS10102'!D72 -> 4000000000 | D26: ='ISS10102'!E72 -> 10703100000 | E26: ='ISS10102'!F72 -> 6703100000 | F26: ='ISS10102'!G72 -> 3999900000 | G26: ='ISS10102'!H72 -> 3719315125 | H26: =F26-G26 -> 280584875 | I26: =I25+7 -> 37329 | J26: ='ISS10102'!K72 -> 182 | M26: 13 | N26: ='ISS10102'!O72 -> 92.985203 | O26: ='ISS10102'!P72 -> 14.068137 | Q26: =((100-N26)/N26*(365/182))*100 -> 15.129437 | R26: =((100-O26)/O26*(365/182))*100 -> 1225.0085 | W26: 2011 | X26: =+SUMIF(#REF!,W26,G:G) -> #REF!
A27: 480 | B27: =B26+7 -> 37153 | C27: ='ISS10102'!D77 -> 4000000000 | D27: ='ISS10102'!E77 -> 6831500000 | E27: ='ISS10102'!F77 -> 2831500000 | F27: ='ISS10102'!G77 -> 4000000000 | G27: ='ISS10102'!H77 -> 3719466530 | H27: =F27-G27 -> 280533470 | I27: =I26+7 -> 37336 | J27: ='ISS10102'!K77 -> 182 | M27: ='ISS10102'!N77 -> 13 | N27: ='ISS10102'!O77 -> 92.986663 | O27: ='ISS10102'!P77 -> 14.065208 | Q27: =((100-N27)/N27*(365/182))*100 -> 15.126049 | R27: =((100-O27)/O27*(365/182))*100 -> 1225.3054 | W27: 2012 | X27: =+SUMIF(#REF!,W27,G:G) -> #REF!
A28: 481 | B28: =B27+7 -> 37160 | C28: ='ISS10102'!D82 -> 3000000000 | D28: ='ISS10102'!E82 -> 7517600000 | E28: ='ISS10102'!F82 -> 4517600000 | F28: ='ISS10102'!G82 -> 3000000000 | G28: ='ISS10102'!H82 -> 2804464804 | H28: =F28-G28 -> 195535196 | I28: =I27+7 -> 37343 | J28: ='ISS10102'!K82 -> 182 | M28: ='ISS10102'!N82 -> 12.234 | N28: ='ISS10102'!O82 -> 93.48216 | O28: ='ISS10102'!P82 -> 13.071492 | Q28: =((100-N28)/N28*(365/182))*100 -> 13.982873 | R28: =((100-O28)/O28*(365/182))*100 -> 1333.7012 | W28: 2013 | X28: =+SUMIF(#REF!,W28,G:G) -> #REF!
W29: 2014 | X29: =+SUMIF(#REF!,W29,G:G) -> #REF!
B30: Total Sep 2001 | C30: =SUM(C25:C28) -> 15000000000 | D30: =SUM(D25:D28) -> 29052200000 | E30: =SUM(E25:E28) -> 14052200000 | F30: =SUM(F25:F28) -> 14999900000 | G30: =SUM(G25:G28) -> 13940623737 | H30: =SUM(H25:H28) -> 1059276263 | N30: =AVERAGEA(N25:N28) -> 92.972115 | O30: =AVERAGEA(O25:O28) -> 14.094386 | Q30: =AVERAGEA(Q25:Q28) -> 15.16323 | R30: =((100-O30)/O30*(365/182))*100 -> 1222.3536 | W30: 2015 | X30: =+SUMIF(#REF!,W30,G:G) -> #REF!
W31: 2016 | X31: =+SUMIF(#REF!,W31,G:G) -> #REF!
A32: 482 | B32: 37167 | C32: ='ISS10102'!D92 -> 3000000000 | D32: ='ISS10102'!E92 -> 7190900000 | E32: ='ISS10102'!F92 -> 4190900000 | F32: ='ISS10102'!G92 -> 2999900000 | G32: ='ISS10102'!H92 -> 2814589727 | H32: =F32-G32 -> 185310273 | I32: =I28+7 -> 37350 | J32: ='ISS10102'!K92 -> 182 | M32: ='ISS10102'!N92 -> 11.766 | N32: ='ISS10102'!O92 -> 93.822785 | O32: ='ISS10102'!P92 -> 12.388371 | Q32: =((100-N32)/N32*(365/182))*100 -> 13.204011 | R32: =((100-O32)/O32*(365/182))*100 -> 1418.3031 | W32: 2017 | X32: =+SUMIF(#REF!,W32,G:G) -> #REF!
A33: =A32+1 -> 483 | B33: =B32+7 -> 37174 | C33: ='ISS10102'!D97 -> 3000000000 | D33: ='ISS10102'!E97 -> 7100500000 | E33: ='ISS10102'!F97 -> 4100500000 | F33: ='ISS10102'!G97 -> 2999900000 | G33: ='ISS10102'!H97 -> 2826262928 | H33: =F33-G33 -> 173637072 | I33: =B33+J33+1 -> 37357 | J33: ='ISS10102'!K97 -> 182 | M33: ='ISS10102'!N97 -> 11.205 | N33: ='ISS10102'!O97 -> 94.211905 | O33: ='ISS10102'!P97 -> 11.607993 | Q33: =((100-N33)/N33*(365/182))*100 -> 12.321154 | R33: =((100-O33)/O33*(365/182))*100 -> 1527.1346 | W33: 2018 | X33: =+SUMIF(#REF!,W33,G:G) -> #REF!
A34: =A33+1 -> 484 | B34: =B33+7 -> 37181 | C34: ='ISS10102'!D102 -> 3000000000 | D34: ='ISS10102'!E102 -> 12000600000 | E34: ='ISS10102'!F102 -> 9000600000 | F34: ='ISS10102'!G102 -> 3000000000 | G34: ='ISS10102'!H102 -> 2846426314 | H34: =F34-G34 -> 153573686 | I34: =B34+J34+1 -> 37364 | J34: ='ISS10102'!K102 -> 182 | M34: ='ISS10102'!N102 -> 9.001 | N34: ='ISS10102'!O102 -> 94.880877 | O34: ='ISS10102'!P102 -> 10.266373 | Q34: =((100-N34)/N34*(365/182))*100 -> 10.820276 | R34: =((100-O34)/O34*(365/182))*100 -> 1752.9102 | W34: 2019 | X34: =+SUMIF(#REF!,W34,G:G) -> #REF!
A35: =A34+1 -> 485 | B35: =B34+7 -> 37188 | C35: ='ISS10102'!D107 -> 3000000000 | D35: ='ISS10102'!E107 -> 4935300000 | E35: ='ISS10102'!F107 -> 1935300000 | F35: ='ISS10102'!G107 -> 2999900000 | G35: ='ISS10102'!H107 -> 2854346884 | H35: =F35-G35 -> 145553116 | I35: =B35+J35+1 -> 37371 | J35: ='ISS10102'!K107 -> 182 | M35: ='ISS10102'!N107 -> 8.686 | N35: ='ISS10102'!O107 -> 95.148068 | O35: ='ISS10102'!P107 -> 9.7305235 | Q35: =((100-N35)/N35*(365/182))*100 -> 10.226717 | R35: =((100-O35)/O35*(365/182))*100 -> 1860.4851 | W35: 2020 | X35: =+SUMIF(#REF!,W35,G:G) -> #REF!
A36: =A35+1 -> 486 | B36: =B35+7 -> 37195 | C36: ='ISS10102'!D112 -> 2000000000 | D36: ='ISS10102'!E112 -> 5738800000 | E36: ='ISS10102'!F112 -> 3738800000 | F36: ='ISS10102'!G112 -> 2000000000 | G36: ='ISS10102'!H112 -> 1906225848 | H36: =F36-G36 -> 93774152 | I36: =B36+J36+1 -> 37378 | J36: ='ISS10102'!K112 -> 182 | M36: ='ISS10102'!N112 -> 9.071 | N36: ='ISS10102'!O112 -> 95.311292 | O36: ='ISS10102'!P112 -> 9.4031773 | Q36: =((100-N36)/N36*(365/182))*100 -> 9.8657537 | R36: =((100-O36)/O36*(365/182))*100 -> 1932.2344 | W36: 2021 | X36: =+SUMIF(#REF!,W36,G:G) -> #REF!
W37: 2022 | X37: =+SUMIF(#REF!,W37,G:G) -> #REF!
B38: Total Oct 2001 | C38: =SUM(C32:C36) -> 14000000000 | D38: =SUM(D32:D36) -> 36966100000 | E38: =SUM(E32:E36) -> 22966100000 | F38: =SUM(F32:F36) -> 13999700000 | G38: =SUM(G32:G36) -> 13247851701 | H38: =SUM(H32:H36) -> 751848299 | N38: =AVERAGEA(N32:N36) -> 94.674985 | O38: =AVERAGEA(O32:O36) -> 10.679288 | Q38: =AVERAGEA(Q32:Q36) -> 11.287582 | R38: =((100-O38)/O38*(365/182))*100 -> 1677.3797
F39: =SUM(F32:F35) -> 11999700000
A40: =A36+1 -> 487 | B40: =B36+7 -> 37202 | C40: ='ISS10102'!D122 -> 3000000000 | D40: ='ISS10102'!E122 -> 5866400000 | E40: ='ISS10102'!F122 -> 2866400000 | F40: ='ISS10102'!G122 -> 3000000000 | G40: ='ISS10102'!H122 -> 2865331424 | H40: =F40-G40 -> 134668576 | I40: =B40+J40+1 -> 37385 | J40: ='ISS10102'!K122 -> 182 | M40: ='ISS10102'!N122 -> 3.61 | N40: ='ISS10102'!O122 -> 95.511047 | O40: ='ISS10102'!P122 -> 9.0025696 | Q40: =((100-N40)/N40*(365/182))*100 -> 9.4256841 | R40: =((100-O40)/O40*(365/182))*100 -> 2027.1417
A41: =A40+1 -> 488 | B41: =B40+7 -> 37209 | C41: ='ISS10102'!D127 -> 4000000000 | D41: ='ISS10102'!E127 -> 11313500000 | E41: ='ISS10102'!F127 -> 7313500000 | F41: ='ISS10102'!G127 -> 4000000000 | G41: ='ISS10102'!H127 -> 3828537535 | H41: =F41-G41 -> 171462465 | I41: =B41+J41+1 -> 37392 | J41: ='ISS10102'!K127 -> 182 | M41: ='ISS10102'!N127 -> 8.251 | N41: ='ISS10102'!O127 -> 95.713438 | O41: ='ISS10102'!P127 -> 8.5966758 | Q41: =((100-N41)/N41*(365/182))*100 -> 8.9816811 | R41: =((100-O41)/O41*(365/182))*100 -> 2132.3226
A42: =A41+1 -> 489 | B42: =B41+7 -> 37216 | C42: ='ISS10102'!D132 -> 4000000000 | D42: ='ISS10102'!E132 -> 9885000000 | E42: ='ISS10102'!F132 -> 5885000000 | F42: ='ISS10102'!G132 -> 4000000000 | G42: ='ISS10102'!H132 -> 3833158200 | H42: =F42-G42 -> 166841800 | I42: =B42+J42+1 -> 37399 | J42: ='ISS10102'!K132 -> 182 | M42: ='ISS10102'!N132 -> 8.253 | N42: ='ISS10102'!O132 -> 95.828955 | O42: ='ISS10102'!P132 -> 8.3650078 | Q42: =((100-N42)/N42*(365/182))*100 -> 8.7291026 | R42: =((100-O42)/O42*(365/182))*100 -> 2196.9313
A43: =A42+1 -> 490 | B43: =B42+7 -> 37223 | C43: ='ISS10102'!D137 -> 4000000000 | D43: ='ISS10102'!E137 -> 7637500000 | E43: ='ISS10102'!F137 -> 3637500000 | F43: ='ISS10102'!G137 -> 4000000000 | G43: ='ISS10102'!H137 -> 3833600625 | H43: =F43-G43 -> 166399375 | I43: =B43+J43+1 -> 37406 | J43: ='ISS10102'!K137 -> 182 | M43: ='ISS10102'!N137 -> 8.19 | N43: ='ISS10102'!O137 -> 95.840016 | O43: ='ISS10102'!P137 -> 8.3428258 | Q43: =((100-N43)/N43*(365/182))*100 -> 8.7049504 | R43: =((100-O43)/O43*(365/182))*100 -> 2203.3057
F44: =SUM(F40:F43)+F36 -> 17000000000
B45: Total Nov 2001 | C45: =SUM(C40:C43) -> 15000000000 | D45: =SUM(D40:D43) -> 34702400000 | E45: =SUM(E40:E43) -> 19702400000 | F45: =SUM(F40:F43) -> 15000000000 | G45: =SUM(G40:G43) -> 14360627784 | H45: =SUM(H40:H43) -> 639372216 | N45: =AVERAGEA(N40:N43) -> 95.723364 | O45: =AVERAGEA(O40:O43) -> 8.5767698 | Q45: =AVERAGEA(Q40:Q43) -> 8.9603546 | R45: =((100-O45)/O45*(365/182))*100 -> 2137.7371
A47: =A43+1 -> 491 | B47: =B43+7 -> 37230 | C47: ='ISS10102'!D147 -> 4000000000 | D47: ='ISS10102'!E147 -> 11106500000 | E47: ='ISS10102'!F147 -> 7106500000 | F47: ='ISS10102'!G147 -> 4000000000 | G47: ='ISS10102'!H147 -> 3839475730 | H47: =F47-G47 -> 160524270 | I47: =B47+J47+1 -> 37413 | J47: 182 | M47: ='ISS10102'!N147 -> 7.749 | N47: ='ISS10102'!O147 -> 95.986893 | O47: ='ISS10102'!P147 -> 8.0482635 | Q47: =((100-N47)/N47*(365/182))*100 -> 8.3847526 | R47: =((100-O47)/O47*(365/182))*100 -> 2291.2856
A48: =A47+1 -> 492 | B48: =B47+7 -> 37237 | C48: ='ISS10102'!D152 -> 4000000000 | D48: ='ISS10102'!E152 -> 9110200000 | E48: ='ISS10102'!F152 -> 5110200000 | F48: ='ISS10102'!G152 -> 4000000000 | G48: ='ISS10102'!H152 -> 3858485634 | H48: =F48-G48 -> 141514366 | I48: =B48+J48+1 -> 37420 | J48: 182 | M48: ='ISS10102'!N152 -> 6.839 | N48: ='ISS10102'!O152 -> 96.462141 | O48: ='ISS10102'!P152 -> 7.0951571 | Q48: =((100-N48)/N48*(365/182))*100 -> 7.3553801 | R48: =((100-O48)/O48*(365/182))*100 -> 2626.0187
A49: =A48+1 -> 493 | B49: =B48+7 -> 37244 | C49: ='ISS10102'!D157 -> 4000000000 | D49: ='ISS10102'!E157 -> 6966600000 | E49: ='ISS10102'!F157 -> 2966600000 | F49: ='ISS10102'!G157 -> 4000000000 | G49: ='ISS10102'!H157 -> 3861468722 | H49: =F49-G49 -> 138531278 | I49: =B49+J49+1 -> 37427 | J49: 182 | M49: ='ISS10102'!N157 -> 6.5 | N49: ='ISS10102'!O157 -> 96.536718 | O49: ='ISS10102'!P157 -> 6.9455929 | Q49: =((100-N49)/N49*(365/182))*100 -> 7.194768 | R49: =((100-O49)/O49*(365/182))*100 -> 2686.8851
A50: =A49+1 -> 494 | B50: =B49+7 -> 37251 | C50: ='ISS10102'!D162 -> 3000000000 | D50: ='ISS10102'!E162 -> 4383000000 | E50: ='ISS10102'!F162 -> 1383000000 | F50: ='ISS10102'!G162 -> 3000000000 | G50: ='ISS10102'!H162 -> 2894601610 | H50: =F50-G50 -> 105398390 | I50: =B50+J50+1 -> 37434 | J50: 182 | M50: ='ISS10102'!N162 -> 6.765 | N50: ='ISS10102'!O162 -> 96.48672 | O50: ='ISS10102'!P162 -> 7.0458631 | Q50: =((100-N50)/N50*(365/182))*100 -> 7.3024174 | R50: =((100-O50)/O50*(365/182))*100 -> 2645.7938
A52: =A50+1 -> 495 | B52: =B50+7 -> 37258 | C52: 2000000000 | D52: 7495500000 | E52: =D52-C52 -> 5495500000 | F52: 2000000000 | G52: 1931352980 | H52: =F52-G52 -> 68647020 | I52: =B52+J52+1 -> 37441 | J52: 182 | M52: 6.7 | N52: =G52/F52*100 -> 96.567649 | O52: =(100-N52)/100*(365/182)*100 -> 6.8835611 | Q52: =((100-N52)/N52*(365/182))*100 -> 7.1282268 | R52: =((100-O52)/O52*(365/182))*100 -> 2712.9055
A53: =A52+1 -> 496 | B53: =B52+6 -> 37264 | C53: 3000000000 | D53: 7667500000 | E53: =D53-C53 -> 4667500000 | F53: 2999900000 | G53: 2902822848 | H53: =F53-G53 -> 97077152 | I53: =B53+J53+1 -> 37447 | J53: 182 | M53: 6.299 | N53: =G53/F53*100 -> 96.763987 | O53: =(100-N53)/100*(365/182)*100 -> 6.4898062 | Q53: =((100-N53)/N53*(365/182))*100 -> 6.7068404 | R53: =((100-O53)/O53*(365/182))*100 -> 2889.6731
A54: =A53+1 -> 497 | B54: =B53+7 -> 37271 | C54: 4000000000 | D54: 11025600000 | E54: =D54-C54 -> 7025600000 | F54: 4000000000 | G54: 3871933284 | H54: =F54-G54 -> 128066716 | I54: =B54+J54+1 -> 37454 | J54: 182 | M54: 6.317 | N54: =G54/F54*100 -> 96.798332 | O54: =(100-N54)/100*(365/182)*100 -> 6.4209274 | Q54: =((100-N54)/N54*(365/182))*100 -> 6.6333037 | R54: =((100-O54)/O54*(365/182))*100 -> 2922.8226
A55: =A54+1 -> 498 | B55: =B54+7 -> 37278 | C55: 3000000000 | D55: 8421000000 | E55: =D55-C55 -> 5421000000 | F55: 3000000000 | G55: 2906904950 | H55: =F55-G55 -> 93095050 | I55: =B55+J55+1 -> 37461 | J55: 182 | M55: 6.203 | N55: =G55/F55*100 -> 96.896832 | O55: =(100-N55)/100*(365/182)*100 -> 6.223387 | Q55: =((100-N55)/N55*(365/182))*100 -> 6.4226941 | R55: =((100-O55)/O55*(365/182))*100 -> 3021.9635
A56: =A55+1 -> 499 | B56: =B55+7 -> 37285 | C56: 3000000000 | D56: 6325300000 | E56: =D56-C56 -> 3325300000 | F56: 3000000000 | G56: 2911298855 | H56: =F56-G56 -> 88701145 | I56: =B56+J56+1 -> 37468 | J56: 182 | M56: 5.836 | N56: =G56/F56*100 -> 97.043295 | O56: =(100-N56)/100*(365/182)*100 -> 5.9296553 | Q56: =((100-N56)/N56*(365/182))*100 -> 6.1103194 | R56: =((100-O56)/O56*(365/182))*100 -> 3181.594
A60: =A56+1 -> 500 | B60: =B56+7 -> 37292 | C60: 2000000000 | D60: 4983500000 | E60: =D60-C60 -> 2983500000 | F60: 2000000000 | G60: 1944253099 | H60: =F60-G60 -> 55746901 | I60: =B60+J60+1 -> 37475 | J60: 182 | M60: 5.311 | N60: =G60/F60*100 -> 97.212655 | O60: =(100-N60)/100*(365/182)*100 -> 5.5900052 | Q60: =((100-N60)/N60*(365/182))*100 -> 5.7502855 | R60: =((100-O60)/O60*(365/182))*100 -> 3387.0939
A61: =A60+1 -> 501 | B61: =B60+7 -> 37299 | C61: 3000000000 | D61: 7872500000 | E61: =D61-C61 -> 4872500000 | F61: 3000000000 | G61: 2921842096 | H61: =F61-G61 -> 78157904 | I61: =B61+J61+1 -> 37482 | J61: 182 | M61: 5 | N61: =G61/F61*100 -> 97.394737 | O61: =(100-N61)/100*(365/182)*100 -> 5.2248416 | Q61: =((100-N61)/N61*(365/182))*100 -> 5.3646036 | R61: =((100-O61)/O61*(365/182))*100 -> 3637.8339
A62: =A61+1 -> 502 | B62: =B61+7 -> 37306 | C62: 4000000000 | D62: 8344800000 | E62: =D62-C62 -> 4344800000 | F62: 4000000000 | G62: 3901330197 | H62: =F62-G62 -> 98669803 | I62: =B62+J62+1 -> 37489 | J62: 182 | M62: 5 | N62: =G62/F62*100 -> 97.533255 | O62: =(100-N62)/100*(365/182)*100 -> 4.9470437 | Q62: =((100-N62)/N62*(365/182))*100 -> 5.072161 | R62: =((100-O62)/O62*(365/182))*100 -> 3853.3757
A63: =A62+1 -> 503 | B63: =B62+7 -> 37313 | C63: 4000000000 | D63: 11791300000 | E63: =D63-C63 -> 7791300000 | F63: 4000000000 | G63: 3907212257 | H63: =F63-G63 -> 92787743 | I63: =B63+J63+1 -> 37496 | J63: 182 | M63: 4.5 | N63: =G63/F63*100 -> 97.680306 | O63: =(100-N63)/100*(365/182)*100 -> 4.6521327 | Q63: =((100-N63)/N63*(365/182))*100 -> 4.7626107 | R63: =((100-O63)/O63*(365/182))*100 -> 4110.3648
A67: =A63+1 -> 504 | B67: =B63+8 -> 37321 | C67: 4000000000 | D67: 15737500000 | E67: =D67-C67 -> 11737500000 | F67: 4000000000 | G67: 3915326284 | H67: =F67-G67 -> 84673716 | I67: =B67+J67+1 -> 37504 | J67: 182 | M67: 3.913 | N67: =G67/F67*100 -> 97.883157 | O67: =(100-N67)/100*(365/182)*100 -> 4.2453168 | Q67: =((100-N67)/N67*(365/182))*100 -> 4.337127 | R67: =((100-O67)/O67*(365/182))*100 -> 4523.4667
A68: =A67+1 -> 505 | B68: =B67+7 -> 37328 | C68: 3000000000 | D68: 9554700000 | E68: =D68-C68 -> 6554700000 | F68: 2999900000 | G68: 2944607939 | H68: =F68-G68 -> 55292061 | I68: =B68+J68+1 -> 37511 | J68: 182 | M68: 3.65 | N68: =G68/F68*100 -> 98.15687 | O68: =(100-N68)/100*(365/182)*100 -> 3.6963874 | Q68: =((100-N68)/N68*(365/182))*100 -> 3.7657959 | R68: =((100-O68)/O68*(365/182))*100 -> 5225.0034
A69: =A68+1 -> 506 | B69: =B68+7 -> 37335 | C69: 4000000000 | D69: 7100900000 | E69: =D69-C69 -> 3100900000 | F69: 4000000000 | G69: 3925659189 | H69: =F69-G69 -> 74340811 | I69: =B69+J69+1 -> 37518 | J69: 182 | M69: 3.1 | N69: =G69/F69*100 -> 98.14148 | O69: =(100-N69)/100*(365/182)*100 -> 3.7272522 | Q69: =((100-N69)/N69*(365/182))*100 -> 3.7978357 | R69: =((100-O69)/O69*(365/182))*100 -> 5180.0752
A70: =A69+1 -> 507 | B70: =B69+7 -> 37342 | C70: 4000000000 | D70: 4866500000 | E70: =D70-C70 -> 866500000 | F70: 4000000000 | G70: 3890205975 | H70: =F70-G70 -> 109794025 | I70: =B70+J70+1 -> 37525 | J70: 182 | M70: 3.584 | N70: =G70/F70*100 -> 97.255149 | O70: =(100-N70)/100*(365/182)*100 -> 5.5047828 | Q70: =((100-N70)/N70*(365/182))*100 -> 5.6601454 | R70: =((100-O70)/O70*(365/182))*100 -> 3442.6361
A74: =A70+1 -> 508 | B74: =B70+7 -> 37349 | C74: 2500000000 | D74: 4759000000 | E74: =D74-C74 -> 2259000000 | F74: 2500000000 | G74: 2419548380 | H74: =F74-G74 -> 80451620 | I74: =B74+J74+1 -> 37532 | J74: 182 | M74: 5.8 | N74: =G74/F74*100 -> 96.781935 | O74: =(100-N74)/100*(365/182)*100 -> 6.4538113 | Q74: =((100-N74)/N74*(365/182))*100 -> 6.6684049 | R74: =((100-O74)/O74*(365/182))*100 -> 2906.9082
A75: =A74+1 -> 509 | B75: =B74+7 -> 37356 | C75: 2000000000 | D75: 5482500000 | E75: =D75-C75 -> 3482500000 | F75: 1999900000 | G75: 1937822068 | H75: =F75-G75 -> 62077932 | I75: =B75+J75+1 -> 37539 | J75: 182 | M75: 5.778 | N75: =G75/F75*100 -> 96.895948 | O75: =(100-N75)/100*(365/182)*100 -> 6.2251588 | Q75: =((100-N75)/N75*(365/182))*100 -> 6.4245812 | R75: =((100-O75)/O75*(365/182))*100 -> 3021.0463
A76: =A75+1 -> 510 | B76: =B75+7 -> 37363 | C76: 2000000000 | D76: 6854200000 | E76: =D76-C76 -> 4854200000 | F76: 1999900000 | G76: 1940437290 | H76: =F76-G76 -> 59462710 | I76: =B76+J76+1 -> 37546 | J76: 182 | M76: 5.8 | N76: =G76/F76*100 -> 97.026716 | O76: =(100-N76)/100*(365/182)*100 -> 5.9629051 | Q76: =((100-N76)/N76*(365/182))*100 -> 6.1456322 | R76: =((100-O76)/O76*(365/182))*100 -> 3162.7349
A77: =A76+1 -> 511 | B77: =B76+7 -> 37370 | C77: 2500000000 | D77: 8643500000 | E77: =D77-C77 -> 6143500000 | F77: 2500000000 | G77: 2427970965 | H77: =F77-G77 -> 72029035 | I77: =B77+J77+1 -> 37553 | J77: 182 | M77: 5.499 | N77: =G77/F77*100 -> 97.118839 | O77: =(100-N77)/100*(365/182)*100 -> 5.7781534 | Q77: =((100-N77)/N77*(365/182))*100 -> 5.9495701 | R77: =((100-O77)/O77*(365/182))*100 -> 3270.2731
F78: =SUM(F74:F77) -> 8999800000
A81: =A77+1 -> 512 | B81: =B77+8 -> 37378 | C81: 2500000000 | D81: 3590800000 | E81: =D81-C81 -> 1090800000 | F81: 2500000000 | G81: 2432930956 | H81: =F81-G81 -> 67069044 | I81: =B81+J81+1 -> 37561 | J81: 182 | M81: 5.244 | N81: =G81/F81*100 -> 97.317238 | O81: =(100-N81)/100*(365/182)*100 -> 5.380264 | Q81: =((100-N81)/N81*(365/182))*100 -> 5.5285827 | R81: =((100-O81)/O81*(365/182))*100 -> 3526.9526
A82: =A81+1 -> 513 | B82: =B81+6 -> 37384 | C82: 3000000000 | D82: 6498100000 | E82: =D82-C82 -> 3498100000 | F82: 3000000000 | G82: 2924192251 | H82: =F82-G82 -> 75807749 | I82: =B82+J82+1 -> 37567 | J82: 182 | M82: 4.978 | N82: =G82/F82*100 -> 97.473075 | O82: =(100-N82)/100*(365/182)*100 -> 5.0677341 | Q82: =((100-N82)/N82*(365/182))*100 -> 5.1991118 | R82: =((100-O82)/O82*(365/182))*100 -> 3756.8296
A83: =A82+1 -> 514 | B83: =B82+7 -> 37391 | C83: 4000000000 | D83: 7604900000 | E83: =D83-C83 -> 3604900000 | F83: 4000000000 | G83: 3893379711 | H83: =F83-G83 -> 106620289 | I83: =B83+J83+1 -> 37574 | J83: 182 | M83: 4.978 | N83: =G83/F83*100 -> 97.334493 | O83: =(100-N83)/100*(365/182)*100 -> 5.3456601 | Q83: =((100-N83)/N83*(365/182))*100 -> 5.4920511 | R83: =((100-O83)/O83*(365/182))*100 -> 3551.0817
A84: =A83+1 -> 515 | B84: =B83+7 -> 37398 | C84: 5000000000 | D84: 6753000000 | E84: =D84-C84 -> 1753000000 | F84: 5000000000 | G84: 4859110510 | H84: =F84-G84 -> 140889490 | I84: =B84+J84+1 -> 37581 | J84: 182 | M84: 5.264 | N84: =G84/F84*100 -> 97.18221 | O84: =(100-N84)/100*(365/182)*100 -> 5.651062 | Q84: =((100-N84)/N84*(365/182))*100 -> 5.814914 | R84: =((100-O84)/O84*(365/182))*100 -> 3348.3313
A85: =A84+1 -> 516 | B85: =B84+7 -> 37405 | C85: 5000000000 | D85: 12817000000 | E85: =D85-C85 -> 7817000000 | F85: 5000000000 | G85: 4850520210 | H85: =F85-G85 -> 149479790 | I85: =B85+J85+1 -> 37588 | J85: 182 | M85: 5.499 | N85: =G85/F85*100 -> 97.010404 | O85: =(100-N85)/100*(365/182)*100 -> 5.995618 | Q85: =((100-N85)/N85*(365/182))*100 -> 6.1803865 | R85: =((100-O85)/O85*(365/182))*100 -> 3144.3843
F86: =SUM(F81:F85) -> 19500000000
A89: =A85+1 -> 517 | B89: =B85+7 -> 37412 | C89: 5000000000 | D89: 5000000000 | E89: =D89-C89 -> 0 | F89: 5000000000 | G89: 4830664750 | H89: =F89-G89 -> 169335250 | I89: =B89+J89+1 -> 37595 | J89: 182 | M89: 6.179 | N89: =G89/F89*100 -> 96.613295 | O89: =(100-N89)/100*(365/182)*100 -> 6.7920183 | Q89: =((100-N89)/N89*(365/182))*100 -> 7.0301073 | R89: =((100-O89)/O89*(365/182))*100 -> 2752.173
A90: =A89+1 -> 518 | B90: =B89+7 -> 37419 | C90: 5000000000 | D90: 10780300000 | E90: =D90-C90 -> 5780300000 | F90: 5000000000 | G90: 4823990157 | H90: =F90-G90 -> 176009843 | I90: =B90+J90+1 -> 37602 | J90: 182 | M90: 4.5 | N90: =G90/F90*100 -> 96.479803 | O90: =(100-N90)/100*(365/182)*100 -> 7.0597355 | Q90: =((100-N90)/N90*(365/182))*100 -> 7.3173195 | R90: =((100-O90)/O90*(365/182))*100 -> 2640.2008
A91: =A90+1 -> 519 | B91: =B90+7 -> 37426 | C91: 5000000000 | D91: 9920600000 | E91: =D91-C91 -> 4920600000 | F91: 4999900000 | G91: 4834776817 | H91: =F91-G91 -> 165123183 | I91: =B91+J91+1 -> 37609 | J91: 182 | M91: 5.499 | N91: =G91/F91*100 -> 96.69747 | O91: =(100-N91)/100*(365/182)*100 -> 6.6232052 | Q91: =((100-N91)/N91*(365/182))*100 -> 6.849409 | R91: =((100-O91)/O91*(365/182))*100 -> 2827.4324
A92: =A91+1 -> 520 | B92: =B91+7 -> 37433 | C92: 4000000000 | D92: 6730900000 | E92: =D92-C92 -> 2730900000 | F92: 4000000000 | G92: 3871236829 | H92: =F92-G92 -> 128763171 | I92: =B92+J92+1 -> 37616 | J92: 182 | M92: 6.016 | N92: =G92/F92*100 -> 96.780921 | O92: =(100-N92)/100*(365/182)*100 -> 6.4558458 | Q92: =((100-N92)/N92*(365/182))*100 -> 6.670577 | R92: =((100-O92)/O92*(365/182))*100 -> 2905.9289
F93: =SUM(F89:F92) -> 18999900000
A96: =A92+1 -> 521 | B96: =B92+7 -> 37440 | C96: 4000000000 | D96: 4000000000 | E96: =D96-C96 -> 0 | F96: 4000000000 | G96: 3840285235 | H96: =F96-G96 -> 159714765 | I96: =B96+J96+1 -> 37623 | J96: 182 | M96: 6.674 | N96: =G96/F96*100 -> 96.007131 | O96: =(100-N96)/100*(365/182)*100 -> 8.0076771 | Q96: =((100-N96)/N96*(365/182))*100 -> 8.3407108 | R96: =((100-O96)/O96*(365/182))*100 -> 2303.9153
A97: =A96+1 -> 522 | B97: =B96+7 -> 37447 | C97: 3000000000 | D97: 3000000000 | E97: =D97-C97 -> 0 | F97: 3000000000 | G97: 2850029000 | H97: =F97-G97 -> 149971000 | I97: =B97+J97+1 -> 37630 | J97: 182 | M97: 8.385 | N97: =G97/F97*100 -> 95.000967 | O97: =(100-N97)/100*(365/182)*100 -> 10.025534 | Q97: =((100-N97)/N97*(365/182))*100 -> 10.553086 | R97: =((100-O97)/O97*(365/182))*100 -> 1799.8373
A98: =A97+1 -> 523 | B98: =B97+7 -> 37454 | C98: 3000000000 | D98: 6414500000 | E98: =D98-C98 -> 3414500000 | F98: 3000000000 | G98: 2853307275 | H98: =F98-G98 -> 146692725 | I98: =B98+J98+1 -> 37637 | J98: 182 | M98: 8.7 | N98: =G98/F98*100 -> 95.110242 | O98: =(100-N98)/100*(365/182)*100 -> 9.8063818 | Q98: =((100-N98)/N98*(365/182))*100 -> 10.310542 | R98: =((100-O98)/O98*(365/182))*100 -> 1844.5417
A99: =A98+1 -> 524 | B99: =B98+7 -> 37461 | C99: 3000000000 | D99: 5652500000 | E99: =D99-C99 -> 2652500000 | F99: 3000000000 | G99: 2853324230 | H99: =F99-G99 -> 146675770 | I99: =B99+J99+1 -> 37644 | J99: 182 | M99: 9.526 | N99: =G99/F99*100 -> 95.110808 | O99: =(100-N99)/100*(365/182)*100 -> 9.8052484 | Q99: =((100-N99)/N99*(365/182))*100 -> 10.309289 | R99: =((100-O99)/O99*(365/182))*100 -> 1844.7781
A100: =A99+1 -> 525 | B100: =B99+7 -> 37468 | C100: 3000000000 | D100: 6271900000 | E100: =D100-C100 -> 3271900000 | F100: 3000000000 | G100: 2856396537 | H100: =F100-G100 -> 143603463 | I100: =B100+J100+1 -> 37651 | J100: 182 | M100: 9.249 | N100: =G100/F100*100 -> 95.213218 | O100: =(100-N100)/100*(365/182)*100 -> 9.5998652 | Q100: =((100-N100)/N100*(365/182))*100 -> 10.082492 | R100: =((100-O100)/O100*(365/182))*100 -> 1888.5367
F101: =SUM(F96:F100) -> 16000000000 | H101: =SUM(H96:H100) -> 746657723
A104: =A100+1 -> 526 | B104: =B100+7 -> 37475 | C104: 2000000000 | D104: 5374500000 | E104: =D104-C104 -> 3374500000 | F104: 1999600000 | G104: 1903712225 | H104: =F104-G104 -> 95887775 | I104: =B104+J104+1 -> 37658 | J104: 182 | M104: 9.249 | N104: =G104/F104*100 -> 95.204652 | O104: =(100-N104)/100*(365/182)*100 -> 9.6170437 | Q104: =((100-N104)/N104*(365/182))*100 -> 10.101443 | R104: =((100-O104)/O104*(365/182))*100 -> 1884.805
A105: =A104+1 -> 527 | B105: =B104+7 -> 37482 | C105: 2000000000 | D105: 3670800000 | E105: =D105-C105 -> 1670800000 | F105: 2000000000 | G105: 1901066379 | H105: =F105-G105 -> 98933621 | I105: =B105+J105+1 -> 37665 | J105: 182 | M105: 9.249 | N105: =G105/F105*100 -> 95.053319 | O105: =(100-N105)/100*(365/182)*100 -> 9.9205417 | Q105: =((100-N105)/N105*(365/182))*100 -> 10.436818 | R105: =((100-O105)/O105*(365/182))*100 -> 1821.008
A106: =A105+1 -> 528 | B106: =B105+7 -> 37489 | C106: 2000000000 | D106: 6259700000 | E106: =D106-C106 -> 4259700000 | F106: 2000000000 | G106: 1896679948 | H106: =F106-G106 -> 103320052 | I106: =B106+J106+1 -> 37672 | J106: 182 | N106: =G106/F106*100 -> 94.833997 | O106: =(100-N106)/100*(365/182)*100 -> 10.36039 | Q106: =((100-N106)/N106*(365/182))*100 -> 10.924763 | R106: =((100-O106)/O106*(365/182))*100 -> 1735.1832
A107: =A106+1 -> 529 | B107: =B106+7 -> 37496 | C107: 2000000000 | D107: 6664000000 | E107: =D107-C107 -> 4664000000 | F107: 2000000000 | G107: 1897250220 | H107: =F107-G107 -> 102749780 | I107: =B107+J107+1 -> 37679 | J107: 182 | N107: =G107/F107*100 -> 94.862511 | O107: =(100-N107)/100*(365/182)*100 -> 10.303206 | Q107: =((100-N107)/N107*(365/182))*100 -> 10.861199 | R107: =((100-O107)/O107*(365/182))*100 -> 1745.9267
F108: =SUM(F104:F107) -> 7999600000 | H108: =SUM(H104:H107) -> 400891228
A111: =A107+1 -> 530 | B111: =B107+7 -> 37503 | C111: 3000000000 | D111: 7729400000 | E111: =D111-C111 -> 4729400000 | F111: 2999900000 | G111: 2847125749 | H111: =F111-G111 -> 152774251 | I111: =B111+J111+1 -> 37686 | J111: 182 | N111: =G111/F111*100 -> 94.907355 | O111: =(100-N111)/100*(365/182)*100 -> 10.213271 | Q111: =((100-N111)/N111*(365/182))*100 -> 10.761306 | R111: =((100-O111)/O111*(365/182))*100 -> 1763.0668
A112: =A111+1 -> 531 | B112: =B111+7 -> 37510 | C112: 4000000000 | D112: 6297900000 | E112: =D112-C112 -> 2297900000 | F112: 4000000000 | G112: 3796640412 | H112: =F112-G112 -> 203359588 | I112: =B112+J112+1 -> 37693 | J112: 182 | N112: =G112/F112*100 -> 94.91601 | O112: =(100-N112)/100*(365/182)*100 -> 10.195913 | Q112: =((100-N112)/N112*(365/182))*100 -> 10.742037 | R112: =((100-O112)/O112*(365/182))*100 -> 1766.4097
A113: =A112+1 -> 532 | B113: =B112+7 -> 37517 | C113: 5000000000 | D113: 5000000000 | E113: =D113-C113 -> 0 | F113: 5000000000 | G113: 4740282200 | H113: =F113-G113 -> 259717800 | I113: =B113+J113+1 -> 37700 | J113: 182 | N113: =G113/F113*100 -> 94.805644 | O113: =(100-N113)/100*(365/182)*100 -> 10.417252 | Q113: =((100-N113)/N113*(365/182))*100 -> 10.988009 | R113: =((100-O113)/O113*(365/182))*100 -> 1724.617
A114: =A113+1 -> 533 | B114: =B113+7 -> 37524 | C114: 5000000000 | D114: 5649400000 | E114: =D114-C114 -> 649400000 | F114: 5000000000 | G114: 4735944716 | H114: =F114-G114 -> 264055284 | I114: =B114+J114+1 -> 37707 | J114: 182 | N114: =G114/F114*100 -> 94.718894 | O114: =(100-N114)/100*(365/182)*100 -> 10.591228 | Q114: =((100-N114)/N114*(365/182))*100 -> 11.181748 | R114: =((100-O114)/O114*(365/182))*100 -> 1692.9934
F115: =SUM(F111:F114) -> 16999900000 | H115: =SUM(H111:H114) -> 879906923
A118: =A114+1 -> 534 | B118: =B114+7 -> 37531 | C118: 5000000000 | D118: 5000000000 | E118: =D118-C118 -> 0 | F118: 5000000000 | G118: 4718898900 | H118: =F118-G118 -> 281101100 | I118: =B118+J118+1 -> 37714 | J118: 182 | N118: =G118/F118*100 -> 94.377978 | O118: =(100-N118)/100*(365/182)*100 -> 11.274934 | Q118: =((100-N118)/N118*(365/182))*100 -> 11.946573 | R118: =((100-O118)/O118*(365/182))*100 -> 1578.17
A119: =A118+1 -> 535 | B119: =B118+7 -> 37538 | C119: 5000000000 | D119: 5000000000 | E119: =D119-C119 -> 0 | F119: 5000000000 | G119: 4718900000 | H119: =F119-G119 -> 281100000 | I119: =B119+J119+1 -> 37721 | J119: 182 | N119: =G119/F119*100 -> 94.378 | O119: =(100-N119)/100*(365/182)*100 -> 11.27489 | Q119: =((100-N119)/N119*(365/182))*100 -> 11.946524 | R119: =((100-O119)/O119*(365/182))*100 -> 1578.177
A120: =A119+1 -> 536 | B120: =B119+7 -> 37545 | C120: 8000000000 | D120: 7868300000 | E120: =D120-C120 -> -131700000 | F120: 7868300000 | G120: 7408147985 | H120: =F120-G120 -> 460152015 | I120: =B120+J120+1 -> 37728 | J120: 182 | N120: =G120/F120*100 -> 94.151824 | O120: =(100-N120)/100*(365/182)*100 -> 11.728484 | Q120: =((100-N120)/N120*(365/182))*100 -> 12.456991 | R120: =((100-O120)/O120*(365/182))*100 -> 1509.3855
A121: =A120+1 -> 537 | B121: =B120+7 -> 37552 | C121: 6000000000 | D121: 10419200000 | E121: =D121-C121 -> 4419200000 | F121: 6000000000 | G121: 5639891950 | H121: =F121-G121 -> 360108050 | I121: =B121+J121+1 -> 37735 | J121: 182 | N121: =G121/F121*100 -> 93.998199 | O121: =(100-N121)/100*(365/182)*100 -> 12.036579 | Q121: =((100-N121)/N121*(365/182))*100 -> 12.805116 | R121: =((100-O121)/O121*(365/182))*100 -> 1465.6171
F123: =SUM(F118:F122) -> 23868300000
A125: =A121+1 -> 538 | B125: =B121+7 -> 37559 | C125: 5000000000 | D125: 8284400000 | E125: =D125-C125 -> 3284400000 | F125: 5000000000 | G125: 4693878380 | H125: =F125-G125 -> 306121620 | I125: =B125+J125+1 -> 37742 | J125: 182 | N125: =G125/F125*100 -> 93.877568 | O125: =(100-N125)/100*(365/182)*100 -> 12.278505 | Q125: =((100-N125)/N125*(365/182))*100 -> 13.079274 | R125: =((100-O125)/O125*(365/182))*100 -> 1432.7883
A126: =A125+1 -> 539 | B126: =B125+7 -> 37566 | C126: 6000000000 | D126: 4412800000 | E126: =D126-C126 -> -1587200000 | F126: 4412800000 | G126: 4122131664 | H126: =F126-G126 -> 290668336 | I126: =B126+J126+1 -> 37749 | J126: 182 | N126: =G126/F126*100 -> 93.413063 | O126: =(100-N126)/100*(365/182)*100 -> 13.210065 | Q126: =((100-N126)/N126*(365/182))*100 -> 14.141561 | R126: =((100-O126)/O126*(365/182))*100 -> 1317.607
A127: =A126+1 -> 540 | B127: =B126+7 -> 37573 | C127: 5000000000 | D127: 4562600000 | E127: =D127-C127 -> -437400000 | F127: 4562600000 | G127: 4250424708 | H127: =F127-G127 -> 312175292 | I127: =B127+J127+1 -> 37756 | J127: 182 | N127: =G127/F127*100 -> 93.157952 | O127: =(100-N127)/100*(365/182)*100 -> 13.72169 | Q127: =((100-N127)/N127*(365/182))*100 -> 14.729489 | R127: =((100-O127)/O127*(365/182))*100 -> 1261.0012
...

Sheet maturities - 273
A2: Ref:ISS9899. WK3
A3: worksheet b
A4: - | B4: - | D4: - | E4: - | F4: - | G4: - | H4: - | I4: - | J4: - | K4: - | L4: - | M4: - | N4: - | O4: - | P4: - | Q4: -
A5: Auction | B5: Issue date | D5: Amount offered | E5: Total bids | F5: Over/(Under) | G5: Face Value of | H5: Cost Value | I5: Interest due | J5: Date due | K5: Duration | L5: Implicit annual | M5: Clearing | N5: Lowest | O5: Weighted | P5: Average | Q5: Annualised
A6: No | D6: in | E6: (Competitive & | F6: Subscribed | G6: issues | L6: interest rate | M6: factor | N6: factor | O6: Average | P6: Discount | Q6: yield
D7: Auction | E7: Uncompetitive) | M7: (%) | N7: (%) | O7: Price | P7: factor
B8: (1) | D8: (1a) | E8: (1b) | G8: (2) | H8: (3) | I8: (4) | J8: (5) | K8: (6) | L8: (9) | M8: (10) | N8: (11) | O8: (12) | P8: (13)
A9: - | B9: - | D9: - | E9: - | F9: - | G9: - | H9: - | I9: - | J9: - | K9: - | L9: - | M9: - | N9: - | O9: - | P9: - | Q9: -
A10: 469 | B10: 37076 | D10: ='ISS10102'!D13 -> 4000000000 | E10: ='ISS10102'!E13 -> 5477000000 | F10: ='ISS10102'!F13 -> 1477000000 | G10: ='ISS10102'!G13 -> 4000000000 | H10: ='ISS10102'!H13 -> 3698699840 | I10: ='ISS10102'!I13 -> 301300160 | J10: =B10+K10+1 -> 37350 | K10: ='ISS10102'!K13 -> 273 | N10: ='ISS10102'!N13 -> 9.426 | O10: ='ISS10102'!O13 -> 92.467496 | P10: ='ISS10102'!P13 -> 10.07093 | Q10: =((100-O10)/O10*(365/273))*100 -> 10.891319
A11: =A10+1 -> 470 | B11: =B10+7 -> 37083 | D11: ='ISS10102'!D18 -> 5000000000 | E11: ='ISS10102'!E18 -> 5000000000 | F11: ='ISS10102'!F18 -> 0 | G11: ='ISS10102'!G18 -> 5000000000 | H11: ='ISS10102'!H18 -> 4570702500 | I11: ='ISS10102'!I18 -> 429297500 | J11: =J10+7 -> 37357 | K11: ='ISS10102'!K18 -> 273 | N11: ='ISS10102'!N18 -> 10.629 | O11: ='ISS10102'!O18 -> 91.41405 | P11: ='ISS10102'!P18 -> 11.479384 | Q11: =((100-O11)/O11*(365/273))*100 -> 12.55757
A12: =A11+1 -> 471 | B12: =B11+7 -> 37090 | D12: ='ISS10102'!D23 -> 5000000000 | E12: ='ISS10102'!E23 -> 5000000000 | F12: ='ISS10102'!F23 -> 0 | G12: ='ISS10102'!G23 -> 5000000000 | H12: ='ISS10102'!H23 -> 4483755000 | I12: ='ISS10102'!I23 -> 516245000 | J12: =J11+7 -> 37364 | K12: ='ISS10102'!K23 -> 273 | N12: ='ISS10102'!N23 -> 11.848 | O12: ='ISS10102'!O23 -> 89.6751 | P12: ='ISS10102'!P23 -> 13.804353 | Q12: =((100-O12)/O12*(365/273))*100 -> 15.393742
A13: =A12+1 -> 472 | B13: =B12+7 -> 37097 | D13: ='ISS10102'!D28 -> 5000000000 | E13: ='ISS10102'!E28 -> 5000000000 | F13: ='ISS10102'!F28 -> 0 | G13: ='ISS10102'!G28 -> 5000000000 | H13: ='ISS10102'!H28 -> 4265972900 | I13: ='ISS10102'!I28 -> 734027100 | J13: =J12+7 -> 37371 | K13: ='ISS10102'!K28 -> 273 | N13: ='ISS10102'!N28 -> 12 | O13: ='ISS10102'!O28 -> 85.319458 | P13: ='ISS10102'!P28 -> 19.627831 | Q13: =((100-O13)/O13*(365/273))*100 -> 23.005105
B15: Total Jul 2001 | D15: =SUM(D10:D13) -> 19000000000 | E15: =SUM(E10:E13) -> 20477000000 | F15: =SUM(F10:F13) -> 1477000000 | G15: =SUM(G10:G13) -> 19000000000 | H15: =SUM(H10:H13) -> 17019130240 | I15: =SUM(I10:I13) -> 1980869760 | O15: =AVERAGEA(O10:O13) -> 89.719026 | P15: =AVERAGEA(P10:P13) -> 13.745625 | Q15: =AVERAGEA(Q10:Q13) -> 15.461934
A17: =A13+1 -> 473 | B17: =B13+7 -> 37104 | D17: ='ISS10102'!D38 -> 4000000000 | E17: ='ISS10102'!E38 -> 10723700000 | F17: ='ISS10102'!F38 -> 6723700000 | G17: ='ISS10102'!G38 -> 3999900000 | H17: ='ISS10102'!H38 -> 3411615570 | I17: ='ISS10102'!I38 -> 588284430 | J17: =J13+7 -> 37378 | K17: ='ISS10102'!K38 -> 273 | N17: ='ISS10102'!N38 -> 17.381 | O17: ='ISS10102'!O38 -> 85.292522 | P17: ='ISS10102'!P38 -> 19.663845 | Q17: =((100-O17)/O17*(365/273))*100 -> 23.054594
A18: =A17+1 -> 474 | B18: =B17+7 -> 37111 | D18: ='ISS10102'!D43 -> 6000000000 | E18: ='ISS10102'!E43 -> 10552200000 | F18: ='ISS10102'!F43 -> 4552200000 | G18: ='ISS10102'!G43 -> 6000000000 | H18: ='ISS10102'!H43 -> 5070862258 | I18: ='ISS10102'!I43 -> 929137742 | J18: =J17+7 -> 37385 | K18: ='ISS10102'!K43 -> 273 | N18: ='ISS10102'!N43 -> 18 | O18: ='ISS10102'!O43 -> 84.514371 | P18: ='ISS10102'!P43 -> 20.704229 | Q18: =((100-O18)/O18*(365/273))*100 -> 24.49788
A19: =A18+1 -> 475 | B19: =B18+7 -> 37118 | D19: ='ISS10102'!D48 -> 5000000000 | E19: ='ISS10102'!E48 -> 9401000000 | F19: ='ISS10102'!F48 -> 4401000000 | G19: ='ISS10102'!G48 -> 5000000000 | H19: ='ISS10102'!H48 -> 4213782060 | I19: ='ISS10102'!I48 -> 786217940 | J19: =J18+7 -> 37392 | K19: ='ISS10102'!K48 -> 273 | N19: ='ISS10102'!N48 -> 18.918 | O19: ='ISS10102'!O48 -> 84.275641 | P19: ='ISS10102'!P48 -> 21.02341 | Q19: =((100-O19)/O19*(365/273))*100 -> 24.94601
A20: =A19+1 -> 476 | B20: =B19+7 -> 37125 | D20: ='ISS10102'!D53 -> 5000000000 | E20: ='ISS10102'!E53 -> 14861900000 | F20: ='ISS10102'!F53 -> 9861900000 | G20: ='ISS10102'!G53 -> 4999900000 | H20: ='ISS10102'!H53 -> 4271361534 | I20: ='ISS10102'!I53 -> 728538466 | J20: =J19+7 -> 37399 | K20: ='ISS10102'!K53 -> 273 | N20: ='ISS10102'!N53 -> 17.381 | O20: ='ISS10102'!O53 -> 85.428939 | P20: ='ISS10102'!P53 -> 19.481455 | Q20: =((100-O20)/O20*(365/273))*100 -> 22.80428
A21: =A20+1 -> 477 | B21: =B20+7 -> 37132 | D21: ='ISS10102'!D58 -> 4000000000 | E21: ='ISS10102'!E58 -> 12127000000 | F21: ='ISS10102'!F58 -> 8127000000 | G21: ='ISS10102'!G58 -> 3999900000 | H21: ='ISS10102'!H58 -> 3461414160 | I21: ='ISS10102'!I58 -> 538485840 | J21: =J20+7 -> 37406 | K21: ='ISS10102'!K58 -> 273 | N21: ='ISS10102'!N58 -> 17.515 | O21: ='ISS10102'!O58 -> 86.537517 | P21: ='ISS10102'!P58 -> 17.99929 | Q21: =((100-O21)/O21*(365/273))*100 -> 20.799406
B23: Total Aug 2001 | D23: =SUM(D17:D21) -> 24000000000 | E23: =SUM(E17:E21) -> 57665800000 | F23: =SUM(F17:F21) -> 33665800000 | G23: =SUM(G17:G21) -> 23999700000 | H23: =SUM(H17:H21) -> 20429035582 | I23: =SUM(I17:I21) -> 3570664418 | O23: =AVERAGEA(O17:O21) -> 85.209798 | P23: =AVERAGEA(P17:P21) -> 19.774446 | Q23: =AVERAGEA(Q17:Q21) -> 23.220434
A25: =A21+1 -> 478 | B25: =B21+7 -> 37139 | D25: ='ISS10102'!D68 -> 5000000000 | E25: ='ISS10102'!E68 -> 4999800000 | F25: ='ISS10102'!F68 -> -200000 | G25: ='ISS10102'!G68 -> 4999800000 | H25: ='ISS10102'!H68 -> 4342526855 | I25: =G25-H25 -> 657273145 | J25: =J21+7 -> 37413 | K25: ='ISS10102'!K68 -> 273 | N25: 17 | O25: ='ISS10102'!O68 -> 86.854011 | P25: ='ISS10102'!P68 -> 17.576139 | Q25: =((100-O25)/O25*(365/273))*100 -> 20.236416
A26: =A25+1 -> 479 | B26: =B25+7 -> 37146 | D26: ='ISS10102'!D73 -> 5000000000 | E26: ='ISS10102'!E73 -> 16566000000 | F26: ='ISS10102'!F73 -> 11566000000 | G26: ='ISS10102'!G73 -> 5000000000 | H26: ='ISS10102'!H73 -> 4397456245 | I26: =G26-H26 -> 602543755 | J26: =J25+7 -> 37420 | K26: ='ISS10102'!K73 -> 273 | N26: ='ISS10102'!N73 -> 15.119 | O26: ='ISS10102'!O73 -> 87.949125 | P26: ='ISS10102'!P73 -> 16.111976 | Q26: =((100-O26)/O26*(365/273))*100 -> 18.319655
A27: =A26+1 -> 480 | B27: =B26+7 -> 37153 | D27: ='ISS10102'!D78 -> 5000000000 | E27: ='ISS10102'!E78 -> 12395200000 | F27: ='ISS10102'!F78 -> 7395200000 | G27: ='ISS10102'!G78 -> 4999700000 | H27: ='ISS10102'!H78 -> 4432431555 | I27: =G27-H27 -> 567268445 | J27: =J26+7 -> 37427 | K27: ='ISS10102'!K78 -> 273 | N27: ='ISS10102'!N78 -> 14.292 | O27: ='ISS10102'!O78 -> 88.65395 | P27: ='ISS10102'!P78 -> 15.169627 | Q27: =((100-O27)/O27*(365/273))*100 -> 17.111056
A28: =A27+1 -> 481 | B28: =B27+7 -> 37160 | D28: ='ISS10102'!D83 -> 4000000000 | E28: ='ISS10102'!E83 -> 11636000000 | F28: ='ISS10102'!F83 -> 7636000000 | G28: ='ISS10102'!G83 -> 3999900000 | H28: ='ISS10102'!H83 -> 3584442625 | I28: =G28-H28 -> 415457375 | J28: =J27+7 -> 37434 | K28: ='ISS10102'!K83 -> 273 | N28: ='ISS10102'!N83 -> 13.169 | O28: ='ISS10102'!O83 -> 89.613306 | P28: ='ISS10102'!P83 -> 13.886972 | Q28: =((100-O28)/O28*(365/273))*100 -> 15.496551
B30: Total Sep 2001 | D30: =SUM(D25:D28) -> 19000000000 | E30: =SUM(E25:E28) -> 45597000000 | F30: =SUM(F25:F28) -> 26597000000 | G30: =SUM(G25:G28) -> 18999400000 | H30: =SUM(H25:H28) -> 16756857280 | I30: =SUM(I25:I28) -> 2242542720 | J30: =SUM(J25:J28) -> 149694 | K30: =SUM(K25:K28) -> 1092 | O30: =AVERAGEA(O25:O28) -> 88.267598 | P30: =AVERAGEA(P25:P28) -> 15.686178 | Q30: =AVERAGEA(Q25:Q28) -> 17.790919
A32: =A28+1 -> 482 | B32: =B28+7 -> 37167 | D32: ='ISS10102'!D93 -> 4000000000 | E32: ='ISS10102'!E93 -> 8376000000 | F32: ='ISS10102'!F93 -> 4376000000 | G32: ='ISS10102'!G93 -> 3999900000 | H32: ='ISS10102'!H93 -> 3603379951 | I32: =G32-H32 -> 396520049 | J32: =J28+7 -> 37441 | K32: ='ISS10102'!K93 -> 273 | N32: ='ISS10102'!N93 -> 12.568 | O32: ='ISS10102'!O93 -> 90.086751 | P32: ='ISS10102'!P93 -> 13.253978 | Q32: =((100-O32)/O32*(365/273))*100 -> 14.712461
A33: =A32+1 -> 483 | B33: =B32+7 -> 37174 | D33: ='ISS10102'!D98 -> 4000000000 | E33: ='ISS10102'!E98 -> 9208000000 | F33: ='ISS10102'!F98 -> 5208000000 | G33: ='ISS10102'!G98 -> 4000000000 | H33: ='ISS10102'!H98 -> 3613052690 | I33: =G33-H33 -> 386947310 | J33: =B33+K33+1 -> 37448 | K33: ='ISS10102'!K98 -> 273 | N33: ='ISS10102'!N98 -> 12.16 | O33: ='ISS10102'!O98 -> 90.326317 | P33: ='ISS10102'!P98 -> 12.933678 | Q33: =((100-O33)/O33*(365/273))*100 -> 14.318837
A34: =A33+1 -> 484 | B34: =B33+7 -> 37181 | D34: ='ISS10102'!D103 -> 4000000000 | E34: ='ISS10102'!E103 -> 12281000000 | F34: ='ISS10102'!F103 -> 8281000000 | G34: ='ISS10102'!G103 -> 4000000000 | H34: ='ISS10102'!H103 -> 3628802660 | I34: =G34-H34 -> 371197340 | J34: =B34+K34+1 -> 37455 | K34: ='ISS10102'!K103 -> 273 | N34: ='ISS10102'!N103 -> 12 | O34: ='ISS10102'!O103 -> 90.720067 | P34: ='ISS10102'!P103 -> 12.407237 | Q34: =((100-O34)/O34*(365/273))*100 -> 13.676398
A35: =A34+1 -> 485 | B35: =B34+7 -> 37188 | D35: ='ISS10102'!D108 -> 4000000000 | E35: ='ISS10102'!E108 -> 5369500000 | F35: ='ISS10102'!F108 -> 1369500000 | G35: ='ISS10102'!G108 -> 4000000000 | H35: ='ISS10102'!H108 -> 3647779923 | I35: =G35-H35 -> 352220077 | J35: =B35+K35+1 -> 37462 | K35: ='ISS10102'!K108 -> 273 | N35: ='ISS10102'!N108 -> 8.666 | O35: ='ISS10102'!O108 -> 91.194498 | P35: ='ISS10102'!P108 -> 11.772924 | Q35: =((100-O35)/O35*(365/273))*100 -> 12.909687
A36: =A35+1 -> 486 | B36: =B35+7 -> 37195 | D36: ='ISS10102'!D113 -> 3000000000 | E36: ='ISS10102'!E113 -> 8260800000 | F36: ='ISS10102'!F113 -> 5260800000 | G36: ='ISS10102'!G113 -> 3000000000 | H36: ='ISS10102'!H113 -> 2768805482 | I36: =G36-H36 -> 231194518 | J36: =B36+K36+1 -> 37469 | K36: ='ISS10102'!K113 -> 273 | N36: ='ISS10102'!N113 -> 9.499 | O36: ='ISS10102'!O113 -> 92.293516 | P36: ='ISS10102'!P113 -> 10.303541 | Q36: =((100-O36)/O36*(365/273))*100 -> 11.163884
B38: Total Oct 2001 | D38: =SUM(D32:D36) -> 19000000000 | E38: =SUM(E32:E36) -> 43495300000 | F38: =SUM(F32:F36) -> 24495300000 | G38: =SUM(G32:G36) -> 18999900000 | H38: =SUM(H32:H36) -> 17261820706 | I38: =SUM(I32:I36) -> 1738079294 | O38: =AVERAGEA(O32:O36) -> 90.92423 | P38: =AVERAGEA(P32:P36) -> 12.134272 | Q38: =AVERAGEA(Q32:Q36) -> 13.356253
A40: =A36+1 -> 487 | B40: =B36+7 -> 37202 | D40: ='ISS10102'!D123 -> 4000000000 | E40: ='ISS10102'!E123 -> 9789600000 | F40: ='ISS10102'!F123 -> 5789600000 | G40: ='ISS10102'!G123 -> 4000000000 | H40: ='ISS10102'!H123 -> 3694062442 | I40: =G40-H40 -> 305937558 | J40: =B40+K40+1 -> 37476 | K40: ='ISS10102'!K123 -> 273 | N40: ='ISS10102'!N123 -> 9.499 | O40: ='ISS10102'!O123 -> 92.351561 | P40: ='ISS10102'!P123 -> 10.225935 | Q40: =((100-O40)/O40*(365/273))*100 -> 11.072834
A41: =A40+1 -> 488 | B41: =B40+7 -> 37209 | D41: ='ISS10102'!D128 -> 5000000000 | E41: ='ISS10102'!E128 -> 12591300000 | F41: ='ISS10102'!F128 -> 7591300000 | G41: ='ISS10102'!G128 -> 5000000000 | H41: ='ISS10102'!H128 -> 4626930920 | I41: =G41-H41 -> 373069080 | J41: =B41+K41+1 -> 37483 | K41: ='ISS10102'!K128 -> 273 | N41: ='ISS10102'!N128 -> 9.328 | O41: ='ISS10102'!O128 -> 92.538618 | P41: ='ISS10102'!P128 -> 9.9758399 | Q41: =((100-O41)/O41*(365/273))*100 -> 10.780191
A42: =A41+1 -> 489 | B42: =B41+7 -> 37216 | D42: ='ISS10102'!D133 -> 5000000000 | E42: ='ISS10102'!E133 -> 11940000000 | F42: ='ISS10102'!F133 -> 6940000000 | G42: ='ISS10102'!G133 -> 5000000000 | H42: ='ISS10102'!H133 -> 4620339900 | I42: =G42-H42 -> 379660100 | J42: =B42+K42+1 -> 37490 | K42: ='ISS10102'!K133 -> 273 | N42: ='ISS10102'!N133 -> 9.85 | O42: ='ISS10102'!O133 -> 92.406798 | P42: ='ISS10102'!P133 -> 10.152083 | Q42: =((100-O42)/O42*(365/273))*100 -> 10.986295
A43: =A42+1 -> 490 | B43: =B42+7 -> 37223 | D43: ='ISS10102'!D138 -> 5000000000 | E43: ='ISS10102'!E138 -> 13460500000 | F43: ='ISS10102'!F138 -> 8460500000 | G43: ='ISS10102'!G138 -> 4999900000 | H43: ='ISS10102'!H138 -> 4622696692 | I43: =G43-H43 -> 377203308 | J43: =B43+K43+1 -> 37497 | K43: ='ISS10102'!K138 -> 273 | N43: ='ISS10102'!N138 -> 9.999 | O43: ='ISS10102'!O138 -> 92.455783 | P43: ='ISS10102'!P138 -> 10.086591 | Q43: =((100-O43)/O43*(365/273))*100 -> 10.909637
B45: Total Nov 2001 | D45: =SUM(D40:D43) -> 19000000000 | E45: =SUM(E40:E43) -> 47781400000 | F45: =SUM(F40:F43) -> 28781400000 | G45: =SUM(G40:G43) -> 18999900000 | H45: =SUM(H40:H43) -> 17564029954 | I45: =SUM(I40:I43) -> 1435870046 | O45: =AVERAGEA(O40:O43) -> 92.43819 | P45: =AVERAGEA(P40:P43) -> 10.110112 | Q45: =AVERAGEA(Q40:Q43) -> 10.937239
A47: =A43+1 -> 491 | B47: =B43+7 -> 37230 | D47: ='ISS10102'!D148 -> 5000000000 | E47: ='ISS10102'!E148 -> 11046600000 | F47: ='ISS10102'!F148 -> 6046600000 | G47: ='ISS10102'!G148 -> 5000000000 | H47: ='ISS10102'!H148 -> 4641359698 | I47: =G47-H47 -> 358640302 | J47: =B47+K47+1 -> 37504 | K47: 273 | N47: ='ISS10102'!N148 -> 9.001 | O47: ='ISS10102'!O148 -> 92.827194 | P47: ='ISS10102'!P148 -> 9.5900154 | Q47: =((100-O47)/O47*(365/273))*100 -> 10.331041
A48: =A47+1 -> 492 | B48: =B47+7 -> 37237 | D48: ='ISS10102'!D153 -> 5000000000 | E48: ='ISS10102'!E153 -> 12881000000 | F48: ='ISS10102'!F153 -> 7881000000 | G48: ='ISS10102'!G153 -> 5000000000 | H48: ='ISS10102'!H153 -> 4661725350 | I48: =G48-H48 -> 338274650 | J48: =B48+K48+1 -> 37511 | K48: 273 | N48: ='ISS10102'!N153 -> 8.491 | O48: ='ISS10102'!O153 -> 93.234507 | P48: ='ISS10102'!P153 -> 9.0454394 | Q48: =((100-O48)/O48*(365/273))*100 -> 9.701815
A49: =A48+1 -> 493 | B49: =B48+7 -> 37244 | D49: ='ISS10102'!D158 -> 5000000000 | E49: ='ISS10102'!E158 -> 10769300000 | F49: ='ISS10102'!F158 -> 5769300000 | G49: ='ISS10102'!G158 -> 5000000000 | H49: ='ISS10102'!H158 -> 4649306756 | I49: =G49-H49 -> 350693244 | J49: =B49+K49+1 -> 37518 | K49: 273 | N49: ='ISS10102'!N158 -> 9.304 | O49: ='ISS10102'!O158 -> 92.986135 | P49: ='ISS10102'!P158 -> 9.3775117 | Q49: =((100-O49)/O49*(365/273))*100 -> 10.084849
A50: =A49+1 -> 494 | B50: =B49+7 -> 37251 | D50: ='ISS10102'!D163 -> 4000000000 | E50: ='ISS10102'!E163 -> 3650000000 | F50: ='ISS10102'!F163 -> -350000000 | G50: ='ISS10102'!G163 -> 3650000000 | H50: ='ISS10102'!H163 -> 3386184000 | I50: =G50-H50 -> 263816000 | J50: =B50+K50+1 -> 37525 | K50: 273 | N50: ='ISS10102'!N163 -> 9.261 | O50: ='ISS10102'!O163 -> 92.772164 | P50: ='ISS10102'!P163 -> 9.6635897 | Q50: =((100-O50)/O50*(365/273))*100 -> 10.416475
A52: =A50+1 -> 495 | B52: =B50+7 -> 37258 | D52: 3000000000 | E52: 1051000000 | F52: =E52-D52 -> -1949000000 | G52: 3000000000 | H52: 2786309700 | I52: =G52-H52 -> 213690300 | J52: =B52+K52+1 -> 37532 | K52: 273 | N52: 9.359 | O52: =H52/G52*100 -> 92.87699 | P52: =(100-O52)/100*(365/273)*100 -> 9.5234383 | Q52: =((100-O52)/O52*(365/273))*100 -> 10.253819
A53: =A52+1 -> 496 | B53: =B52+6 -> 37264 | D53: 4000000000 | E53: 12811100000 | F53: =E53-D53 -> 8811100000 | G53: 3999900000 | H53: 3730252749 | I53: =G53-H53 -> 269647251 | J53: =B53+K53+1 -> 37538 | K53: 273 | N53: 8.69 | O53: =H53/G53*100 -> 93.25865 | P53: =(100-O53)/100*(365/273)*100 -> 9.01316 | Q53: =((100-O53)/O53*(365/273))*100 -> 9.6646906
A54: =A53+1 -> 497 | B54: =B53+7 -> 37271 | D54: 5000000000 | E54: 14182000000 | F54: =E54-D54 -> 9182000000 | G54: 5000000000 | H54: 4666249410 | I54: =G54-H54 -> 333750590 | J54: =B54+K54+1 -> 37545 | K54: 273 | N54: 8.69 | O54: =H54/G54*100 -> 93.324988 | P54: =(100-O54)/100*(365/273)*100 -> 8.9244663 | Q54: =((100-O54)/O54*(365/273))*100 -> 9.5627832
A55: =A54+1 -> 498 | B55: =B54+7 -> 37278 | D55: 4000000000 | E55: 10592800000 | F55: =E55-D55 -> 6592800000 | G55: 4000000000 | H55: 3745373251 | I55: =G55-H55 -> 254626749 | J55: =B55+K55+1 -> 37552 | K55: 273 | N55: 7.8 | O55: =H55/G55*100 -> 93.634331 | P55: =(100-O55)/100*(365/273)*100 -> 8.5108758 | Q55: =((100-O55)/O55*(365/273))*100 -> 9.0894821
A56: =A55+1 -> 499 | B56: =B55+7 -> 37285 | D56: 4000000000 | E56: 10232100000 | F56: =E56-D56 -> 6232100000 | G56: 3999900000 | H56: 3766371350 | I56: =G56-H56 -> 233528650 | J56: =B56+K56+1 -> 37559 | K56: 273 | N56: 7.621 | O56: =H56/G56*100 -> 94.161638 | P56: =(100-O56)/100*(365/273)*100 -> 7.8058689 | Q56: =((100-O56)/O56*(365/273))*100 -> 8.289861
G57: =SUM(G52:G56) -> 19999800000
A60: =A56+1 -> 500 | B60: =B56+7 -> 37292 | D60: 3000000000 | E60: 9200000000 | F60: =E60-D60 -> 6200000000 | G60: 3000000000 | H60: 2838765000 | I60: =G60-H60 -> 161235000 | J60: =B60+K60+1 -> 37566 | K60: 273 | N60: 7.006 | O60: =H60/G60*100 -> 94.6255 | P60: =(100-O60)/100*(365/273)*100 -> 7.1856868 | Q60: =((100-O60)/O60*(365/273))*100 -> 7.5938165
A61: =A60+1 -> 501 | B61: =B60+7 -> 37299 | D61: 5000000000 | E61: 11773000000 | F61: =E61-D61 -> 6773000000 | G61: 4999900000 | H61: 4744320356 | I61: =G61-H61 -> 255579644 | J61: =B61+K61+1 -> 37573 | K61: 273 | N61: 6.652 | O61: =H61/G61*100 -> 94.888305 | P61: =(100-O61)/100*(365/273)*100 -> 6.8343176 | Q61: =((100-O61)/O61*(365/273))*100 -> 7.2024868
A62: =A61+1 -> 502 | B62: =B61+7 -> 37306 | D62: 5000000000 | E62: 10394500000 | F62: =E62-D62 -> 5394500000 | G62: 5000000000 | H62: 4761961255 | I62: =G62-H62 -> 238038745 | J62: =B62+K62+1 -> 37580 | K62: 273 | N62: 6.652 | O62: =H62/G62*100 -> 95.239225 | P62: =(100-O62)/100*(365/273)*100 -> 6.3651386 | Q62: =((100-O62)/O62*(365/273))*100 -> 6.6833162
A63: =A62+1 -> 503 | B63: =B62+7 -> 37313 | D63: 5000000000 | E63: 18533000000 | F63: =E63-D63 -> 13533000000 | G63: 4999800000 | H63: 4783420776 | I63: =G63-H63 -> 216379224 | J63: =B63+K63+1 -> 37587 | K63: 273 | N63: 5.25 | O63: =H63/G63*100 -> 95.672242 | P63: =(100-O63)/100*(365/273)*100 -> 5.786196 | Q63: =((100-O63)/O63*(365/273))*100 -> 6.0479361
G64: =SUM(G60:G63) -> 17999700000
A67: =A63+1 -> 504 | B67: =B63+8 -> 37321 | D67: 7000000000 | E67: 15020000000 | F67: =E67-D67 -> 8020000000 | G67: 6999900000 | H67: 6718719514 | I67: =G67-H67 -> 281180486 | J67: =B67+K67+1 -> 37595 | K67: 273 | N67: 5.25 | O67: =H67/G67*100 -> 95.983079 | P67: =(100-O67)/100*(365/273)*100 -> 5.3706093 | Q67: =((100-O67)/O67*(365/273))*100 -> 5.5953709
A68: =A67+1 -> 505 | B68: =B67+7 -> 37328 | D68: 4000000000 | E68: 10455000000 | F68: =E68-D68 -> 6455000000 | G68: 4000000000 | H68: 3848369700 | I68: =G68-H68 -> 151630300 | J68: =B68+K68+1 -> 37602 | K68: 273 | N68: 5 | O68: =H68/G68*100 -> 96.209243 | P68: =(100-O68)/100*(365/273)*100 -> 5.0682289 | Q68: =((100-O68)/O68*(365/273))*100 -> 5.2679231
A69: =A68+1 -> 506 | B69: =B68+7 -> 37335 | D69: 5000000000 | E69: 9361400000 | F69: =E69-D69 -> 4361400000 | G69: 5000000000 | H69: 4811428536 | I69: =G69-H69 -> 188571464 | J69: =B69+K69+1 -> 37609 | K69: 273 | N69: 4.5 | O69: =H69/G69*100 -> 96.228571 | P69: =(100-O69)/100*(365/273)*100 -> 5.0423871 | Q69: =((100-O69)/O69*(365/273))*100 -> 5.2400104
A70: =A69+1 -> 507 | B70: =B69+7 -> 37342 | D70: 5000000000 | E70: 5000000000 | F70: =E70-D70 -> 0 | G70: 5000000000 | H70: 4746283943 | I70: =G70-H70 -> 253716057 | J70: =B70+K70+1 -> 37616 | K70: 273 | N70: 5.141 | O70: =H70/G70*100 -> 94.925679 | P70: =(100-O70)/100*(365/273)*100 -> 6.7843488 | Q70: =((100-O70)/O70*(365/273))*100 -> 7.1470111
G71: =SUM(G67:G70) -> 20999900000
A74: =A70+1 -> 508 | B74: =B70+7 -> 37349 | D74: 3000000000 | E74: 7563700000 | F74: =E74-D74 -> 4563700000 | G74: 3000000000 | H74: 2815153506 | I74: =G74-H74 -> 184846494 | J74: =B74+K74+1 -> 37623 | K74: 273 | N74: 7.001 | O74: =H74/G74*100 -> 93.83845 | P74: =(100-O74)/100*(365/273)*100 -> 8.2379695 | Q74: =((100-O74)/O74*(365/273))*100 -> 8.7788849
A75: =A74+1 -> 509 | B75: =B74+7 -> 37356 | D75: 2500000000 | E75: 7294000000 | F75: =E75-D75 -> 4794000000 | G75: 2499900000 | H75: 2349503402 | I75: =G75-H75 -> 150396598 | J75: =B75+K75+1 -> 37630 | K75: 273 | N75: 7.501 | O75: =H75/G75*100 -> 93.983895 | P75: =(100-O75)/100*(365/273)*100 -> 8.0435098 | Q75: =((100-O75)/O75*(365/273))*100 -> 8.5583915
A76: =A75+1 -> 510 | B76: =B75+7 -> 37363 | D76: 2500000000 | E76: 9764500000 | F76: =E76-D76 -> 7264500000 | G76: 2499900000 | H76: 2352231649 | I76: =G76-H76 -> 147668351 | J76: =B76+K76+1 -> 37637 | K76: 273 | N76: 7.755 | O76: =H76/G76*100 -> 94.09303 | P76: =(100-O76)/100*(365/273)*100 -> 7.8975977 | Q76: =((100-O76)/O76*(365/273))*100 -> 8.3933929
A77: =A76+1 -> 511 | B77: =B76+7 -> 37370 | D77: 3000000000 | E77: 12230000000 | F77: =E77-D77 -> 9230000000 | G77: 3000000000 | H77: 2831268900 | I77: =G77-H77 -> 168731100 | J77: =B77+K77+1 -> 37644 | K77: 273 | N77: 7.001 | O77: =H77/G77*100 -> 94.37563 | P77: =(100-O77)/100*(365/273)*100 -> 7.5197621 | Q77: =((100-O77)/O77*(365/273))*100 -> 7.9679066
A78: =A77+1 -> 512 | B78: =B77+8 -> 37378 | D78: 4000000000 | E78: 8401700000 | F78: =E78-D78 -> 4401700000 | G78: 4000000000 | H78: 3784482319 | I78: =G78-H78 -> 215517681 | J78: =B78+K78+1 -> 37652 | K78: 273 | N78: 6.662 | O78: =H78/G78*100 -> 94.612058 | P78: =(100-O78)/100*(365/273)*100 -> 7.2036588 | Q78: =((100-O78)/O78*(365/273))*100 -> 7.6138908
G79: =SUM(G74:G78) -> 14999800000 | I79: =SUM(I74:I77) -> 651642543
I80: =+I79+I78 -> 867160224
A83: =A78+1 -> 513 | B83: =B78+7 -> 37385 | D83: 5000000000 | E83: 11622100000 | F83: =E83-D83 -> 6622100000 | G83: 5000000000 | H83: 4734247830 | I83: =G83-H83 -> 265752170 | J83: =B83+K83+1 -> 37659 | K83: 273 | N83: 6.5 | O83: =H83/G83*100 -> 94.684957 | P83: =(100-O83)/100*(365/273)*100 -> 7.1061936 | Q83: =((100-O83)/O83*(365/273))*100 -> 7.5050925
A84: =A83+1 -> 514 | B84: =B83+7 -> 37392 | D84: 6000000000 | E84: 17233900000 | F84: =E84-D84 -> 11233900000 | G84: 6000000000 | H84: 5681541098 | I84: =G84-H84 -> 318458902 | J84: =B84+K84+1 -> 37666 | K84: 273 | N84: 6.599 | O84: =H84/G84*100 -> 94.692352 | P84: =(100-O84)/100*(365/273)*100 -> 7.0963064 | Q84: =((100-O84)/O84*(365/273))*100 -> 7.494065
A85: =A84+1 -> 515 | B85: =B84+7 -> 37399 | D85: 7000000000 | E85: 14977000000 | F85: =E85-D85 -> 7977000000 | G85: 7000000000 | H85: 6611735350 | I85: =G85-H85 -> 388264650 | J85: =B85+K85+1 -> 37673 | K85: 273 | N85: 7.251 | O85: =H85/G85*100 -> 94.453362 | P85: =(100-O85)/100*(365/273)*100 -> 7.4158345 | Q85: =((100-O85)/O85*(365/273))*100 -> 7.8513187
A86: =A85+1 -> 516 | B86: =B85+7 -> 37406 | D86: 8000000000 | E86: 19149700000 | F86: =E86-D86 -> 11149700000 | G86: 7999900000 | H86: 7544200725 | I86: =G86-H86 -> 455699275 | J86: =B86+K86+1 -> 37680 | K86: 273 | N86: 7.251 | O86: =H86/G86*100 -> 94.303688 | P86: =(100-O86)/100*(365/273)*100 -> 7.6159485 | Q86: =((100-O86)/O86*(365/273))*100 -> 8.0759816
G87: =SUM(G83:G86) -> 25999900000 | I87: =SUM(I78:I86) -> 3162495445
I88: =+I87-I78 -> 2946977764
A90: =A86+1 -> 517 | B90: =B86+6 -> 37412 | D90: 8000000000 | E90: 8539000000 | F90: =E90-D90 -> 539000000 | G90: 8000000000 | H90: 7500810650 | I90: =G90-H90 -> 499189350 | J90: =B90+K90+1 -> 37686 | K90: 273 | N90: 7.3 | O90: =H90/G90*100 -> 93.760133 | P90: =(100-O90)/100*(365/273)*100 -> 8.3426792 | Q90: =((100-O90)/O90*(365/273))*100 -> 8.897896
A91: =A90+1 -> 518 | B91: =B90+7 -> 37419 | D91: 8000000000 | E91: 16803000000 | F91: =E91-D91 -> 8803000000 | G91: 8000000000 | H91: 7461812480 | I91: =G91-H91 -> 538187520 | J91: =B91+K91+1 -> 37693 | K91: 273 | N91: 7.999 | O91: =H91/G91*100 -> 93.272656 | P91: =(100-O91)/100*(365/273)*100 -> 8.9944343 | Q91: =((100-O91)/O91*(365/273))*100 -> 9.643163
A92: =A91+1 -> 519 | B92: =B91+7 -> 37426 | D92: 8000000000 | E92: 15200000000 | F92: =E92-D92 -> 7200000000 | G92: 8000000000 | H92: 7480150500 | I92: =G92-H92 -> 519849500 | J92: =B92+K92+1 -> 37700 | K92: 273 | N92: 7.501 | O92: =H92/G92*100 -> 93.501881 | P92: =(100-O92)/100*(365/273)*100 -> 8.687961 | Q92: =((100-O92)/O92*(365/273))*100 -> 9.2917499
A93: =A92+1 -> 520 | B93: =B92+7 -> 37433 | D93: 7000000000 | E93: 12519100000 | F93: =E93-D93 -> 5519100000 | G93: 7000000000 | H93: 6551726648 | I93: =G93-H93 -> 448273352 | J93: =B93+K93+1 -> 37707 | K93: 273 | N93: 7.999 | O93: =H93/G93*100 -> 93.596095 | P93: =(100-O93)/100*(365/273)*100 -> 8.5619976 | Q93: =((100-O93)/O93*(365/273))*100 -> 9.1478149
G94: =SUM(G90:G93) -> 31000000000 | I94: =SUM(I90:I93) -> 2005499722
A97: =A93+1 -> 521 | B97: =B93+7 -> 37440 | D97: 7000000000 | E97: 8025400000 | F97: =E97-D97 -> 1025400000 | G97: 7000000000 | H97: 6483990462 | I97: =G97-H97 -> 516009538 | J97: =B97+K97+1 -> 37714 | K97: 273 | N97: 8.6 | O97: =H97/G97*100 -> 92.628435 | P97: =(100-O97)/100*(365/273)*100 -> 9.8557552 | Q97: =((100-O97)/O97*(365/273))*100 -> 10.640097
A98: =A97+1 -> 522 | B98: =B97+7 -> 37447 | D98: 5000000000 | E98: 7463000000 | F98: =E98-D98 -> 2463000000 | G98: 5000000000 | H98: 4571256550 | I98: =G98-H98 -> 428743450 | J98: =B98+K98+1 -> 37721 | K98: 273 | N98: 10.164 | O98: =H98/G98*100 -> 91.425131 | P98: =(100-O98)/100*(365/273)*100 -> 11.464568 | Q98: =((100-O98)/O98*(365/273))*100 -> 12.539844
A99: =A98+1 -> 523 | B99: =B98+7 -> 37454 | D99: 8000000000 | E99: 19011000000 | F99: =E99-D99 -> 11011000000 | G99: 8000000000 | H99: 7311496900 | I99: =G99-H99 -> 688503100 | J99: =B99+K99+1 -> 37728 | K99: 273 | N99: 10.2 | O99: =H99/G99*100 -> 91.393711 | P99: =(100-O99)/100*(365/273)*100 -> 11.506577 | Q99: =((100-O99)/O99*(365/273))*100 -> 12.590118
A100: =A99+1 -> 524 | B100: =B99+7 -> 37461 | D100: 8000000000 | E100: 15965600000 | F100: =E100-D100 -> 7965600000 | G100: 8000000000 | H100: 7305812716 | I100: =G100-H100 -> 694187284 | J100: =B100+K100+1 -> 37735 | K100: 273 | N100: 11.03 | O100: =H100/G100*100 -> 91.322659 | P100: =(100-O100)/100*(365/273)*100 -> 11.601573 | Q100: =((100-O100)/O100*(365/273))*100 -> 12.703937
G102: =SUM(G97:G101) -> 28000000000
A104: =A100+1 -> 525 | B104: =B100+7 -> 37468 | D104: 8000000000 | E104: 15958700000 | F104: =E104-D104 -> 7958700000 | G104: 7999900000 | H104: 7323535915 | I104: =G104-H104 -> 676364085 | J104: =B104+K104+1 -> 37742 | K104: 273 | N104: 10.901 | O104: =H104/G104*100 -> 91.545343 | P104: =(100-O104)/100*(365/273)*100 -> 11.303845 | Q104: =((100-O104)/O104*(365/273))*100 -> 12.34781
A105: =A104+1 -> 526 | B105: =B104+7 -> 37475 | D105: 4000000000 | E105: 10664700000 | F105: =E105-D105 -> 6664700000 | G105: 3999900000 | H105: 3669435386 | I105: =G105-H105 -> 330464614 | J105: =B105+K105+1 -> 37749 | K105: 273 | N105: 10.901 | O105: =H105/G105*100 -> 91.738178 | P105: =(100-O105)/100*(365/273)*100 -> 11.046026 | Q105: =((100-O105)/O105*(365/273))*100 -> 12.040816
A106: =A105+1 -> 527 | B106: =B105+7 -> 37482 | D106: 5000000000 | E106: 6348000000 | F106: =E106-D106 -> 1348000000 | G106: 5000000000 | H106: 4543608900 | I106: =G106-H106 -> 456391100 | J106: =B106+K106+1 -> 37756 | K106: 273 | N106: 10.901 | O106: =H106/G106*100 -> 90.872178 | P106: =(100-O106)/100*(365/273)*100 -> 12.203865 | Q106: =((100-O106)/O106*(365/273))*100 -> 13.429704
A107: =A106+1 -> 528 | B107: =B106+7 -> 37489 | D107: 6000000000 | E107: 10870300000 | F107: =E107-D107 -> 4870300000 | G107: 5999900000 | H107: 5421715939 | I107: =G107-H107 -> 578184061 | J107: =B107+K107+1 -> 37763 | K107: 273 | O107: =H107/G107*100 -> 90.363438 | P107: =(100-O107)/100*(365/273)*100 -> 12.884048 | Q107: =((100-O107)/O107*(365/273))*100 -> 14.258032
A108: =A107+1 -> 529 | B108: =B107+7 -> 37496 | D108: 6000000000 | E108: 14885700000 | F108: =E108-D108 -> 8885700000 | G108: 6000000000 | H108: 5417941843 | I108: =G108-H108 -> 582058157 | J108: =B108+K108+1 -> 37770 | K108: 273 | O108: =H108/G108*100 -> 90.299031 | P108: =(100-O108)/100*(365/273)*100 -> 12.97016 | Q108: =((100-O108)/O108*(365/273))*100 -> 14.363565
G109: =SUM(G104:G108) -> 28999700000
A112: =A108+1 -> 530 | B112: =B108+7 -> 37503 | D112: 7000000000 | E112: 12797600000 | F112: =E112-D112 -> 5797600000 | G112: 7000000000 | H112: 6321387876 | I112: =G112-H112 -> 678612124 | J112: =B112+K112+1 -> 37777 | K112: 273 | O112: =H112/G112*100 -> 90.305541 | P112: =(100-O112)/100*(365/273)*100 -> 12.961456 | Q112: =((100-O112)/O112*(365/273))*100 -> 14.352891
A113: =A112+1 -> 531 | B113: =B112+7 -> 37510 | D113: 8000000000 | E113: 12675300000 | F113: =E113-D113 -> 4675300000 | G113: 7999800000 | H113: 7220848839 | I113: =G113-H113 -> 778951161 | J113: =B113+K113+1 -> 37784 | K113: 273 | O113: =H113/G113*100 -> 90.262867 | P113: =(100-O113)/100*(365/273)*100 -> 13.018511 | Q113: =((100-O113)/O113*(365/273))*100 -> 14.422887
A114: =A113+1 -> 532 | B114: =B113+7 -> 37517 | D114: 9000000000 | E114: 13563400000 | F114: =E114-D114 -> 4563400000 | G114: 9000000000 | H114: 8123340666 | I114: =G114-H114 -> 876659334 | J114: =B114+K114+1 -> 37791 | K114: 273 | O114: =H114/G114*100 -> 90.259341 | P114: =(100-O114)/100*(365/273)*100 -> 13.023226 | Q114: =((100-O114)/O114*(365/273))*100 -> 14.428674
A115: =A114+1 -> 533 | B115: =B114+7 -> 37524 | D115: 10000000000 | E115: 19400000000 | F115: =E115-D115 -> 9400000000 | G115: 10000000000 | H115: 9023461000 | I115: =G115-H115 -> 976539000 | J115: =B115+K115+1 -> 37798 | K115: 273 | O115: =H115/G115*100 -> 90.23461 | P115: =(100-O115)/100*(365/273)*100 -> 13.056291 | Q115: =((100-O115)/O115*(365/273))*100 -> 14.469271
G116: =SUM(G112:G115) -> 33999800000
A119: =A115+1 -> 534 | B119: =B115+7 -> 37531 | D119: 9000000000 | E119: 12301500000 | F119: =E119-D119 -> 3301500000 | G119: 8999900000 | H119: 8121558335 | I119: =G119-H119 -> 878341665 | J119: =B119+K119+1 -> 37805 | K119: 273 | O119: =H119/G119*100 -> 90.24054 | P119: =(100-O119)/100*(365/273)*100 -> 13.048363 | Q119: =((100-O119)/O119*(365/273))*100 -> 14.459535
A120: =A119+1 -> 535 | B120: =B119+8 -> 37539 | D120: 8000000000 | E120: 8000000000 | F120: =E120-D120 -> 0 | G120: 8000000000 | H120: 7189597200 | I120: =G120-H120 -> 810402800 | J120: =B120+K120+1 -> 37813 | K120: 273 | O120: =H120/G120*100 -> 89.869965 | P120: =(100-O120)/100*(365/273)*100 -> 13.54382 | Q120: =((100-O120)/O120*(365/273))*100 -> 15.070463
A121: =A120+1 -> 536 | B121: =B120+6 -> 37545 | D121: 8000000000 | E121: 15660000000 | F121: =E121-D121 -> 7660000000 | G121: 8000000000 | H121: 7162824500 | I121: =G121-H121 -> 837175500 | J121: =B121+K121+1 -> 37819 | K121: 273 | O121: =H121/G121*100 -> 89.535306 | P121: =(100-O121)/100*(365/273)*100 -> 13.991257 | Q121: =((100-O121)/O121*(365/273))*100 -> 15.626525
A122: =A121+1 -> 537 | B122: =B121+7 -> 37552 | D122: 10000000000 | E122: 15460000000 | F122: =E122-D122 -> 5460000000 | G122: 10000000000 | H122: 8946885400 | I122: =G122-H122 -> 1053114600 | J122: =B122+K122+1 -> 37826 | K122: 273 | O122: =H122/G122*100 -> 89.468854 | P122: =(100-O122)/100*(365/273)*100 -> 14.080104 | Q122: =((100-O122)/O122*(365/273))*100 -> 15.737436
A123: =A122+1 -> 538 | B123: =B122+7 -> 37559 | D123: 6000000000 | E123: 10040000000 | F123: =E123-D123 -> 4040000000 | G123: 6000000000 | H123: 5380365300 | I123: =G123-H123 -> 619634700 | J123: =B123+K123+1 -> 37833 | K123: 273 | O123: =H123/G123*100 -> 89.672755 | P123: =(100-O123)/100*(365/273)*100 -> 13.807489 | Q123: =((100-O123)/O123*(365/273))*100 -> 15.397641
A127: =A123+1 -> 539 | B127: =B123+7 -> 37566 | D127: 7000000000 | E127: 7136200000 | F127: =E127-D127 -> 136200000 | G127: 7000000000 | H127: 6253986328 | I127: =G127-H127 -> 746013672 | J127: =B127+K127+1 -> 37840 | K127: 273 | O127: =H127/G127*100 -> 89.342662 | P127: =(100-O127)/100*(365/273)*100 -> 14.248822 | Q127: =((100-O127)/O127*(365/273))*100 -> 15.948509
A128: =A127+1 -> 540 | B128: =B127+7 -> 37573 | D128: 7000000000 | E128: 7721400000 | F128: =E128-D128 -> 721400000 | G128: 7000000000 | H128: 6223291396 | I128: =G128-H128 -> 776708604 | J128: =B128+K128+1 -> 37847 | K128: 273 | O128: =H128/G128*100 -> 88.904163 | P128: =(100-O128)/100*(365/273)*100 -> 14.835094 | Q128: =((100-O128)/O128*(365/273))*100 -> 16.686613
A129: =A128+1 -> 541 | B129: =B128+7 -> 37580 | D129: 9000000000 | E129: 11360000000 | F129: =E129-D129 -> 2360000000 | G129: 9000000000 | H129: 7932395200 | I129: =G129-H129 -> 1067604800 | J129: =B129+K129+1 -> 37854 | K129: 273 | O129: =H129/G129*100 -> 88.137724 | P129: =(100-O129)/100*(365/273)*100 -> 15.859819 | Q129: =((100-O129)/O129*(365/273))*100 -> 17.994359
A130: =A129+1 -> 542 | B130: =B129+7 -> 37587 | D130: 8000000000 | E130: 15813000000 | F130: =E130-D130 -> 7813000000 | G130: 8000000000 | H130: 7064857530 | I130: =G130-H130 -> 935142470 | J130: =B130+K130+1 -> 37861 | K130: 273 | O130: =H130/G130*100 -> 88.310719 | P130: =(100-O130)/100*(365/273)*100 -> 15.628526 | Q130: =((100-O130)/O130*(365/273))*100 -> 17.697201
A134: =A130+1 -> 543 | B134: =B130+7 -> 37594 | D134: 8000000000 | E134: 12743500000 | F134: =E134-D134 -> 4743500000 | G134: 8000000000 | H134: 7067928445 | I134: =G134-H134 -> 932071555 | J134: =B134+K134+1 -> 37868 | K134: 273 | O134: =H134/G134*100 -> 88.349106 | P134: =(100-O134)/100*(365/273)*100 -> 15.577203 | Q134: =((100-O134)/O134*(365/273))*100 -> 17.631421
A135: =A134+1 -> 544 | B135: =B134+7 -> 37601 | D135: 8000000000 | E135: 13730000000 | F135: =E135-D135 -> 5730000000 | G135: 8000000000 | H135: 7062551400 | I135: =G135-H135 -> 937448600 | J135: =B135+K135+1 -> 37875 | K135: 273 | O135: =H135/G135*100 -> 88.281892 | P135: =(100-O135)/100*(365/273)*100 -> 15.667067 | Q135: =((100-O135)/O135*(365/273))*100 -> 17.746637
...

Sheet maturities - 364
A2: Ref:ISS9899. WK3
A3: worksheet b
A4: - | B4: - | C4: - | D4: - | E4: - | F4: - | G4: - | H4: - | I4: - | J4: - | K4: - | L4: - | M4: - | N4: - | O4: -
A5: Auction | B5: Issue date | C5: Amount offered | D5: Total bids | E5: Over/(Under) | F5: Face Value of | G5: Cost Value | H5: Interest due | I5: Date due | J5: Duration | K5: Implicit annual | L5: Clearing | M5: Lowest | N5: Weighted | O5: Average | P5: Money market yielr
A6: No | C6: in | D6: (Competitive & | E6: Subscribed | F6: issues | K6: interest rate | L6: factor | M6: factor | N6: Average | O6: Discount | Q6: Annualised | R6: Rejected Amount | S6: Bid-to-cover
C7: Auction | D7: Uncompetitive) | L7: (%) | M7: (%) | N7: Price | O7: factor | Q7: yield
B8: (1) | C8: (1a) | D8: (1b) | F8: (2) | G8: (3) | H8: (4) | I8: (5) | J8: (6) | K8: (9) | L8: (10) | M8: (11) | N8: (12) | O8: (13)
A9: - | B9: - | C9: - | D9: - | E9: - | F9: - | G9: - | H9: - | I9: - | J9: - | K9: - | L9: - | M9: - | N9: - | O9: - | Q9: -
A11: 469 | B11: 37076 | C11: ='ISS10102'!D14 -> 5000000000 | D11: ='ISS10102'!E14 -> 6412000000 | E11: ='ISS10102'!F14 -> 1412000000 | F11: ='ISS10102'!G14 -> 5000000000 | G11: ='ISS10102'!H14 -> 4459772680 | H11: ='ISS10102'!I14 -> 540227320 | I11: ='ISS10102'!J14 -> 37441 | J11: ='ISS10102'!K14 -> 364 | M11: ='ISS10102'!N14 -> 10.123 | N11: ='ISS10102'!O14 -> 89.195454 | O11: ='ISS10102'!P14 -> 10.834229 | Q11: =((100-N11)/N11*(365/364))*100 -> 12.146616 | R11: =+IF(F11<C11,IF(F11=D11,0,D11-F11),0) -> 0
A12: =A11+1 -> 470 | B12: =B11+7 -> 37083 | C12: ='ISS10102'!D19 -> 7000000000 | D12: ='ISS10102'!E19 -> 7000000000 | E12: ='ISS10102'!F19 -> 0 | F12: ='ISS10102'!G19 -> 7000000000 | G12: ='ISS10102'!H19 -> 6220102016 | H12: ='ISS10102'!I19 -> 779897984 | I12: ='ISS10102'!J19 -> 37448 | J12: ='ISS10102'!K19 -> 364 | M12: ='ISS10102'!N19 -> 9.916 | N12: ='ISS10102'!O19 -> 88.8586 | O12: ='ISS10102'!P19 -> 11.172008 | Q12: =((100-N12)/N12*(365/364))*100 -> 12.572793 | R12: =+IF(F12<C12,IF(F12=D12,0,D12-F12),0) -> 0
A13: =A12+1 -> 471 | B13: =B12+7 -> 37090 | C13: ='ISS10102'!D24 -> 7000000000 | D13: ='ISS10102'!E24 -> 7000000000 | E13: ='ISS10102'!F24 -> 0 | F13: ='ISS10102'!G24 -> 7000000000 | G13: ='ISS10102'!H24 -> 6001002268 | H13: ='ISS10102'!I24 -> 998997732 | I13: ='ISS10102'!J24 -> 37455 | J13: ='ISS10102'!K24 -> 364 | M13: ='ISS10102'!N24 -> 11 | N13: ='ISS10102'!O24 -> 85.728604 | O13: ='ISS10102'!P24 -> 14.310603 | Q13: =((100-N13)/N13*(365/364))*100 -> 16.692915 | R13: =+IF(F13<C13,IF(F13=D13,0,D13-F13),0) -> 0
A14: =A13+1 -> 472 | B14: =B13+7 -> 37097 | C14: ='ISS10102'!D29 -> 7000000000 | D14: ='ISS10102'!E29 -> 7000000000 | E14: ='ISS10102'!F29 -> 0 | F14: ='ISS10102'!G29 -> 7000000000 | G14: ='ISS10102'!H29 -> 5421688900 | H14: ='ISS10102'!I29 -> 1578311100 | I14: ='ISS10102'!J29 -> 37462 | J14: ='ISS10102'!K29 -> 364 | M14: ='ISS10102'!N29 -> 16.713 | N14: ='ISS10102'!O29 -> 77.452699 | O14: ='ISS10102'!P29 -> 22.609245 | Q14: =((100-N14)/N14*(365/364))*100 -> 29.191035 | R14: =+IF(F14<C14,IF(F14=D14,0,D14-F14),0) -> 0
R15: =+IF(F15<C15,IF(F15=D15,0,D15-F15),0) -> 0
B16: Total Jul 2001 | C16: =SUM(C11:C14) -> 26000000000 | D16: =SUM(D11:D14) -> 27412000000 | E16: =SUM(E11:E14) -> 1412000000 | F16: =SUM(F11:F14) -> 26000000000 | G16: =SUM(G11:G14) -> 22102565864 | H16: =SUM(H11:H14) -> 3897434136 | N16: =AVERAGEA(N11:N14) -> 85.308839 | O16: =AVERAGEA(O11:O14) -> 14.731521 | Q16: =AVERAGEA(Q11:Q14) -> 17.65084 | R16: =+IF(F16<C16,IF(F16=D16,0,D16-F16),0) -> 0
R17: =+IF(F17<C17,IF(F17=D17,0,D17-F17),0) -> 0 | U17: 2001
A18: =A14+1 -> 473 | B18: =B14+7 -> 37104 | C18: ='ISS10102'!D39 -> 5000000000 | D18: ='ISS10102'!E39 -> 15353400000 | E18: ='ISS10102'!F39 -> 10353400000 | F18: ='ISS10102'!G39 -> 5000000000 | G18: ='ISS10102'!H39 -> 4012973427 | H18: ='ISS10102'!I39 -> 987026573 | I18: ='ISS10102'!J39 -> 37469 | J18: ='ISS10102'!K39 -> 364 | M18: ='ISS10102'!N39 -> 15.041 | N18: ='ISS10102'!O39 -> 80.259469 | O18: ='ISS10102'!P39 -> 19.794764 | Q18: =((100-N18)/N18*(365/364))*100 -> 24.663462 | R18: =+IF(F18<C18,IF(F18=D18,0,D18-F18),0) -> 0 | U18: 2002
A19: =A18+1 -> 474 | B19: =B18+7 -> 37111 | C19: ='ISS10102'!D44 -> 7000000000 | D19: ='ISS10102'!E44 -> 15452500000 | E19: ='ISS10102'!F44 -> 8452500000 | F19: ='ISS10102'!G44 -> 7000000000 | G19: ='ISS10102'!H44 -> 5594245390 | H19: ='ISS10102'!I44 -> 1405754610 | I19: ='ISS10102'!J44 -> 37476 | J19: ='ISS10102'!K44 -> 364 | M19: ='ISS10102'!N44 -> 18 | N19: ='ISS10102'!O44 -> 79.917791 | O19: ='ISS10102'!P44 -> 20.13738 | Q19: =((100-N19)/N19*(365/364))*100 -> 25.197618 | R19: =+IF(F19<C19,IF(F19=D19,0,D19-F19),0) -> 0 | U19: 2003
A20: =A19+1 -> 475 | B20: =B19+7 -> 37118 | C20: ='ISS10102'!D49 -> 8000000000 | D20: ='ISS10102'!E49 -> 11284200000 | E20: ='ISS10102'!F49 -> 3284200000 | F20: ='ISS10102'!G49 -> 8000000000 | G20: ='ISS10102'!H49 -> 6279888734 | H20: ='ISS10102'!I49 -> 1720111266 | I20: =I19+7 -> 37483 | J20: ='ISS10102'!K49 -> 364 | M20: ='ISS10102'!N49 -> 17.047 | N20: ='ISS10102'!O49 -> 78.498609 | O20: ='ISS10102'!P49 -> 21.560461 | Q20: =((100-N20)/N20*(365/364))*100 -> 27.466042 | R20: =+IF(F20<C20,IF(F20=D20,0,D20-F20),0) -> 0 | U20: 2004
A21: =A20+1 -> 476 | B21: =B20+7 -> 37125 | C21: ='ISS10102'!D54 -> 8000000000 | D21: ='ISS10102'!E54 -> 24842300000 | E21: ='ISS10102'!F54 -> 16842300000 | F21: ='ISS10102'!G54 -> 8000000000 | G21: ='ISS10102'!H54 -> 6344013800 | H21: ='ISS10102'!I54 -> 1655986200 | I21: =I20+7 -> 37490 | J21: ='ISS10102'!K54 -> 364 | M21: ='ISS10102'!N54 -> 19.052 | N21: ='ISS10102'!O54 -> 79.300173 | O21: ='ISS10102'!P54 -> 20.756695 | Q21: =((100-N21)/N21*(365/364))*100 -> 26.174842 | R21: =+IF(F21<C21,IF(F21=D21,0,D21-F21),0) -> 0 | U21: 2005
A22: =A21+1 -> 477 | B22: =B21+7 -> 37132 | C22: ='ISS10102'!D59 -> 6000000000 | D22: ='ISS10102'!E59 -> 21190000000 | E22: ='ISS10102'!F59 -> 15190000000 | F22: ='ISS10102'!G59 -> 6000000000 | G22: ='ISS10102'!H59 -> 4895849528 | H22: ='ISS10102'!I59 -> 1104150472 | I22: =I21+7 -> 37497 | J22: ='ISS10102'!K59 -> 364 | M22: ='ISS10102'!N59 -> 17 | N22: ='ISS10102'!O59 -> 81.597492 | O22: ='ISS10102'!P59 -> 18.453064 | Q22: =((100-N22)/N22*(365/364))*100 -> 22.614744 | R22: =+IF(F22<C22,IF(F22=D22,0,D22-F22),0) -> 0 | U22: 2006
R23: =+IF(F23<C23,IF(F23=D23,0,D23-F23),0) -> 0 | U23: 2007
B24: Total Aug 2001 | C24: =SUM(C18:C22) -> 34000000000 | D24: =SUM(D18:D22) -> 88122400000 | E24: =SUM(E18:E22) -> 54122400000 | F24: =SUM(F18:F22) -> 34000000000 | G24: =SUM(G18:G22) -> 27126970879 | H24: =SUM(H18:H22) -> 6873029121 | N24: =AVERAGEA(N18:N22) -> 79.914707 | O24: =AVERAGEA(O18:O22) -> 20.140473 | Q24: =AVERAGEA(Q18:Q22) -> 25.223342 | R24: =+IF(F24<C24,IF(F24=D24,0,D24-F24),0) -> 0 | U24: 2008
R25: =+IF(F25<C25,IF(F25=D25,0,D25-F25),0) -> 0 | U25: 2009
A26: =A22+1 -> 478 | B26: =B22+7 -> 37139 | C26: ='ISS10102'!D69 -> 8000000000 | D26: ='ISS10102'!E69 -> 8000000000 | E26: ='ISS10102'!F69 -> 0 | F26: ='ISS10102'!G69 -> 8000000000 | G26: ='ISS10102'!H69 -> 6605823681 | H26: ='ISS10102'!I69 -> 1394176319 | I26: =I22+7 -> 37504 | J26: ='ISS10102'!K69 -> 364 | M26: 16.044 | N26: ='ISS10102'!O69 -> 82.572796 | O26: ='ISS10102'!P69 -> 17.475081 | Q26: =((100-N26)/N26*(365/364))*100 -> 21.163242 | R26: =+IF(F26<C26,IF(F26=D26,0,D26-F26),0) -> 0 | U26: 2010
A27: =A26+1 -> 479 | B27: =B26+7 -> 37146 | C27: ='ISS10102'!D74 -> 8000000000 | D27: ='ISS10102'!E74 -> 22810600000 | E27: ='ISS10102'!F74 -> 14810600000 | F27: ='ISS10102'!G74 -> 7999900000 | G27: ='ISS10102'!H74 -> 6714532035 | H27: =F27-G27 -> 1285367965 | I27: =I26+7 -> 37511 | J27: ='ISS10102'!K74 -> 364 | M27: ='ISS10102'!N74 -> 15.296 | N27: ='ISS10102'!O74 -> 83.9327 | O27: ='ISS10102'!P74 -> 16.111441 | Q27: =((100-N27)/N27*(365/364))*100 -> 19.195667 | R27: =+IF(F27<C27,IF(F27=D27,0,D27-F27),0) -> 14810700000 | U27: 2011
A28: =A27+1 -> 480 | B28: =B27+7 -> 37153 | C28: ='ISS10102'!D79 -> 8000000000 | D28: ='ISS10102'!E79 -> 18959200000 | E28: ='ISS10102'!F79 -> 10959200000 | F28: ='ISS10102'!G79 -> 8000000000 | G28: ='ISS10102'!H79 -> 6823165425 | H28: =F28-G28 -> 1176834575 | I28: =I27+7 -> 37518 | J28: ='ISS10102'!K79 -> 364 | M28: ='ISS10102'!N79 -> 14.165 | N28: ='ISS10102'!O79 -> 85.289568 | O28: ='ISS10102'!P79 -> 14.750845 | Q28: =((100-N28)/N28*(365/364))*100 -> 17.295017 | R28: =+IF(F28<C28,IF(F28=D28,0,D28-F28),0) -> 0 | U28: 2012
A29: 481 | B29: =B28+7 -> 37160 | C29: ='ISS10102'!D84 -> 8000000000 | D29: ='ISS10102'!E84 -> 14976600000 | E29: ='ISS10102'!F84 -> 6976600000 | F29: ='ISS10102'!G84 -> 8000000000 | G29: ='ISS10102'!H84 -> 6884172060 | H29: =F29-G29 -> 1115827940 | I29: =I28+7 -> 37525 | J29: ='ISS10102'!K84 -> 364 | M29: ='ISS10102'!N84 -> 13.136 | N29: ='ISS10102'!O84 -> 86.052151 | O29: ='ISS10102'!P84 -> 13.986168 | Q29: =((100-N29)/N29*(365/364))*100 -> 16.25313 | R29: =+IF(F29<C29,IF(F29=D29,0,D29-F29),0) -> 0 | U29: 2013
R30: =+IF(F30<C30,IF(F30=D30,0,D30-F30),0) -> 0 | U30: 2014
B31: Total Sep 2001 | C31: =SUM(C26:C29) -> 32000000000 | D31: =SUM(D26:D29) -> 64746400000 | E31: =SUM(E26:E29) -> 32746400000 | F31: =SUM(F26:F29) -> 31999900000 | G31: =SUM(G26:G29) -> 27027693201 | H31: =SUM(H26:H29) -> 4972206799 | N31: =AVERAGEA(N26:N29) -> 84.461804 | O31: =AVERAGEA(O26:O29) -> 15.580884 | Q31: =AVERAGEA(Q26:Q29) -> 18.476764 | R31: =+IF(F31<C31,IF(F31=D31,0,D31-F31),0) -> 32746500000 | U31: 2015
R32: =+IF(F32<C32,IF(F32=D32,0,D32-F32),0) -> 0 | U32: 2016
A33: =A29+1 -> 482 | B33: =B29+7 -> 37167 | C33: ='ISS10102'!D94 -> 8000000000 | D33: ='ISS10102'!E94 -> 13773000000 | E33: ='ISS10102'!F94 -> 5773000000 | F33: ='ISS10102'!G94 -> 8000000000 | G33: ='ISS10102'!H94 -> 6897486170 | H33: =F33-G33 -> 1102513830 | I33: =I29+7 -> 37532 | J33: ='ISS10102'!K94 -> 364 | M33: ='ISS10102'!N94 -> 12.5 | N33: ='ISS10102'!O94 -> 86.218577 | O33: ='ISS10102'!P94 -> 13.819284 | Q33: =((100-N33)/N33*(365/364))*100 -> 16.028198 | R33: =+IF(F33<C33,IF(F33=D33,0,D33-F33),0) -> 0 | U33: 2017
A34: =A33+1 -> 483 | B34: =B33+7 -> 37174 | C34: ='ISS10102'!D99 -> 8000000000 | D34: ='ISS10102'!E99 -> 16275100000 | E34: ='ISS10102'!F99 -> 8275100000 | F34: ='ISS10102'!G99 -> 8000000000 | G34: ='ISS10102'!H99 -> 6901193713 | H34: =F34-G34 -> 1098806287 | I34: =B34+J34+1 -> 37539 | J34: ='ISS10102'!K99 -> 364 | M34: ='ISS10102'!N99 -> 12.93 | N34: ='ISS10102'!O99 -> 86.264921 | O34: ='ISS10102'!P99 -> 13.772812 | Q34: =((100-N34)/N34*(365/364))*100 -> 15.965716 | R34: =+IF(F34<C34,IF(F34=D34,0,D34-F34),0) -> 0 | U34: 2018
A35: =A34+1 -> 484 | B35: =B34+7 -> 37181 | C35: ='ISS10102'!D104 -> 8000000000 | D35: ='ISS10102'!E104 -> 17358000000 | E35: ='ISS10102'!F104 -> 9358000000 | F35: ='ISS10102'!G104 -> 8000000000 | G35: ='ISS10102'!H104 -> 6931435340 | H35: =F35-G35 -> 1068564660 | I35: =B35+J35+1 -> 37546 | J35: ='ISS10102'!K104 -> 364 | M35: ='ISS10102'!N104 -> 12 | N35: ='ISS10102'!O104 -> 86.642942 | O35: ='ISS10102'!P104 -> 13.393753 | Q35: =((100-N35)/N35*(365/364))*100 -> 15.458563 | R35: =+IF(F35<C35,IF(F35=D35,0,D35-F35),0) -> 0 | U35: 2019
A36: =A35+1 -> 485 | B36: =B35+7 -> 37188 | C36: ='ISS10102'!D109 -> 8000000000 | D36: ='ISS10102'!E109 -> 14369500000 | E36: ='ISS10102'!F109 -> 6369500000 | F36: ='ISS10102'!G109 -> 8000000000 | G36: ='ISS10102'!H109 -> 6997034628 | H36: =F36-G36 -> 1002965372 | I36: =B36+J36+1 -> 37553 | J36: ='ISS10102'!K109 -> 364 | M36: ='ISS10102'!N109 -> 12 | N36: ='ISS10102'!O109 -> 87.462933 | O36: ='ISS10102'!P109 -> 12.57151 | Q36: =((100-N36)/N36*(365/364))*100 -> 14.373529 | R36: =+IF(F36<C36,IF(F36=D36,0,D36-F36),0) -> 0 | U36: 2020
A37: =A36+1 -> 486 | B37: =B36+7 -> 37195 | C37: ='ISS10102'!D114 -> 5000000000 | D37: ='ISS10102'!E114 -> 15853700000 | E37: ='ISS10102'!F114 -> 10853700000 | F37: ='ISS10102'!G114 -> 4999900000 | G37: ='ISS10102'!H114 -> 4402932800 | H37: =F37-G37 -> 596967200 | I37: =B37+J37+1 -> 37560 | J37: ='ISS10102'!K114 -> 364 | M37: ='ISS10102'!N114 -> 11 | N37: ='ISS10102'!O114 -> 88.060417 | O37: ='ISS10102'!P114 -> 11.972384 | Q37: =((100-N37)/N37*(365/364))*100 -> 13.595647 | R37: =+IF(F37<C37,IF(F37=D37,0,D37-F37),0) -> 10853800000 | U37: 2021
R38: =+IF(F38<C38,IF(F38=D38,0,D38-F38),0) -> 0 | U38: 2022
B39: Total Oct 2001 | C39: =SUM(C33:C37) -> 37000000000 | D39: =SUM(D33:D37) -> 77629300000 | E39: =SUM(E33:E37) -> 40629300000 | F39: =SUM(F33:F37) -> 36999900000 | G39: =SUM(G33:G37) -> 32130082651 | H39: =SUM(H33:H37) -> 4869817349 | N39: =AVERAGEA(N33:N37) -> 86.929958 | O39: =AVERAGEA(O33:O37) -> 13.105949 | Q39: =AVERAGEA(Q33:Q37) -> 15.08433 | R39: =+IF(F39<C39,IF(F39=D39,0,D39-F39),0) -> 40629400000
R40: =+IF(F40<C40,IF(F40=D40,0,D40-F40),0) -> 0
A41: =A37+1 -> 487 | B41: =B37+7 -> 37202 | C41: ='ISS10102'!D124 -> 8000000000 | D41: ='ISS10102'!E124 -> 17576200000 | E41: ='ISS10102'!F124 -> 9576200000 | F41: ='ISS10102'!G124 -> 7999800000 | G41: ='ISS10102'!H124 -> 7104350028 | H41: =F41-G41 -> 895449972 | I41: =B41+J41+1 -> 37567 | J41: ='ISS10102'!K124 -> 364 | M41: ='ISS10102'!N124 -> 9.913 | N41: ='ISS10102'!O124 -> 88.806596 | O41: ='ISS10102'!P124 -> 11.224156 | Q41: =((100-N41)/N41*(365/364))*100 -> 12.638876 | R41: =+IF(F41<C41,IF(F41=D41,0,D41-F41),0) -> 9576400000
A42: =A41+1 -> 488 | B42: =B41+7 -> 37209 | C42: ='ISS10102'!D129 -> 9000000000 | D42: ='ISS10102'!E129 -> 21839200000 | E42: ='ISS10102'!F129 -> 12839200000 | F42: ='ISS10102'!G129 -> 9000000000 | G42: ='ISS10102'!H129 -> 7966065155 | H42: =F42-G42 -> 1033934845 | I42: =B42+J42+1 -> 37574 | J42: ='ISS10102'!K129 -> 364 | M42: ='ISS10102'!N129 -> 10.027 | N42: ='ISS10102'!O129 -> 88.511835 | O42: ='ISS10102'!P129 -> 11.519726 | Q42: =((100-N42)/N42*(365/364))*100 -> 13.014899 | R42: =+IF(F42<C42,IF(F42=D42,0,D42-F42),0) -> 0
A43: =A42+1 -> 489 | B43: =B42+7 -> 37216 | C43: ='ISS10102'!D134 -> 10000000000 | D43: ='ISS10102'!E134 -> 25987700000 | E43: ='ISS10102'!F134 -> 15987700000 | F43: ='ISS10102'!G134 -> 10000000000 | G43: ='ISS10102'!H134 -> 8859862207 | H43: =F43-G43 -> 1140137793 | I43: =B43+J43+1 -> 37581 | J43: ='ISS10102'!K134 -> 364 | M43: ='ISS10102'!N134 -> 11 | N43: ='ISS10102'!O134 -> 88.598622 | O43: ='ISS10102'!P134 -> 11.4327 | Q43: =((100-N43)/N43*(365/364))*100 -> 12.903926 | R43: =+IF(F43<C43,IF(F43=D43,0,D43-F43),0) -> 0
A44: =A43+1 -> 490 | B44: =B43+7 -> 37223 | C44: ='ISS10102'!D139 -> 10000000000 | D44: ='ISS10102'!E139 -> 30302300000 | E44: ='ISS10102'!F139 -> 20302300000 | F44: ='ISS10102'!G139 -> 10000000000 | G44: ='ISS10102'!H139 -> 8899862681 | H44: =F44-G44 -> 1100137319 | I44: =B44+J44+1 -> 37588 | J44: ='ISS10102'!K139 -> 364 | M44: ='ISS10102'!N139 -> 10.318 | N44: ='ISS10102'!O139 -> 88.998627 | O44: ='ISS10102'!P139 -> 11.031597 | Q44: =((100-N44)/N44*(365/364))*100 -> 12.395244 | R44: =+IF(F44<C44,IF(F44=D44,0,D44-F44),0) -> 0
R45: =+IF(F45<C45,IF(F45=D45,0,D45-F45),0) -> 0
B46: Total Nov 2001 | C46: =SUM(C41:C44) -> 37000000000 | D46: =SUM(D41:D44) -> 95705400000 | E46: =SUM(E41:E44) -> 58705400000 | F46: =SUM(F41:F44) -> 36999800000 | G46: =SUM(G41:G44) -> 32830140071 | H46: =SUM(H41:H44) -> 4169659929 | N46: =AVERAGEA(N41:N44) -> 88.72892 | O46: =AVERAGEA(O41:O44) -> 11.302045 | Q46: =AVERAGEA(Q41:Q44) -> 12.738236 | R46: =+IF(F46<C46,IF(F46=D46,0,D46-F46),0) -> 58705600000
R47: =+IF(F47<C47,IF(F47=D47,0,D47-F47),0) -> 0
A48: =A44+1 -> 491 | B48: =B44+7 -> 37230 | C48: ='ISS10102'!D149 -> 12000000000 | D48: ='ISS10102'!E149 -> 24015700000 | E48: ='ISS10102'!F149 -> 12015700000 | F48: ='ISS10102'!G149 -> 11999900000 | G48: ='ISS10102'!H149 -> 10752803294 | H48: =F48-G48 -> 1247096706 | I48: =B48+J48+1 -> 37595 | J48: ='ISS10102'!K149 -> 364 | M48: ='ISS10102'!N149 -> 9.917 | N48: ='ISS10102'!O149 -> 89.607441 | O48: ='ISS10102'!P149 -> 10.42111 | Q48: =((100-N48)/N48*(365/364))*100 -> 11.629737 | R48: =+IF(F48<C48,IF(F48=D48,0,D48-F48),0) -> 12015800000
A49: =A48+1 -> 492 | B49: =B48+7 -> 37237 | C49: ='ISS10102'!D154 -> 14000000000 | D49: ='ISS10102'!E154 -> 22839600000 | E49: ='ISS10102'!F154 -> 8839600000 | F49: ='ISS10102'!G154 -> 14000000000 | G49: ='ISS10102'!H154 -> 12527387718 | H49: =F49-G49 -> 1472612282 | I49: =B49+J49+1 -> 37602 | J49: ='ISS10102'!K154 -> 364 | M49: ='ISS10102'!N154 -> 9.526 | N49: ='ISS10102'!O154 -> 89.481341 | O49: ='ISS10102'!P154 -> 10.547557 | Q49: =((100-N49)/N49*(365/364))*100 -> 11.787437 | R49: =+IF(F49<C49,IF(F49=D49,0,D49-F49),0) -> 0
A50: =A49+1 -> 493 | B50: =B49+7 -> 37244 | C50: ='ISS10102'!D159 -> 14000000000 | D50: ='ISS10102'!E159 -> 33184300000 | E50: ='ISS10102'!F159 -> 19184300000 | F50: ='ISS10102'!G159 -> 14000000000 | G50: ='ISS10102'!H159 -> 12555527288 | H50: =F50-G50 -> 1444472712 | I50: =B50+J50+1 -> 37609 | J50: ='ISS10102'!K159 -> 364 | M50: ='ISS10102'!N159 -> 9.506 | N50: ='ISS10102'!O159 -> 89.682338 | O50: ='ISS10102'!P159 -> 10.346007 | Q50: =((100-N50)/N50*(365/364))*100 -> 11.536282 | R50: =+IF(F50<C50,IF(F50=D50,0,D50-F50),0) -> 0
A51: =A50+1 -> 494 | B51: =B50+7 -> 37251 | C51: ='ISS10102'!D164 -> 7000000000 | D51: ='ISS10102'!E164 -> 7423500000 | E51: ='ISS10102'!F164 -> 423500000 | F51: ='ISS10102'!G164 -> 7000000000 | G51: ='ISS10102'!H164 -> 6240697350 | H51: =F51-G51 -> 759302650 | I51: =B51+J51+1 -> 37616 | J51: ='ISS10102'!K164 -> 364 | M51: ='ISS10102'!N164 -> 10 | N51: ='ISS10102'!O164 -> 89.152819 | O51: ='ISS10102'!P164 -> 10.876981 | Q51: =((100-N51)/N51*(365/364))*100 -> 12.200378 | R51: =+IF(F51<C51,IF(F51=D51,0,D51-F51),0) -> 0
F52: =SUM(F48:F51) -> 46999900000 | G52: =SUM(G48:G51) -> 42076415650 | H52: =SUM(H48:H51) -> 4923484350 | R52: =+IF(F52<C52,IF(F52=D52,0,D52-F52),0) -> 0
A53: =A51+1 -> 495 | B53: =B51+7 -> 37258 | C53: 5000000000 | D53: 13682200000 | E53: =D53-C53 -> 8682200000 | F53: 4999900000 | G53: 4484401670 | H53: =F53-G53 -> 515498330 | I53: =B53+J53+1 -> 37623 | J53: 364 | M53: 10 | N53: =G53/F53*100 -> 89.689827 | O53: =(100-N53)/100*(365/364)*100 -> 10.338497 | Q53: =((100-N53)/N53*(365/364))*100 -> 11.526945 | R53: =+IF(F53<C53,IF(F53=D53,0,D53-F53),0) -> 8682300000
A54: =A53+1 -> 496 | B54: =B53+6 -> 37264 | C54: 7000000000 | D54: 19588600000 | E54: =D54-C54 -> 12588600000 | F54: 7000000000 | G54: 6288363404 | H54: =F54-G54 -> 711636596 | I54: =B54+J54+1 -> 37629 | J54: 364 | M54: 10 | N54: =G54/F54*100 -> 89.833763 | O54: =(100-N54)/100*(365/364)*100 -> 10.194166 | Q54: =((100-N54)/N54*(365/364))*100 -> 11.347812 | R54: =+IF(F54<C54,IF(F54=D54,0,D54-F54),0) -> 0
A55: =A54+1 -> 497 | B55: =B54+7 -> 37271 | C55: 8000000000 | D55: 22712000000 | E55: =D55-C55 -> 14712000000 | F55: 8000000000 | G55: 7236473860 | H55: =F55-G55 -> 763526140 | I55: =B55+J55+1 -> 37636 | J55: 364 | M55: 9.095 | N55: =G55/F55*100 -> 90.455923 | O55: =(100-N55)/100*(365/364)*100 -> 9.5702967 | Q55: =((100-N55)/N55*(365/364))*100 -> 10.580066 | R55: =+IF(F55<C55,IF(F55=D55,0,D55-F55),0) -> 0
A56: =A55+1 -> 498 | B56: =B55+7 -> 37278 | C56: 7000000000 | D56: 13386600000 | E56: =D56-C56 -> 6386600000 | F56: 6999900000 | G56: 6355628184 | H56: =F56-G56 -> 644271816 | I56: =B56+J56+1 -> 37643 | J56: 364 | M56: 9 | N56: =G56/F56*100 -> 90.795985 | O56: =(100-N56)/100*(365/364)*100 -> 9.2293003 | Q56: =((100-N56)/N56*(365/364))*100 -> 10.164877 | R56: =+IF(F56<C56,IF(F56=D56,0,D56-F56),0) -> 6386700000
A57: =A56+1 -> 499 | B57: =B56+7 -> 37285 | C57: 5000000000 | D57: 13725900000 | E57: =D57-C57 -> 8725900000 | F57: 5000000000 | G57: 4568554122 | H57: =F57-G57 -> 431445878 | I57: =B57+J57+1 -> 37650 | J57: 364 | M57: 8.408 | N57: =G57/F57*100 -> 91.371082 | O57: =(100-N57)/100*(365/364)*100 -> 8.6526234 | Q57: =((100-N57)/N57*(365/364))*100 -> 9.4697613 | R57: =+IF(F57<C57,IF(F57=D57,0,D57-F57),0) -> 0
F58: =SUM(F53:F57) -> 31999800000 | G58: =SUM(G53:G57) -> 28933421240 | H58: =SUM(H53:H57) -> 3066378760 | R58: =+IF(F58<C58,IF(F58=D58,0,D58-F58),0) -> 0
R59: =+IF(F59<C59,IF(F59=D59,0,D59-F59),0) -> 0
R60: =+IF(F60<C60,IF(F60=D60,0,D60-F60),0) -> 0
A61: =A57+1 -> 500 | B61: =B57+7 -> 37292 | C61: 4000000000 | D61: 12168900000 | E61: =D61-C61 -> 8168900000 | F61: 4000000000 | G61: 3685343229 | H61: =F61-G61 -> 314656771 | I61: =B61+J61+1 -> 37657 | J61: 364 | M61: 6.15 | N61: =G61/F61*100 -> 92.133581 | O61: =(100-N61)/100*(365/364)*100 -> 7.8880303 | Q61: =((100-N61)/N61*(365/364))*100 -> 8.561515 | R61: =+IF(F61<C61,IF(F61=D61,0,D61-F61),0) -> 0
A62: =A61+1 -> 501 | B62: =B61+7 -> 37299 | C62: 7000000000 | D62: 15791900000 | E62: =D62-C62 -> 8791900000 | F62: 7000000000 | G62: 6505899352 | H62: =F62-G62 -> 494100648 | I62: =B62+J62+1 -> 37664 | J62: 364 | M62: 6.518 | N62: =G62/F62*100 -> 92.941419 | O62: =(100-N62)/100*(365/364)*100 -> 7.0779724 | Q62: =((100-N62)/N62*(365/364))*100 -> 7.61552 | R62: =+IF(F62<C62,IF(F62=D62,0,D62-F62),0) -> 0
A63: =A62+1 -> 502 | B63: =B62+7 -> 37306 | C63: 8000000000 | D63: 16001000000 | E63: =D63-C63 -> 8001000000 | F63: 8000000000 | G63: 7473783870 | H63: =F63-G63 -> 526216130 | I63: =B63+J63+1 -> 37671 | J63: 364 | M63: 6.518 | N63: =G63/F63*100 -> 93.422298 | O63: =(100-N63)/100*(365/364)*100 -> 6.5957722 | Q63: =((100-N63)/N63*(365/364))*100 -> 7.0601691 | R63: =+IF(F63<C63,IF(F63=D63,0,D63-F63),0) -> 0
A64: =A63+1 -> 503 | B64: =B63+7 -> 37313 | C64: 8000000000 | D64: 27365000000 | E64: =D64-C64 -> 19365000000 | F64: 7999900000 | G64: 7527193209 | H64: =F64-G64 -> 472706791 | I64: =B64+J64+1 -> 37678 | J64: 364 | M64: 5.8 | N64: =G64/F64*100 -> 94.091091 | O64: =(100-N64)/100*(365/364)*100 -> 5.925142 | Q64: =((100-N64)/N64*(365/364))*100 -> 6.2972402 | R64: =+IF(F64<C64,IF(F64=D64,0,D64-F64),0) -> 19365100000
F65: =SUM(F61:F64) -> 26999900000 | G65: =SUM(G61:G64) -> 25192219660 | H65: =SUM(H61:H64) -> 1807680340 | R65: =+IF(F65<C65,IF(F65=D65,0,D65-F65),0) -> 0
R66: =+IF(F66<C66,IF(F66=D66,0,D66-F66),0) -> 0
R67: =+IF(F67<C67,IF(F67=D67,0,D67-F67),0) -> 0
A68: =A64+1 -> 504 | B68: =B64+7 -> 37320 | C68: 9000000000 | D68: 15333500000 | E68: =D68-C68 -> 6333500000 | F68: 9000000000 | G68: 8484088070 | H68: =F68-G68 -> 515911930 | I68: =B68+J68+1 -> 37685 | J68: 364 | M68: 5 | N68: =G68/F68*100 -> 94.267645 | O68: =(100-N68)/100*(365/364)*100 -> 5.748103 | Q68: =((100-N68)/N68*(365/364))*100 -> 6.0976414 | R68: =+IF(F68<C68,IF(F68=D68,0,D68-F68),0) -> 0
A69: =A68+1 -> 505 | B69: =B68+7 -> 37327 | C69: 7000000000 | D69: 16729300000 | E69: =D69-C69 -> 9729300000 | F69: 7000000000 | G69: 6631105040 | H69: =F69-G69 -> 368894960 | I69: =B69+J69+1 -> 37692 | J69: 364 | M69: 4.9 | N69: =G69/F69*100 -> 94.730072 | O69: =(100-N69)/100*(365/364)*100 -> 5.2844058 | Q69: =((100-N69)/N69*(365/364))*100 -> 5.5783826 | R69: =+IF(F69<C69,IF(F69=D69,0,D69-F69),0) -> 0
A70: =A69+1 -> 506 | B70: =B69+7 -> 37334 | C70: 8000000000 | D70: 15313300000 | E70: =D70-C70 -> 7313300000 | F70: 8000000000 | G70: 7566138224 | H70: =F70-G70 -> 433861776 | I70: =B70+J70+1 -> 37699 | J70: 364 | M70: 4.9 | N70: =G70/F70*100 -> 94.576728 | O70: =(100-N70)/100*(365/364)*100 -> 5.4381713 | Q70: =((100-N70)/N70*(365/364))*100 -> 5.75001 | R70: =+IF(F70<C70,IF(F70=D70,0,D70-F70),0) -> 0
A71: =A70+1 -> 507 | B71: =B70+7 -> 37341 | C71: 8000000000 | D71: 8000000000 | E71: =D71-C71 -> 0 | F71: 8000000000 | G71: 7521016860 | H71: =F71-G71 -> 478983140 | I71: =B71+J71+1 -> 37706 | J71: 364 | M71: 5.241 | N71: =G71/F71*100 -> 94.012711 | O71: =(100-N71)/100*(365/364)*100 -> 6.0037378 | Q71: =((100-N71)/N71*(365/364))*100 -> 6.3860916 | R71: =+IF(F71<C71,IF(F71=D71,0,D71-F71),0) -> 0
F72: =SUM(F68:F71) -> 32000000000 | G72: =SUM(G68:G71) -> 30202348194 | H72: =SUM(H68:H71) -> 1797651806 | R72: =+IF(F72<C72,IF(F72=D72,0,D72-F72),0) -> 0
R73: =+IF(F73<C73,IF(F73=D73,0,D73-F73),0) -> 0
R74: =+IF(F74<C74,IF(F74=D74,0,D74-F74),0) -> 0
A75: =A71+1 -> 508 | B75: =B71+8 -> 37349 | C75: 3500000000 | D75: 6618000000 | E75: =D75-C75 -> 3118000000 | F75: 3500000000 | G75: 3186720820 | H75: =F75-G75 -> 313279180 | I75: =B75+J75+1 -> 37714 | J75: 364 | M75: 6.5 | N75: =G75/F75*100 -> 91.049166 | O75: =(100-N75)/100*(365/364)*100 -> 8.9754239 | Q75: =((100-N75)/N75*(365/364))*100 -> 9.8577772 | R75: =+IF(F75<C75,IF(F75=D75,0,D75-F75),0) -> 0
A76: =A75+1 -> 509 | B76: =B75+7 -> 37356 | C76: 3000000000 | D76: 10130500000 | E76: =D76-C76 -> 7130500000 | F76: 3000000000 | G76: 2741836970 | H76: =F76-G76 -> 258163030 | I76: =B76+J76+1 -> 37721 | J76: 364 | M76: 7 | N76: =G76/F76*100 -> 91.394566 | O76: =(100-N76)/100*(365/364)*100 -> 8.6290756 | Q76: =((100-N76)/N76*(365/364))*100 -> 9.4415632 | R76: =+IF(F76<C76,IF(F76=D76,0,D76-F76),0) -> 0
A77: =A76+1 -> 510 | B77: =B76+7 -> 37363 | C77: 3000000000 | D77: 14193000000 | E77: =D77-C77 -> 11193000000 | F77: 3000000000 | G77: 2761343400 | H77: =F77-G77 -> 238656600 | I77: =B77+J77+1 -> 37728 | J77: 364 | M77: 7.22 | N77: =G77/F77*100 -> 92.04478 | O77: =(100-N77)/100*(365/364)*100 -> 7.977075 | Q77: =((100-N77)/N77*(365/364))*100 -> 8.6665154 | R77: =+IF(F77<C77,IF(F77=D77,0,D77-F77),0) -> 0
A78: =A77+1 -> 511 | B78: =B77+7 -> 37370 | C78: 4000000000 | D78: 13523300000 | E78: =D78-C78 -> 9523300000 | F78: 4000000000 | G78: 3704676041 | H78: =F78-G78 -> 295323959 | I78: =B78+J78+1 -> 37735 | J78: 364 | M78: 7.22 | N78: =G78/F78*100 -> 92.616901 | O78: =(100-N78)/100*(365/364)*100 -> 7.4033822 | Q78: =((100-N78)/N78*(365/364))*100 -> 7.9935542 | R78: =+IF(F78<C78,IF(F78=D78,0,D78-F78),0) -> 0
F79: =SUM(F75:F78) -> 13500000000 | G79: =SUM(G75:G78) -> 12394577231 | H79: =SUM(H75:H78) -> 1105422769 | R79: =+IF(F79<C79,IF(F79=D79,0,D79-F79),0) -> 0
R80: =+IF(F80<C80,IF(F80=D80,0,D80-F80),0) -> 0
R81: =+IF(F81<C81,IF(F81=D81,0,D81-F81),0) -> 0
A82: =A78+1 -> 512 | B82: =B78+8 -> 37378 | C82: 6000000000 | D82: 12186600000 | E82: =D82-C82 -> 6186600000 | F82: 6000000000 | G82: 5564075810 | H82: =F82-G82 -> 435924190 | I82: =B82+J82+1 -> 37743 | J82: 364 | M82: 7 | N82: =G82/F82*100 -> 92.734597 | O82: =(100-N82)/100*(365/364)*100 -> 7.2853631 | Q82: =((100-N82)/N82*(365/364))*100 -> 7.8561436 | R82: =+IF(F82<C82,IF(F82=D82,0,D82-F82),0) -> 0
A83: =A82+1 -> 513 | B83: =B82+6 -> 37384 | C83: 9500000000 | D83: 19534500000 | E83: =D83-C83 -> 10034500000 | F83: 9500000000 | G83: 8797209590 | H83: =F83-G83 -> 702790410 | I83: =B83+J83+1 -> 37749 | J83: 364 | M83: 6.267 | N83: =G83/F83*100 -> 92.602206 | O83: =(100-N83)/100*(365/364)*100 -> 7.4181174 | Q83: =((100-N83)/N83*(365/364))*100 -> 8.0107351 | R83: =+IF(F83<C83,IF(F83=D83,0,D83-F83),0) -> 0
A84: =A83+1 -> 514 | B84: =B83+7 -> 37391 | C84: 10000000000 | D84: 19534500000 | E84: =D84-C84 -> 9534500000 | F84: 9999900000 | G84: 9254771040 | H84: =F84-G84 -> 745128960 | I84: =B84+J84+1 -> 37756 | J84: 364 | M84: 6.267 | N84: =G84/F84*100 -> 92.548636 | O84: =(100-N84)/100*(365/364)*100 -> 7.4718349 | Q84: =((100-N84)/N84*(365/364))*100 -> 8.0734144 | R84: =+IF(F84<C84,IF(F84=D84,0,D84-F84),0) -> 9534600000
A85: =A84+1 -> 515 | B85: =B84+7 -> 37398 | C85: 12000000000 | D85: 22817000000 | E85: =D85-C85 -> 10817000000 | F85: 12000000000 | G85: 11044651090 | H85: =F85-G85 -> 955348910 | I85: =B85+J85+1 -> 37763 | J85: 364 | M85: 7.4 | N85: =G85/F85*100 -> 92.038759 | O85: =(100-N85)/100*(365/364)*100 -> 7.9831125 | Q85: =((100-N85)/N85*(365/364))*100 -> 8.673642 | R85: =+IF(F85<C85,IF(F85=D85,0,D85-F85),0) -> 0
A86: =A85+1 -> 516 | B86: =B85+7 -> 37405 | C86: 13000000000 | D86: 29859000000 | E86: =D86-C86 -> 16859000000 | F86: 13000000000 | G86: 11960876778 | H86: =F86-G86 -> 1039123222 | I86: =B86+J86+1 -> 37770 | J86: 364 | M86: 7.41 | N86: =G86/F86*100 -> 92.006744 | O86: =(100-N86)/100*(365/364)*100 -> 8.015215 | Q86: =((100-N86)/N86*(365/364))*100 -> 8.7115516 | R86: =+IF(F86<C86,IF(F86=D86,0,D86-F86),0) -> 0
F87: =SUM(F82:F86) -> 50499900000 | G87: =SUM(G82:G86) -> 46621584308 | H87: =SUM(H82:H86) -> 3878315692 | R87: =+IF(F87<C87,IF(F87=D87,0,D87-F87),0) -> 0
R88: =+IF(F88<C88,IF(F88=D88,0,D88-F88),0) -> 0
R89: =+IF(F89<C89,IF(F89=D89,0,D89-F89),0) -> 0
A90: =A86+1 -> 517 | B90: =B86+7 -> 37412 | C90: 13000000000 | D90: 13249000000 | E90: =D90-C90 -> 249000000 | F90: 13000000000 | G90: 11818893781 | H90: =F90-G90 -> 1181106219 | I90: =B90+J90+1 -> 37777 | J90: 364 | M90: 7.621 | N90: =G90/F90*100 -> 90.914568 | O90: =(100-N90)/100*(365/364)*100 -> 9.1103924 | Q90: =((100-N90)/N90*(365/364))*100 -> 10.020828 | R90: =+IF(F90<C90,IF(F90=D90,0,D90-F90),0) -> 0
A91: =A90+1 -> 518 | B91: =B90+7 -> 37419 | C91: 13000000000 | D91: 31583600000 | E91: =D91-C91 -> 18583600000 | F91: 13000000000 | G91: 11623424596 | H91: =F91-G91 -> 1376575404 | I91: =B91+J91+1 -> 37784 | J91: 364 | M91: 9.094 | N91: =G91/F91*100 -> 89.410958 | O91: =(100-N91)/100*(365/364)*100 -> 10.618132 | Q91: =((100-N91)/N91*(365/364))*100 -> 11.87565 | R91: =+IF(F91<C91,IF(F91=D91,0,D91-F91),0) -> 0
A92: =A91+1 -> 519 | B92: =B91+7 -> 37426 | C92: 13000000000 | D92: 26487100000 | E92: =D92-C92 -> 13487100000 | F92: 13000000000 | G92: 11626312202 | H92: =F92-G92 -> 1373687798 | I92: =B92+J92+1 -> 37791 | J92: 364 | M92: 9.094 | N92: =G92/F92*100 -> 89.433171 | O92: =(100-N92)/100*(365/364)*100 -> 10.595859 | Q92: =((100-N92)/N92*(365/364))*100 -> 11.847795 | R92: =+IF(F92<C92,IF(F92=D92,0,D92-F92),0) -> 0
A93: =A92+1 -> 520 | B93: =B92+7 -> 37433 | C93: 12000000000 | D93: 24069700000 | E93: =D93-C93 -> 12069700000 | F93: 11999900000 | G93: 10837146478 | H93: =F93-G93 -> 1162753522 | I93: =B93+J93+1 -> 37798 | J93: 364 | M93: 10.729 | N93: =G93/F93*100 -> 90.310307 | O93: =(100-N93)/100*(365/364)*100 -> 9.7163135 | Q93: =((100-N93)/N93*(365/364))*100 -> 10.758809 | R93: =+IF(F93<C93,IF(F93=D93,0,D93-F93),0) -> 12069800000
F94: =SUM(F90:F93) -> 50999900000 | G94: =SUM(G90:G93) -> 45905777057 | H94: =SUM(H90:H93) -> 5094122943 | R94: =+IF(F94<C94,IF(F94=D94,0,D94-F94),0) -> 0
F95: =F94+F87+F79+F72+F65+F58+F52+F46+F39+F31+F24+F16 -> 418999000000 | G95: =G94+G87+G79+G72+G65+G58+G52+G46+G39+G31+G24+G16 -> 372543796006 | H95: =H94+H87+H79+H72+H65+H58+H52+H46+H39+H31+H24+H16 -> 46455203994 | R95: =+IF(F95<C95,IF(F95=D95,0,D95-F95),0) -> 0
R96: =+IF(F96<C96,IF(F96=D96,0,D96-F96),0) -> 0
A97: =A93+1 -> 521 | B97: =B93+7 -> 37440 | C97: 12000000000 | D97: 19147900000 | E97: =D97-C97 -> 7147900000 | F97: 12000000000 | G97: 10741081490 | H97: =F97-G97 -> 1258918510 | I97: =B97+J97+1 -> 37805 | J97: 364 | M97: 8.684 | N97: =G97/F97*100 -> 89.509012 | O97: =(100-N97)/100*(365/364)*100 -> 10.519809 | Q97: =((100-N97)/N97*(365/364))*100 -> 11.752793 | R97: =+IF(F97<C97,IF(F97=D97,0,D97-F97),0) -> 0
A98: =A97+1 -> 522 | B98: =B97+7 -> 37447 | C98: 10000000000 | D98: 30229000000 | E98: =D98-C98 -> 20229000000 | F98: 10000000000 | G98: 9032163706 | H98: =F98-G98 -> 967836294 | I98: =B98+J98+1 -> 37812 | J98: 364 | M98: 9.297 | N98: =G98/F98*100 -> 90.321637 | O98: =(100-N98)/100*(365/364)*100 -> 9.7049518 | Q98: =((100-N98)/N98*(365/364))*100 -> 10.74488 | R98: =+IF(F98<C98,IF(F98=D98,0,D98-F98),0) -> 0
A99: =A98+1 -> 523 | B99: =B98+7 -> 37454 | C99: 14000000000 | D99: 22985000000 | E99: =D99-C99 -> 8985000000 | F99: 14000000000 | G99: 12559852985 | H99: =F99-G99 -> 1440147015 | I99: =B99+J99+1 -> 37819 | J99: 364 | M99: 9.4 | N99: =G99/F99*100 -> 89.713236 | O99: =(100-N99)/100*(365/364)*100 -> 10.315025 | Q99: =((100-N99)/N99*(365/364))*100 -> 11.497774 | R99: =+IF(F99<C99,IF(F99=D99,0,D99-F99),0) -> 0
A100: =A99+1 -> 524 | B100: =B99+7 -> 37461 | C100: 14000000000 | D100: 27678400000 | E100: =D100-C100 -> 13678400000 | F100: 14000000000 | G100: 12492740554 | H100: =F100-G100 -> 1507259446 | I100: =B100+J100+1 -> 37826 | J100: 364 | M100: 10.2 | N100: =G100/F100*100 -> 89.233861 | O100: =(100-N100)/100*(365/364)*100 -> 10.795716 | Q100: =((100-N100)/N100*(365/364))*100 -> 12.098228 | R100: =+IF(F100<C100,IF(F100=D100,0,D100-F100),0) -> 0
A101: =A100+1 -> 525 | B101: =B100+7 -> 37468 | C101: 16000000000 | D101: 16000000000 | E101: =D101-C101 -> 0 | F101: 16000000000 | G101: 14146657197 | H101: =F101-G101 -> 1853342803 | I101: =B101+J101+1 -> 37833 | J101: 364 | M101: 10.712 | N101: =G101/F101*100 -> 88.416607 | O101: =(100-N101)/100*(365/364)*100 -> 11.615215 | Q101: =((100-N101)/N101*(365/364))*100 -> 13.136916 | R101: =+IF(F101<C101,IF(F101=D101,0,D101-F101),0) -> 0
R102: =+IF(F102<C102,IF(F102=D102,0,D102-F102),0) -> 0
...

Sheet Bonds
A2: Auction No | B2: Reopening No | C2: Tenor Years | D2: Duration | E2: Issue date | F2: Amount offered in Auction | G2: Total bids (Competitive & Uncompetitive) | H2: Over/(Under) Subscribed | I2: Face Value of Issues | J2: Cost Value | K2: Interest due | L2: Date due | M2: Weighted Average Price | N2: Yield to Maturity | O2: Bid to cover Ratio | P2: WAP Range (Rejected Amount) | Q2: YTM Range | R2: Coupon
A3: Q000005-T-BOND-2-14-JAN-2006 | B3: 1 | C3: =(L3-E3)/364 -> 1.6208791 | E3: 38141 | F3: 30000000000 | G3: 44187500000 | H3: =G3-F3 -> 14187500000 | I3: 29999700000 | J3: 29641204301 | K3: =I3-J3 -> 358495699 | L3: 38731 | M3: 98.805 | N3: 13.558 | O3: =+G3/F3 -> 1.4729167 | S3: 2004 | T3: 1.6208791
A4: Q000005-T-BOND-3-22-FEB-2007 | B4: 2 | C4: =(L4-E4)/364 -> 2.6950549 | E4: 38154 | F4: 30000000000 | G4: 44811400000 | H4: =G4-F4 -> 14811400000 | I4: 29999900000 | J4: 27792597023 | K4: =I4-J4 -> 2207302977 | L4: 39135 | M4: 92.642 | N4: 15.127 | O4: =+G4/F4 -> 1.4937133 | S4: 2005 | T4: 2.6950549
A5: Q000005-T-BOND-3-22-FEB-2007 | B5: 3 | C5: =(L5-E5)/364 -> 2.6181319 | E5: 38182 | F5: 30000000000 | G5: 32123100000 | H5: =G5-F5 -> 2123100000 | I5: 29999600000 | J5: 27144360632 | K5: =I5-J5 -> 2855239368 | L5: 39135 | M5: 90.482 | N5: 16.802 | O5: =+G5/F5 -> 1.07077 | S5: 2006 | T5: 2.6181319
A6: Q000005-T-BOND-2-29-JUN-2006 | B6: 4 | C6: =(L6-E6)/364 -> 1.8873626 | E6: 38210 | F6: 30000000000 | G6: 40000900000 | H6: =G6-F6 -> 10000900000 | I6: 29999700000 | J6: 27891858679 | K6: =I6-J6 -> 2107841321 | L6: 38897 | M6: 92.974 | N6: 15.105 | O6: =+G6/F6 -> 1.3333633 | S6: 2007 | T6: 1.8873626
A7: Q000005-T-BOND-2-29-JUN-2006 | B7: 5 | C7: =(L7-E7)/364 -> 1.8104396 | E7: 38238 | F7: 30000000000 | G7: 50525800000 | H7: =G7-F7 -> 20525800000 | I7: 29999900000 | J7: 28260410231 | K7: =I7-J7 -> 1739489769 | L7: 38897 | M7: 94.202 | N7: 15.006 | O7: =+G7/F7 -> 1.6841933 | S7: 2008 | T7: 1.8104396
A8: Q000005-T-BOND-3-04-OCT-2007 | B8: 6 | C8: =(L8-E8)/364 -> 2.9258242 | E8: 38294 | F8: 30000000000 | G8: 33431100000 | H8: =G8-F8 -> 3431100000 | I8: 30000000000 | J8: 26352149388 | K8: =I8-J8 -> 3647850612 | L8: 39359 | M8: 87.84 | N8: 15.935 | O8: =+G8/F8 -> 1.11437 | S8: 2009 | T8: 2.9258242
A9: Q000005-T-BOND-5-19-MAR-2009 | B9: 7 | C9: 5 | E9: 38308 | F9: 20000000000 | G9: 32226600000 | H9: =G9-F9 -> 12226600000 | I9: 20000000000 | J9: 17092590193 | K9: =I9-J9 -> 2907409807 | L9: 39891 | M9: 85.463 | N9: 16.039 | O9: =+G9/F9 -> 1.61133 | S9: 2010 | T9: 5
A10: Q000005-T-BOND-3-04-OCT-2007 | B10: 8 | C10: =(L10-E10)/364 -> 2.8489011 | E10: 38322 | F10: 30000000000 | G10: 35650000000 | H10: =G10-F10 -> 5650000000 | I10: 30000000000 | J10: 25709454845 | K10: =I10-J10 -> 4290545155 | L10: 39359 | M10: 85.698 | N10: 17.554 | O10: =+G10/F10 -> 1.1883333 | S10: 2011 | T10: 2.8489011
A11: Q000005-T-BOND-2-25-JAN-2007 | B11: 9 | C11: =(L11-E11)/364 -> 1.9258242 | E11: 38406 | F11: 35000000000 | G11: 45417400000 | H11: =G11-F11 -> 10417400000 | I11: 34999800000 | J11: 32797149766 | K11: =I11-J11 -> 2202650234 | L11: 39107 | M11: 93.707 | N11: 14.294 | O11: =+G11/F11 -> 1.29764 | S11: 2012 | T11: 1.9258242
A12: Q000005-T-BOND-2-25-JAN-2007 | B12: 10 | C12: =(L12-E12)/364 -> 1.8489011 | E12: 38434 | F12: 35000000000 | G12: 45846100000 | H12: =G12-F12 -> 10846100000 | I12: 34999700000 | J12: 33058510388 | K12: =I12-J12 -> 1941189612 | L12: 39107 | M12: 94.454 | N12: 14.463 | O12: =+G12/F12 -> 1.3098886 | S12: 2013 | T12: 1.8489011
A13: Q000005-T-BOND-3-17-APR-2008 | B13: 11 | C13: =(L13-E13)/364 -> 2.9258242 | E13: 38490 | F13: 20000000000 | G13: 25565600000 | H13: =G13-F13 -> 5565600000 | I13: 20000000000 | J13: 16861586220 | K13: =I13-J13 -> 3138413780 | L13: 39555 | M13: 84.308 | N13: 17.7 | O13: =+G13/F13 -> 1.27828 | S13: 2014 | T13: 3.4258242
A14: Q000005-T-BOND-3-24-JUL-2008 | B14: 12 | C14: =(L14-E14)/364 -> 2.9258242 | E14: 38588 | F14: 25000000000 | G14: 29625500000 | H14: =G14-F14 -> 4625500000 | I14: 24999900000 | J14: 22246296609 | K14: =I14-J14 -> 2753603391 | L14: 39653 | M14: 88.986 | N14: 15.405 | O14: =+G14/F14 -> 1.18502 | S14: 2015 | T14: 1.9642857
A15: Q000005-T-BOND-5-19-MAR-2009 | B15: 13 | C15: =(L15-E15)/364 -> 3.4258242 | E15: 38644 | F15: 20000000000 | G15: 42776100000 | H15: =G15-F15 -> 22776100000 | I15: 20000000000 | J15: 17887598581 | K15: =I15-J15 -> 2112401419 | L15: 39891 | M15: 89.438 | N15: 15.124 | O15: =+G15/F15 -> 2.138805 | S15: 2016 | T15: 4.5027473
A16: Q000005-T-BOND-3-18-SEP-2008 | B16: 14 | C16: =(L16-E16)/364 -> 2.8489011 | E16: 38672 | F16: 20000000000 | G16: 35295200000 | H16: =G16-F16 -> 15295200000 | I16: 19999900000 | J16: 18319926864 | K16: =I16-J16 -> 1679973136 | L16: 39709 | M16: 91.6 | N16: 14.645 | O16: =+G16/F16 -> 1.76476 | S16: 2017 | T16: 1.771978
A17: Q000005-T-BOND-2-29-NOV-2007 | B17: 15 | C17: =(L17-E17)/364 -> 1.9642857 | E17: 38700 | F17: 15000000000 | G17: 33052700000 | H17: =G17-F17 -> 18052700000 | I17: 14999900000 | J17: 14231485735 | K17: =I17-J17 -> 768414265 | L17: 39415 | M17: 94.877 | N17: 13.274 | O17: =+G17/F17 -> 2.2035133 | S17: 2018 | T17: 2.3873626
A18: 45220-T-BOND-3-05-MAR-09 | B18: 29-1 | C18: =(L18-E18)/364 -> 2.8489011 | E18: 38840 | F18: 20000000000 | G18: 44152500000 | H18: =G18-F18 -> 24152500000 | I18: 20000000000 | J18: 19085751172 | K18: =I18-J18 -> 914248828 | L18: 39877 | M18: 95.429 | N18: 12.884 | O18: =+G18/F18 -> 2.207625 | S18: 2019 | T18: 1.6181319
A19: 45220-T-BOND-3-25-JUN-09 | B19: 32 | C19: =(L19-E19)/364 -> 2.9258242 | E19: 38924 | F19: 20000000000 | G19: 19818900000 | H19: =G19-F19 -> -181100000 | I19: 18318900000 | J19: 16860473010 | K19: =I19-J19 -> 1458426990 | L19: 39989 | M19: 92.039 | N19: 13.99 | O19: =+G19/F19 -> 0.990945 | S19: 2020 | T19: 1.5796703
A20: 45220-T-BOND-5-26-MAY-11 | B20: 31 | C20: =(L20-E20)/364 -> 4.5027473 | E20: 39050 | F20: 20000000000 | G20: 39227900000 | H20: =G20-F20 -> 19227900000 | I20: 20000000000 | J20: 17990754900 | K20: =I20-J20 -> 2009245100 | L20: 40689 | M20: 89.954 | N20: 13.822 | O20: =+G20/F20 -> 1.961395 | S20: 2021 | T20: 4.771978
A21: 45220-T-BOND-2-16-OCT-08 | B21: 35 | C21: =(L21-E21)/364 -> 1.771978 | E21: 39092 | F21: 30000000000 | G21: 48342200000 | H21: =G21-F21 -> 18342200000 | I21: 30000000000 | J21: 28865996370 | K21: =I21-J21 -> 1134003630 | L21: 39737 | M21: 96.22 | N21: 13.975 | O21: =+G21/F21 -> 1.6114067 | S21: 2022 | T21: 9.8489011
A22: 45220-T-BOND-2-11-DEC-08 | B22: 38 | C22: =(L22-E22)/364 -> 1.8489011 | E22: 39120 | F22: 30000000000 | G22: 54302300000 | H22: =G22-F22 -> 24302300000 | I22: 30000000000 | J22: 29022763940 | K22: =I22-J22 -> 977236060 | L22: 39793 | M22: 96.743 | N22: 12.984 | O22: =+G22/F22 -> 1.8100767 | T22: 2.1565934
A23: 45220-T-BOND-3-12-NOV-09 | B23: 36 | C23: =(L23-E23)/364 -> 2.6950549 | E23: 39148 | F23: 30000000000 | G23: 51137000000 | H23: =G23-F23 -> 21137000000 | I23: 30000000000 | J23: 29568252440 | K23: =I23-J23 -> 431747560 | L23: 40129 | M23: 98.561 | N23: 12.289 | O23: =+G23/F23 -> 1.7045667 | T23: 2.9642857
A24: 45220-T-BOND-3-20-AUG-09 | B24: 33 | C24: =(L24-E24)/364 -> 2.3873626 | E24: 39176 | F24: 30000000000 | G24: 56671300000 | H24: =G24-F24 -> 26671300000 | I24: 30000000000 | J24: 28860376065 | K24: =I24-J24 -> 1139623935 | L24: 40045 | M24: 96.201 | N24: 12.7232 | O24: =+G24/F24 -> 1.8890433 | T24: 1.6950549
A25: 45220-T-BOND-3-29-APR-10 | B25: 39 | C25: =(L25-E25)/364 -> 2.9258242 | E25: 39232 | F25: 30000000000 | G25: 31191600000 | H25: =G25-F25 -> 1191600000 | I25: 30000000000 | J25: 28028238736 | K25: =I25-J25 -> 1971761264 | L25: 40297 | M25: 93.427 | N25: 13.366 | O25: =+G25/F25 -> 1.03972 | T25: 2.0027473
A26: 45220-T-BOND-3-05-FEB-09 | B26: 28 | C26: =(L26-E26)/364 -> 1.6181319 | E26: 39260 | F26: 20000000000 | G26: 121776100000 | H26: =G26-F26 -> 101776100000 | I26: 20000000000 | J26: 19866524133 | K26: =I26-J26 -> 133475867 | L26: 39849 | M26: 99.333 | N26: 13.5 | O26: =+G26/F26 -> 6.088805 | T26: 4.5412088
A27: 45220-T-BOND-2-07-JAN-10 | B27: 51 | C27: =(L27-E27)/364 -> 1.5796703 | E27: 39610 | F27: 40000000000 | G27: 54777500000 | H27: =G27-F27 -> 14777500000 | I27: 40000000000 | J27: 39079084200 | K27: =I27-J27 -> 920915800 | L27: 40185 | M27: 97.698 | N27: 14.778 | O27: =+G27/F27 -> 1.3694375 | T27: 2.771978
A28: 45220-T-BOND-3-24-MAY-12 | B28: 68 | C28: =(L28-E28)/364 -> 2.9258242 | E28: 39988 | F28: 50000000000 | G28: 137668900000 | H28: =G28-F28 -> 87668900000 | I28: 50000000000 | J28: 45771498442 | K28: =I28-J28 -> 4228501558 | L28: 41053 | M28: 91.543 | N28: 14.215 | O28: =+G28/F28 -> 2.753378 | T28: 8.1565934
A29: 45220-T-BOND-5-11-SEP-14 | B29: 71 | C29: =(L29-E29)/364 -> 4.771978 | E29: 40156 | F29: 40000000000 | G29: 188636800000 | H29: =G29-F29 -> 148636800000 | I29: 40000000000 | J29: 38293693556 | K29: =I29-J29 -> 1706306444 | L29: 41893 | M29: 95.734 | N29: 12.666 | O29: =+G29/F29 -> 4.71592 | T29: 5.0164835
A30: 45220-T-BOND-5-11-SEP-14 | B30: 71 | C30: =(L30-E30)/364 -> 4.771978 | E30: 40156 | F30: 40000000000 | G30: 188636800000 | H30: =G30-F30 -> 148636800000 | I30: 40000000000 | J30: 38293693556 | K30: =I30-J30 -> 1706306444 | L30: 41893 | M30: 95.734 | N30: 12.666 | O30: =+G30/F30 -> 4.71592 | T30: 3.010989
A31: 45220-T-BOND-10-23-JAN-20 | B31: 76 | C31: =(L31-E31)/364 -> 9.8489011 | E31: 40268 | F31: 50000000000 | G31: 131754300000 | H31: =G31-F31 -> 81754300000 | I31: 50000000000 | J31: 48700461950 | K31: =I31-J31 -> 1299538050 | L31: 43853 | M31: 97.401 | N31: 11.741 | O31: =+G31/F31 -> 2.635086 | T31: 4.8104396
A32: 45220-T-BOND-5-19-JUL-12 | B32: 42 | C32: =(L32-E32)/364 -> 2.1565934 | E32: 40324 | F32: 60000000000 | G32: 222444100000 | H32: =G32-F32 -> 162444100000 | I32: 60000000000 | J32: 64367522771 | K32: =I32-J32 -> -4367522771 | L32: 41109 | M32: 107.279 | N32: 8.886 | O32: =+G32/F32 -> 3.7074017 | T32: 3.0027473
A33: 45220-T-BOND-3-24-OCT-13 | B33: 87 | C33: =(L33-E33)/364 -> 2.9642857 | E33: 40492 | F33: 60000000000 | G33: 142521000000 | H33: =G33-F33 -> 82521000000 | I33: 60000000000 | J33: 58890301120 | K33: =I33-J33 -> 1109698880 | L33: 41571 | M33: 98.151 | N33: 11.156 | O33: =+G33/F33 -> 2.37535 | T33: 5.0027473
... A35: 45220-T-BOND-3-24-APR-14 | B35: 94 | C35: =(L35-E35)/364 -> 2.6181319 | E35: 40800 | F35: 40000000000 | G35: 164897900000 | H35: =G35-F35 -> 124897900000 | I35: 40000000000 | J35: 36771337303 | K35: =I35-J35 -> 3228662697 | L35: 41753 | M35: 91.928 | N35: 16.0366 | O35: =+G35/F35 -> 4.1224475 | T35: 8.6923077
A36: 45220-T-BOND-3-27-FEB-14 | B36: 92 | C36: =(L36-E36)/364 -> 2.0027473 | E36: 40968 | F36: 40000000000 | G36: 276834200000 | H36: =G36-F36 -> 236834200000 | I36: 40000000000 | J36: 36224979988 | K36: =I36-J36 -> 3775020012 | L36: 41697 | M36: 90.562 | N36: 15.946 | O36: =+G36/F36 -> 6.920855 | Q36: =+YEAR(E36) -> 2012 | T36: 15.002747
A37: 45220-T-BOND-5-08-SEP-16 | B37: 100 | C37: =(L37-E37)/364 -> 4.5412088 | E37: 40968 | F37: 60000000000 | G37: 300453400000 | H37: =G37-F37 -> 240453400000 | I37: 60000000000 | J37: 53087753923 | K37: =I37-J37 -> 6912246077 | L37: 42621 | M37: 88.48 | N37: 15.99 | O37: =+G37/F37 -> 5.0075567 | Q37: =+YEAR(E37) -> 2012 | T37: 10.002747
A38: 45220-T-BOND-5-26-FEB-15 | B38: 77 | C38: =(L38-E38)/364 -> 2.771978 | E38: 41052 | F38: 50000000000 | G38: 146956500000 | H38: =G38-F38 -> 96956500000 | I38: 50000000000 | J38: 46137984526 | K38: =I38-J38 -> 3862015474 | L38: 42061 | O38: =+G38/F38 -> 2.93913 | Q38: =+YEAR(E38) -> 2012 | T38: 14.771978
A39: 45220-T-BOND-2-22-MAY-14 | B39: 108 | C39: =(L39-E39)/364 -> 1.771978 | E39: 41136 | F39: 50000000000 | G39: 120104700000 | H39: =G39-F39 -> 70104700000 | I39: 50000000000 | J39: 48574189839 | K39: =I39-J39 -> 1425810161 | L39: 41781 | M39: 97.148 | N39: 13.344 | O39: =+G39/F39 -> 2.402094 | Q39: =+YEAR(E39) -> 2012 | T39: 4.6181319
A40: 45220-T-BOND-10-21-JAN-21 | B40: 91 | C40: =(L40-E40)/364 -> 8.1565934 | E40: 41248 | F40: 50000000000 | G40: 43120000000 | H40: =G40-F40 -> -6880000000 | I40: 41579000000 | J40: 36171794302 | K40: =I40-J40 -> 5407205698 | L40: 44217 | M40: 86.995 | N40: 14.583 | O40: =+G40/F40 -> 0.8624 | Q40: =+YEAR(E40) -> 2012 | T40: 9.771978
A41: 45220-T-BOND-5-22-FEB-18 | B41: 120 | C41: =(L41-E41)/364 -> 5.0164835 | E41: 41327 | F41: 100000000000 | G41: 229016600000 | H41: =G41-F41 -> 129016600000 | I41: 100000000000 | J41: 90972488334 | K41: =I41-J41 -> 9027511666 | L41: 43153 | M41: 90.972 | N41: 13.984 | O41: =+G41/F41 -> 2.290166 | Q41: =+YEAR(E41) -> 2013 | T41: 14.541209
A42: 45220-T-BOND-3-21-APR-16 | B42: 122 | C42: =(L42-E42)/364 -> 3.010989 | E42: 41385 | F42: 100000000000 | G42: 268216300000 | H42: =G42-F42 -> 168216300000 | I42: 100000000000 | J42: 93178691704 | K42: =I42-J42 -> 6821308296 | L42: 42481 | M42: 93.179 | N42: 13.271 | O42: =+G42/F42 -> 2.682163 | Q42: =+YEAR(E42) -> 2013 | T42: 1.8461538
A43: 45220-T-BOND-3-21-APR-16 | B43: 122 | C43: =(L43-E43)/364 -> 2.9642857 | E43: 41402 | F43: 100000000000 | G43: 268216300000 | H43: =G43-F43 -> 168216300000 | I43: 100000000000 | J43: 93178691704 | K43: =I43-J43 -> 6821308296 | L43: 42481 | M43: 93.179 | N43: 13.271 | O43: =+G43/F43 -> 2.682163 | Q43: =+YEAR(E43) -> 2013 | T43: 15
A44: 45220-T-BOND-5-22-FEB-18 | B44: 120 | C44: =(L44-E44)/364 -> 4.8104396 | E44: 41402 | F44: 100000000000 | G44: 229016600000 | H44: =G44-F44 -> 129016600000 | I44: 100000000000 | J44: 90972488334 | K44: =I44-J44 -> 9027511666 | L44: 43153 | M44: 90.972 | N44: 13.984 | O44: =+G44/F44 -> 2.290166 | Q44: =+YEAR(E44) -> 2013 | T44: 2.0054945
A45: 45220-T-BOND-3-02-Jun-16 | B45: 127 | C45: =(L45-E45)/364 -> 3.0027473 | E45: 41430 | F45: 80000000000 | G45: 79378700000 | H45: -621300000 | I45: 79378700000 | J45: 70559588903 | K45: =I45-J45 -> 8819111097 | L45: 42523 | M45: 88.943 | N45: 14.958 | O45: =+G45/F45 -> 0.99223375 | Q45: =+YEAR(E45) -> 2013 | T45: 3.1565934
A46: 45220-T-BOND-5-31-may-18 | B46: 126 | C46: =(L46-E46)/364 -> 5.0027473 | E46: 41430 | F46: 80000000000 | G46: 119075300000 | H46: 39075300000 | I46: 80000000000 | J46: 68998738442 | K46: =I46-J46 -> 11001261558 | L46: 43251 | M46: 86.248 | N46: 14.732 | O46: =+G46/F46 -> 1.4884412 | Q46: =+YEAR(E46) -> 2013 | T46: 14.769231
A47: 45220-T-BOND-3-14-Jul-16 | B47: 128 | C47: =(L47-E47)/364 -> 3.0027473 | E47: 41472 | F47: 145000000000 | G47: 345095300000 | H47: 200095300000 | I47: 145000000000 | J47: 129976831124 | K47: =I47-J47 -> 15023168876 | L47: 42565 | M47: 89.639 | N47: 14.64 | O47: =+G47/F47 -> 2.3799676 | Q47: =+YEAR(E47) -> 2013 | T47: 10
A48: 45220-T-BOND-3-02-Jun-16 | B48: 127 | C48: =(L48-E48)/364 -> 2.8104396 | E48: 41500 | F48: 80000000000 | G48: 168800100000 | H48: 88800100000 | I48: 80000000000 | J48: 74738812092 | K48: =I48-J48 -> 5261187908 | L48: 42523 | M48: 93.424 | N48: 14.019 | O48: =+G48/F48 -> 2.1100012 | Q48: =+YEAR(E48) -> 2013 | T48: 2
A49: 45220-T-BOND-10-Sep-15 | C49: =(L49-E49)/364 -> 2.0027473 | E49: 41528 | F49: 70000000000 | G49: 238029000000 | H49: 168029000000 | I49: 70000000000 | J49: 66520360904 | K49: =I49-J49 -> 3479639096 | L49: 42257 | M49: 94.968 | N49: 12.899 | O49: =+G49/F49 -> 3.4004143 | Q49: =+YEAR(E49) -> 2013 | T49: 14.538462
A50: 45220-T-BOND-6-Sep-18 | C50: =(L50-E50)/364 -> 5.0027473 | E50: 41528 | F50: 75000000000 | G50: 201890800000 | H50: 126890800000 | I50: 75000000000 | J50: 66742342118 | K50: =I50-J50 -> 8257657882 | L50: 43349 | M50: 88.99 | N50: 13.876 | O50: =+G50/F50 -> 2.6918773 | Q50: =+YEAR(E50) -> 2013 | T50: 1.9230769
A51: 45220-T-BOND-9-Jun-22 | C51: =(L51-E51)/364 -> 8.6923077 | E51: 41557 | F51: 70000000000 | G51: 152770600000 | H51: 82770600000 | I51: 70000000000 | J51: 50196387386 | K51: =I51-J51 -> 19803612614 | L51: 44721 | M51: 83.531 | N51: 15.177 | O51: =+G51/F51 -> 2.1824371 | Q51: =+YEAR(E51) -> 2013 | T51: 9.7692308
A52: 45220-T-BOND-5-Nov-15 | C52: =(L52-E52)/364 -> 2.0027473 | E52: 41584 | F52: 80000000000 | G52: 136421600000 | H52: 96421600000 | I52: 40000000000 | J52: 39377899250 | K52: =I52-J52 -> 622100750 | L52: 42313 | M52: 98.44511 | N52: 14.17 | O52: =+G52/F52 -> 1.70527 | Q52: =+YEAR(E52) -> 2013 | T52: 1.7692308
A53: 45220-T-BOND-1-Nov-18 | C53: =(L53-E53)/364 -> 5.0027473 | E53: 41584 | F53: 80000000000 | G53: 198308600000 | H53: 118308600000 | I53: 80000000000 | J53: 79610440553 | K53: =I53-J53 -> 389559447 | L53: 43405 | M53: 99.513 | N53: 14.766 | O53: =+G53/F53 -> 2.4788575 | Q53: =+YEAR(E53) -> 2013 | T53: 1.6923077
A54: 45220-T-BOND-1-Dec-16 | B54: 127 | C54: =(L54-E54)/364 -> 15.002747 | E54: 41612 | F54: 80000000000 | G54: 226169600000 | H54: 88800100000 | I54: 40674000000 | J54: 40921285520 | K54: =I54-J54 -> -247285520 | L54: 47073 | M54: 93.424 | N54: 93.424 | O54: =+G54/F54 -> 2.82712 | Q54: =+YEAR(E54) -> 2013 | T54: 4.7692308
A55: 45220-T-BOND-1-Dec-16 | C55: =(L55-E55)/364 -> 2.8489011 | E55: 41668 | F55: 70000000000 | G55: 181378500000 | H55: 111378500000 | I55: 70000000000 | J55: 73007441330 | K55: =I55-J55 -> -3007441330 | L55: 42705 | M55: 104.2963 | N55: 13.186 | O55: =+G55/F55 -> 2.5911214 | Q55: =+YEAR(E55) -> 2014 | T55: 3.3104396
A56: 45220-T-BOND-18-Jan-24 | C56: =(L56-E56)/364 -> 10.002747 | E56: 41668 | F56: 60000000000 | G56: 235378800000 | H56: 175378800000 | I56: 60000000000 | J56: 6.0146006e+10 | K56: =I56-J56 -> -1.4600584e+08 | L56: 45309 | M56: 100.243 | N56: 13.954 | O56: =+G56/F56 -> 3.92298 | Q56: =+YEAR(E56) -> 2014 | T56: 9.5412088
A57: 45220-T-BOND-25-Feb-16 | C57: =(L57-E57)/364 -> 2.0027473 | E57: 41696 | F57: 100000000000 | G57: 178299300000 | H57: 78299300000 | I57: 100000000000 | J57: 100056520598 | K57: =I57-J57 -> -56520598 | L57: 42425 | M57: 100.057 | N57: 13.342 | O57: =+G57/F57 -> 1.782993 | Q57: =+YEAR(E57) -> 2014 | T57: 0.0027472527
A58: 45220-T-BOND-16-Nov-28 | C58: =(L58-E58)/364 -> 14.771978 | E58: 41696 | F58: 70000000000 | G58: 131217800000 | H58: 61217800000 | I58: 70000000000 | J58: 72423156313 | K58: =I58-J58 -> -2423156313 | L58: 47073 | M58: 103.462 | N58: 15.248 | O58: =+G58/F58 -> 1.87454 | Q58: =+YEAR(E58) -> 2014 | T58: 9.3076923
A59: 45220-T-BOND-24-Mar-16 | C59: =(L59-E59)/364 -> 2.0027473 | E59: 41724 | F59: 90000000000 | G59: 116149500000 | H59: 43250000000 | I59: 72899500000 | J59: 73107226294 | K59: =I59-J59 -> -207726294 | L59: 42453 | M59: 100.285 | N59: 13.835 | O59: =+G59/F59 -> 1.29055 | Q59: =+YEAR(E59) -> 2014 | T59: 4.6153846
A60: 45220-T-BOND-1-Nov-18 | C60: =(L60-E60)/364 -> 4.6181319 | E60: 41724 | F60: 90000000000 | G60: 201211200000 | H60: 94110700000 | I60: 107100500000 | J60: 115056631425 | K60: =I60-J60 -> -7956131425 | L60: 43405 | M60: 107.4286 | N60: 14.067 | O60: =+G60/F60 -> 2.23568 | Q60: =+YEAR(E60) -> 2014 | T60: 3
A61: 45220-T-BOND-1-Dec-16 | C61: =(L61-E61)/364 -> 2.6181319 | E61: 41752 | F61: 80000000000 | G61: 238069800000 | H61: 158069800000 | I61: 80000000000 | J61: 85345966053 | K61: =I61-J61 -> -5345966053 | L61: 42705 | M61: 106.682 | N61: 13.523 | O61: =+G61/F61 -> 2.9758725 | Q61: =+YEAR(E61) -> 2014 | T61: 2.6923077
A62: 45220-T-BOND-18-Jan-24 | C62: =(L62-E62)/364 -> 9.771978 | E62: 41752 | F62: 90000000000 | G62: 176461700000 | H62: 86461700000 | I62: 90000000000 | J62: 93026892521 | K62: =I62-J62 -> -3026892521 | L62: 45309 | M62: 103.363 | N62: 13.964 | O62: =+G62/F62 -> 1.9606856 | Q62: =+YEAR(E62) -> 2014 | T62: 9.5384615
A63: 45220-T-BOND-19-May-16 | C63: =(L63-E63)/364 -> 2.0027473 | E63: 41780 | F63: 100000000000 | G63: 253931900000 | H63: 153931900000 | I63: 100000000000 | J63: 100038195500 | K63: =I63-J63 -> -38195500 | L63: 42509 | M63: 100.038 | N63: 12.853 | O63: =+G63/F63 -> 2.539319 | Q63: =+YEAR(E63) -> 2014 | T63: 2.9230769
A64: 45220-T-BOND-16-Nov-28 | C64: =(L64-E64)/364 -> 14.541209 | E64: 41780 | F64: 70000000000 | G64: 156586800000 | H64: 86586800000 | I64: 70000000000 | J64: 78840177520 | K64: =I64-J64 -> -8840177520 | L64: 47073 | M64: 112.629 | N64: 14.322 | O64: =+G64/F64 -> 2.2369543 | Q64: =+YEAR(E64) -> 2014 | T64: 2.2335165
A65: 45220-T-BOND-19-MAY-16 | C65: =(L65-E65)/364 -> 1.9258242 | E65: 41808 | F65: 70000000000 | G65: 110480300000 | H65: 40480300000 | I65: 70000000000 | J65: 70772667399 | K65: =I65-J65 -> -772667399 | L65: 42509 | M65: 101.104 | N65: 12.791 | O65: =+G65/F65 -> 1.57829 | Q65: =+YEAR(E65) -> 2014 | T65: 14.31044
A66: 45220-T-BOND-13-JUN-19 | C66: =(L66-E66)/364 -> 5.0027473 | E66: 41808 | F66: 100000000000 | G66: 148266400000 | H66: 49500000000 | I66: 98766400000 | J66: 98713734808 | K66: =I66-J66 -> 52665192 | L66: 43629 | M66: 99.947 | N66: 13.765 | O66: =+G66/F66 -> 1.482664 | Q66: =+YEAR(E66) -> 2014 | T66: 2.0796703
... A70: TBOND-10YR-14.000% 01-AUG-2024 | C70: =(L70-E70)/364 -> 10.002747 | E70: 41864 | F70: 120000000000 | G70: 185415000000 | H70: 65415000000 | I70: 120000000000 | J70: 120300478530 | K70: =I70-J70 -> -300478530 | L70: 45505 | M70: 100.25 | N70: 13.953 | O70: =+G70/F70 -> 1.545125 | Q70: =+YEAR(E70) -> 2014 | T70: 2.2307692
A71: 2 YEAR 14-JUL-2016 | C71: =(L71-E71)/364 -> 1.8489011 | E71: 41892 | F71: 100000000000 | G71: 108673900000 | H71: =+G71-F71 -> 8673900000 | I71: 100000000000 | J71: 100826559061 | K71: =I71-J71 -> -826559061 | L71: 42565 | M71: 100.827 | N71: 13.574 | O71: =+G71/F71 -> 1.086739 | Q71: =+YEAR(E71) -> 2014 | T71: 4.6923077
A72: 2 YEAR 14-JUL-2016 | C72: =(L72-E72)/364 -> 1.8461538 | E72: 41893 | F72: 100000000000 | G72: 108673900000 | H72: 8673900000 | I72: 100000000000 | J72: 100826559061 | K72: =I72-J72 -> -826559061 | L72: 42565 | M72: 100.827 | N72: 13.574 | O72: =+G72/F72 -> 1.086739 | Q72: =+YEAR(E72) -> 2014 | T72: 2.0769231
A73: 15 YEAR 23-AUG-2019 | C73: =(L73-E73)/364 -> 15 | E73: 41893 | F73: 80000000000 | G73: 109723400000 | H73: 29723400000 | I73: 80000000000 | J73: 80222151430 | K73: =I73-J73 -> -222151430 | L73: 47353 | M73: 100.278 | N73: 14.205 | O73: =+G73/F73 -> 1.3715425 | Q73: =+YEAR(E73) -> 2014 | T73: 4.5384615
A74: 13.750% 07 Oct 2016 | C74: =(L74-E74)/364 -> 2.0054945 | E74: 41920 | F74: 60000000000 | G74: 72966300000 | H74: =+G74-F74 -> 12966300000 | I74: 60000000000 | J74: 60046569102 | K74: =I74-J74 -> -46569102 | L74: 42650 | M74: 100.078 | N74: 13.704 | O74: =+G74/F74 -> 1.216105 | Q74: =+YEAR(E74) -> 2014 | T74: 3.0769231
A75: 13.750% 11-JUL-2019 | C75: =(L75-E75)/364 -> 4.771978 | E75: 41920 | F75: 120000000000 | G75: 85046300000 | H75: =+G75-F75 -> -34953700000 | I75: 58046300000 | J75: 5.9511357e+10 | K75: =I75-J75 -> -1.4650569e+09 | L75: 43657 | M75: 102.524 | N75: 13.935 | O75: =+G75/F75 -> 0.70871917 | Q75: =+YEAR(E75) -> 2014 | T75: 9.8461538
A76: 10.750% 28-DEC-2017 Re-open | C76: =(L76-E76)/364 -> 3.1565934 | E76: 41948 | F76: 80000000000 | G76: 42394100000 | H76: =+G76-F76 -> -37605900000 | I76: 39144100000 | J76: 37076260648 | K76: =I76-J76 -> 2067839352 | L76: 43097 | M76: 94.717 | N76: 14.385 | O76: =+G76/F76 -> 0.52992625 | Q76: =+YEAR(E76) -> 2014 | T76: 4.8461538
A77: 14.000% 01-AUG-2024 Re-open | C77: =(L77-E77)/364 -> 9.771978 | E77: 41948 | F77: 100000000000 | G77: 104323100000 | H77: =+G77-F77 -> 4323100000 | I77: 100000000000 | J77: 99251461842 | K77: =I77-J77 -> 748538158 | L77: 45505 | M77: 99.251 | N77: 14.77 | O77: =+G77/F77 -> 1.043231 | Q77: =+YEAR(E77) -> 2014 | T77: 3.9230769
A78: 2YR 13.750% 07-OCT-2016 Re - open | C78: =(L78-E78)/364 -> 1.8489011 | E78: 41977 | F78: 90000000000 | G78: 102726800000 | H78: =G78-F78 -> 12726800000 | I78: 90000000000 | J78: 91014373792 | K78: =I78-J78 -> -1014373792 | L78: 42650 | M78: 101.127 | N78: 14.321 | O78: =+G78/F78 -> 1.1414089 | Q78: =+YEAR(E78) -> 2014 | T78: 11.153846
A79: 15YR 14.250% 23-AUG-2029 Re - open | C79: =(L79-E79)/364 -> 14.769231 | E79: 41977 | F79: 90000000000 | G79: 133951000000 | H79: =G79-F79 -> 43951000000 | I79: 90000000000 | J79: 84319230830 | K79: =I79-J79 -> 5680769170 | L79: 47353 | M79: 93.688 | N79: 15.946 | O79: =+G79/F79 -> 1.4883444 | Q79: =+YEAR(E79) -> 2014 | T79: 2.4615385
A80: 2YR 13.750% 07-OCT-2016 Re - open | C80: =(L80-E80)/364 -> 1.6950549 | E80: 42033 | F80: 80000000000 | G80: 65612100000 | H80: =G80-F80 -> -14387900000 | I80: 80000000000 | J80: 35430077098 | K80: =I80-J80 -> 44569922902 | L80: 42650 | M80: 100.654 | N80: 16.175 | O80: =+G80/F80 -> 0.82015125 | Q80: =+YEAR(E80) -> 2015 | T80: 3.7692308
A81: 10YR 17.000% 16-JAN-2025 | C81: =(L81-E81)/364 -> 10 | E81: 42033 | F81: 100000000000 | G81: 170215000000 | H81: =G81-F81 -> 70215000000 | I81: 100000000000 | J81: 144872227600 | K81: =I81-J81 -> -44872227600 | L81: 45673 | M81: 99.912 | N81: 17.019 | O81: =+G81/F81 -> 1.70215 | Q81: =+YEAR(E81) -> 2015 | T81: 11
A82: 2YR 16.750% 23-Feb-2017 | C82: =(L82-E82)/364 -> 2 | E82: 42061 | F82: 80000000000 | G82: 127598900000 | H82: =G82-F82 -> 47598900000 | I82: 80000000000 | J82: 80087918262 | K82: =I82-J82 -> -87918262 | L82: 42789 | M82: 100.11 | N82: 16.684 | O82: =+G82/F82 -> 1.5949863 | Q82: =+YEAR(E82) -> 2015 | T82: 2.3076923
A83: 15YR 14.250% 23-AUG-2029 Re - open | C83: =(L83-E83)/364 -> 14.538462 | E83: 42061 | F83: 100000000000 | G83: 248283200000 | H83: =G83-F83 -> 148283200000 | I83: 110000000000 | J83: 99022320864 | K83: =I83-J83 -> 10977679136 | L83: 47353 | M83: 90.02 | N83: 17.407 | O83: =+G83/F83 -> 2.482832 | Q83: =+YEAR(E83) -> 2015 | T83: 5.3076923
A84: 2YR 16.750% 23-FEB-2017 Re-open | C84: =(L84-E84)/364 -> 1.9230769 | E84: 42089 | F84: 60000000000 | G84: 47367200000 | H84: -12632800000 | I84: 18227100000 | J84: 18467035436 | K84: =I84-J84 -> -239935436 | L84: 42789 | M84: 101.316 | N84: 16.705 | O84: 0.78945333 | Q84: =+YEAR(E84) -> 2015 | T84: 14.307692
A85: 5YR 17.00% 19-MAR-2020 | C85: =(L85-E85)/364 -> 5 | E85: 42089 | F85: 120000000000 | G85: 198505000000 | H85: 78505000000 | I85: 161000000000 | J85: 161154838480 | K85: =I85-J85 -> -154838480 | L85: 43909 | M85: 100.096 | N85: 16.971 | O85: 1.6542083 | Q85: =+YEAR(E85) -> 2015 | T85: 2.1538462
A86: 2YR 16.750% 23-FEB-2017 Re open | C86: =(L86-E86)/364 -> 1.8461538 | E86: 42117 | F86: 60000000000 | G86: 487273000000 | H86: -11272700000 | I86: 16222300000 | J86: 16563350310 | K86: =I86-J86 -> -341050310 | L86: 42789 | M86: 102.102 | N86: 16.705 | O86: 0.812 | Q86: =+YEAR(E86) -> 2015 | T86: 5.239011
A87: 10YR 17.00 16-JAN-2025 Re open | C87: =(L87-E87)/364 -> 9.7692308 | E87: 42117 | F87: 120000000000 | G87: 2088370000000 | H87: 88837000000 | I87: 163000000000 | J87: 164081269620 | K87: =I87-J87 -> -1081269620 | L87: 45673 | M87: 100.663 | N87: 17.693 | O87: 1.74 | Q87: =+YEAR(E87) -> 2015 | T87: 3.4615385
